Workbook

Sheet 20251125 Ranked by Tower, MM
A1: ItemID | B1: Item | D1: Mastered | E1: Grand Mastered | F1: Mega Mastered | G1: King's Rating April 2023* | H1: ClientCoin Rating 2024 | I1: Tower Req | J1: Score* | L1: Fish? | M1: Craft? | N1: Explore? | O1: Farm? | P1: Cook? | Q1: Event? | S1: Document is sorted by Tower Req then MM
A2: 21 | B2: Board | C2: =CONCATENATE("((",B2,"))") -> ((Board)) | D2: 87800 | E2: 62478 | F2: 30235 | G2: =VLOOKUP(B2,'Kings Ratings'!$A$2:$B$1000,2,false) -> 1 | H2: =if(G2=11,13,13-ROUNDDOWN(log(J2,4),0)) -> -1 | I2: =vlookup(A2,'202405 MM (Do Not Delete)'!$A$1:$G$1000,7,false) -> 201 | J2: =10000*F2+10*E2+D2 -> 303062580 | L2: =IFERROR(__xludf.DUMMYFUNCTION("if(REGEXMATCH(vlookup(B2,'Kings Ratings'!$A$2:$C$1000,3,false),""Fishing""),""Yes"","""")"),"") | M2: =IFERROR(__xludf.DUMMYFUNCTION("if(REGEXMATCH(vlookup(B2,'Kings Ratings'!$A$2:$C$1000,3,false),""Crafting""),""Yes"","""")"),"Yes") -> Yes | N2: =IFERROR(__xludf.DUMMYFUNCTION("if(REGEXMATCH(vlookup(B2,'Kings Ratings'!$A$2:$C$1000,3,false),""Exploring""),""Yes"","""")"),"") | O2: =IFERROR(__xludf.DUMMYFUNCTION("if(REGEXMATCH(vlookup(B2,'Kings Ratings'!$A$2:$C$1000,3,false),""Farming""),""Yes"","""")"),"") | P2: =IFERROR(__xludf.DUMMYFUNCTION("if(REGEXMATCH(vlookup(B2,'Kings Ratings'!$A$2:$C$1000,3,false),""Cooking""),""Yes"","""")"),"") | Q2: =IFERROR(__xludf.DUMMYFUNCTION("if(REGEXMATCH(vlookup(B2,'Kings Ratings'!$A$2:$C$1000,3,false),""Event""),""Yes"","""")"),"")
A3: 43 | B3: Mushroom | C3: =CONCATENATE("((",B3,"))") -> ((Mushroom)) | D3: 64993 | E3: 37722 | F3: 15495 | G3: =VLOOKUP(B3,'Kings Ratings'!$A$2:$B$1000,2,false) -> 1 | H3: =if(G3=11,13,13-ROUNDDOWN(log(J3,4),0)) -> 0 | I3: =vlookup(A3,'202405 MM (Do Not Delete)'!$A$1:$G$1000,7,false) -> 208 | J3: =10000*F3+10*E3+D3 -> 155392213 | L3: =IFERROR(__xludf.DUMMYFUNCTION("if(REGEXMATCH(vlookup(B3,'Kings Ratings'!$A$2:$C$1000,3,false),""Fishing""),""Yes"","""")"),"") | M3: =IFERROR(__xludf.DUMMYFUNCTION("if(REGEXMATCH(vlookup(B3,'Kings Ratings'!$A$2:$C$1000,3,false),""Crafting""),""Yes"","""")"),"") | N3: =IFERROR(__xludf.DUMMYFUNCTION("if(REGEXMATCH(vlookup(B3,'Kings Ratings'!$A$2:$C$1000,3,false),""Exploring""),""Yes"","""")"),"Yes") -> Yes | O3: =IFERROR(__xludf.DUMMYFUNCTION("if(REGEXMATCH(vlookup(B3,'Kings Ratings'!$A$2:$C$1000,3,false),""Farming""),""Yes"","""")"),"") | P3: =IFERROR(__xludf.DUMMYFUNCTION("if(REGEXMATCH(vlookup(B3,'Kings Ratings'!$A$2:$C$1000,3,false),""Cooking""),""Yes"","""")"),"") | Q3: =IFERROR(__xludf.DUMMYFUNCTION("if(REGEXMATCH(vlookup(B3,'Kings Ratings'!$A$2:$C$1000,3,false),""Event""),""Yes"","""")"),"") | S3: Score showcases difficulty
A4: 95 | B4: Iron Ring | C4: =CONCATENATE("((",B4,"))") -> ((Iron Ring)) | D4: 61712 | E4: 39090 | F4: 16767 | G4: =VLOOKUP(B4,'Kings Ratings'!$A$2:$B$1000,2,false) -> 1 | H4: =if(G4=11,13,13-ROUNDDOWN(log(J4,4),0)) -> 0 | I4: =vlookup(A4,'202405 MM (Do Not Delete)'!$A$1:$G$1000,7,false) -> 203 | J4: =10000*F4+10*E4+D4 -> 168122612 | L4: =IFERROR(__xludf.DUMMYFUNCTION("if(REGEXMATCH(vlookup(B4,'Kings Ratings'!$A$2:$C$1000,3,false),""Fishing""),""Yes"","""")"),"") | M4: =IFERROR(__xludf.DUMMYFUNCTION("if(REGEXMATCH(vlookup(B4,'Kings Ratings'!$A$2:$C$1000,3,false),""Crafting""),""Yes"","""")"),"Yes") -> Yes | N4: =IFERROR(__xludf.DUMMYFUNCTION("if(REGEXMATCH(vlookup(B4,'Kings Ratings'!$A$2:$C$1000,3,false),""Exploring""),""Yes"","""")"),"") | O4: =IFERROR(__xludf.DUMMYFUNCTION("if(REGEXMATCH(vlookup(B4,'Kings Ratings'!$A$2:$C$1000,3,false),""Farming""),""Yes"","""")"),"") | P4: =IFERROR(__xludf.DUMMYFUNCTION("if(REGEXMATCH(vlookup(B4,'Kings Ratings'!$A$2:$C$1000,3,false),""Cooking""),""Yes"","""")"),"") | Q4: =IFERROR(__xludf.DUMMYFUNCTION("if(REGEXMATCH(vlookup(B4,'Kings Ratings'!$A$2:$C$1000,3,false),""Event""),""Yes"","""")"),"") | S4: Score is 10000*MM + 10*GM + M
A5: 76 | B5: Unpolished Shimmer Stone | C5: =CONCATENATE("((",B5,"))") -> ((Unpolished Shimmer Stone)) | D5: 60495 | E5: 31241 | F5: 12251 | G5: =VLOOKUP(B5,'Kings Ratings'!$A$2:$B$1000,2,false) -> 1 | H5: =if(G5=11,13,13-ROUNDDOWN(log(J5,4),0)) -> 0 | I5: =vlookup(A5,'202405 MM (Do Not Delete)'!$A$1:$G$1000,7,false) -> 259 | J5: =10000*F5+10*E5+D5 -> 122882905 | L5: =IFERROR(__xludf.DUMMYFUNCTION("if(REGEXMATCH(vlookup(B5,'Kings Ratings'!$A$2:$C$1000,3,false),""Fishing""),""Yes"","""")"),"") | M5: =IFERROR(__xludf.DUMMYFUNCTION("if(REGEXMATCH(vlookup(B5,'Kings Ratings'!$A$2:$C$1000,3,false),""Crafting""),""Yes"","""")"),"") | N5: =IFERROR(__xludf.DUMMYFUNCTION("if(REGEXMATCH(vlookup(B5,'Kings Ratings'!$A$2:$C$1000,3,false),""Exploring""),""Yes"","""")"),"Yes") -> Yes | O5: =IFERROR(__xludf.DUMMYFUNCTION("if(REGEXMATCH(vlookup(B5,'Kings Ratings'!$A$2:$C$1000,3,false),""Farming""),""Yes"","""")"),"") | P5: =IFERROR(__xludf.DUMMYFUNCTION("if(REGEXMATCH(vlookup(B5,'Kings Ratings'!$A$2:$C$1000,3,false),""Cooking""),""Yes"","""")"),"") | Q5: =IFERROR(__xludf.DUMMYFUNCTION("if(REGEXMATCH(vlookup(B5,'Kings Ratings'!$A$2:$C$1000,3,false),""Event""),""Yes"","""")"),"") | S5: The lower the score, the harder
A6: 163 | B6: Twine | C6: =CONCATENATE("((",B6,"))") -> ((Twine)) | D6: 59720 | E6: 40498 | F6: 20388 | G6: =VLOOKUP(B6,'Kings Ratings'!$A$2:$B$1000,2,false) -> 1 | H6: =if(G6=11,13,13-ROUNDDOWN(log(J6,4),0)) -> 0 | I6: =vlookup(A6,'202405 MM (Do Not Delete)'!$A$1:$G$1000,7,false) -> 202 | J6: =10000*F6+10*E6+D6 -> 204344700 | L6: =IFERROR(__xludf.DUMMYFUNCTION("if(REGEXMATCH(vlookup(B6,'Kings Ratings'!$A$2:$C$1000,3,false),""Fishing""),""x"","""")"),"") | M6: =IFERROR(__xludf.DUMMYFUNCTION("if(REGEXMATCH(vlookup(B6,'Kings Ratings'!$A$2:$C$1000,3,false),""Crafting""),""Yes"","""")"),"Yes") -> Yes | N6: =IFERROR(__xludf.DUMMYFUNCTION("if(REGEXMATCH(vlookup(B6,'Kings Ratings'!$A$2:$C$1000,3,false),""Exploring""),""Yes"","""")"),"") | O6: =IFERROR(__xludf.DUMMYFUNCTION("if(REGEXMATCH(vlookup(B6,'Kings Ratings'!$A$2:$C$1000,3,false),""Farming""),""Yes"","""")"),"") | P6: =IFERROR(__xludf.DUMMYFUNCTION("if(REGEXMATCH(vlookup(B6,'Kings Ratings'!$A$2:$C$1000,3,false),""Cooking""),""Yes"","""")"),"") | Q6: =IFERROR(__xludf.DUMMYFUNCTION("if(REGEXMATCH(vlookup(B6,'Kings Ratings'!$A$2:$C$1000,3,false),""Event""),""Yes"","""")"),"") | S6: This is as based on how other people have gone after
A7: 78 | B7: Glass Orb | C7: =CONCATENATE("((",B7,"))") -> ((Glass Orb)) | D7: 58571 | E7: 28809 | F7: 11011 | G7: =VLOOKUP(B7,'Kings Ratings'!$A$2:$B$1000,2,false) -> 1 | H7: =if(G7=11,13,13-ROUNDDOWN(log(J7,4),0)) -> 0 | I7: =vlookup(A7,'202405 MM (Do Not Delete)'!$A$1:$G$1000,7,false) -> 265 | J7: =10000*F7+10*E7+D7 -> 110456661 | L7: =IFERROR(__xludf.DUMMYFUNCTION("if(REGEXMATCH(vlookup(B7,'Kings Ratings'!$A$2:$C$1000,3,false),""Fishing""),""Yes"","""")"),"") | M7: =IFERROR(__xludf.DUMMYFUNCTION("if(REGEXMATCH(vlookup(B7,'Kings Ratings'!$A$2:$C$1000,3,false),""Crafting""),""Yes"","""")"),"Yes") -> Yes | N7: =IFERROR(__xludf.DUMMYFUNCTION("if(REGEXMATCH(vlookup(B7,'Kings Ratings'!$A$2:$C$1000,3,false),""Exploring""),""Yes"","""")"),"") | O7: =IFERROR(__xludf.DUMMYFUNCTION("if(REGEXMATCH(vlookup(B7,'Kings Ratings'!$A$2:$C$1000,3,false),""Farming""),""Yes"","""")"),"") | P7: =IFERROR(__xludf.DUMMYFUNCTION("if(REGEXMATCH(vlookup(B7,'Kings Ratings'!$A$2:$C$1000,3,false),""Cooking""),""Yes"","""")"),"") | Q7: =IFERROR(__xludf.DUMMYFUNCTION("if(REGEXMATCH(vlookup(B7,'Kings Ratings'!$A$2:$C$1000,3,false),""Event""),""Yes"","""")"),"")
A8: 139 | B8: Skipjack | C8: =CONCATENATE("((",B8,"))") -> ((Skipjack)) | D8: 56454 | E8: 30475 | F8: 15776 | G8: =VLOOKUP(B8,'Kings Ratings'!$A$2:$B$1000,2,false) -> 1 | H8: =if(G8=11,13,13-ROUNDDOWN(log(J8,4),0)) -> 0 | I8: =vlookup(A8,'202405 MM (Do Not Delete)'!$A$1:$G$1000,7,false) -> 204 | J8: =10000*F8+10*E8+D8 -> 158121204 | L8: =IFERROR(__xludf.DUMMYFUNCTION("if(REGEXMATCH(vlookup(B8,'Kings Ratings'!$A$2:$C$1000,3,false),""Fishing""),""Yes"","""")"),"Yes") -> Yes | M8: =IFERROR(__xludf.DUMMYFUNCTION("if(REGEXMATCH(vlookup(B8,'Kings Ratings'!$A$2:$C$1000,3,false),""Crafting""),""Yes"","""")"),"") | N8: =IFERROR(__xludf.DUMMYFUNCTION("if(REGEXMATCH(vlookup(B8,'Kings Ratings'!$A$2:$C$1000,3,false),""Exploring""),""Yes"","""")"),"") | O8: =IFERROR(__xludf.DUMMYFUNCTION("if(REGEXMATCH(vlookup(B8,'Kings Ratings'!$A$2:$C$1000,3,false),""Farming""),""Yes"","""")"),"") | P8: =IFERROR(__xludf.DUMMYFUNCTION("if(REGEXMATCH(vlookup(B8,'Kings Ratings'!$A$2:$C$1000,3,false),""Cooking""),""Yes"","""")"),"") | Q8: =IFERROR(__xludf.DUMMYFUNCTION("if(REGEXMATCH(vlookup(B8,'Kings Ratings'!$A$2:$C$1000,3,false),""Event""),""Yes"","""")"),"") | S8: Kings Rating is GM Focused
A9: 17 | B9: Drum | C9: =CONCATENATE("((",B9,"))") -> ((Drum)) | D9: 54150 | E9: 26728 | F9: 13381 | G9: =VLOOKUP(B9,'Kings Ratings'!$A$2:$B$1000,2,false) -> 1 | H9: =if(G9=11,13,13-ROUNDDOWN(log(J9,4),0)) -> 0 | I9: =vlookup(A9,'202405 MM (Do Not Delete)'!$A$1:$G$1000,7,false) -> 219 | J9: =10000*F9+10*E9+D9 -> 134131430 | L9: =IFERROR(__xludf.DUMMYFUNCTION("if(REGEXMATCH(vlookup(B9,'Kings Ratings'!$A$2:$C$1000,3,false),""Fishing""),""Yes"","""")"),"Yes") -> Yes | M9: =IFERROR(__xludf.DUMMYFUNCTION("if(REGEXMATCH(vlookup(B9,'Kings Ratings'!$A$2:$C$1000,3,false),""Crafting""),""Yes"","""")"),"") | N9: =IFERROR(__xludf.DUMMYFUNCTION("if(REGEXMATCH(vlookup(B9,'Kings Ratings'!$A$2:$C$1000,3,false),""Exploring""),""Yes"","""")"),"") | O9: =IFERROR(__xludf.DUMMYFUNCTION("if(REGEXMATCH(vlookup(B9,'Kings Ratings'!$A$2:$C$1000,3,false),""Farming""),""Yes"","""")"),"") | P9: =IFERROR(__xludf.DUMMYFUNCTION("if(REGEXMATCH(vlookup(B9,'Kings Ratings'!$A$2:$C$1000,3,false),""Cooking""),""Yes"","""")"),"") | Q9: =IFERROR(__xludf.DUMMYFUNCTION("if(REGEXMATCH(vlookup(B9,'Kings Ratings'!$A$2:$C$1000,3,false),""Event""),""Yes"","""")"),"") | S9: ClientCoin Rating is MM Focused
A10: 36 | B10: Wooden Plank | C10: =CONCATENATE("((",B10,"))") -> ((Wooden Plank)) | D10: 54015 | E10: 26311 | F10: 10335 | G10: =VLOOKUP(B10,'Kings Ratings'!$A$2:$B$1000,2,false) -> 1 | H10: =if(G10=11,13,13-ROUNDDOWN(log(J10,4),0)) -> 0 | I10: =vlookup(A10,'202405 MM (Do Not Delete)'!$A$1:$G$1000,7,false) -> 267 | J10: =10000*F10+10*E10+D10 -> 103667125 | L10: =IFERROR(__xludf.DUMMYFUNCTION("if(REGEXMATCH(vlookup(B10,'Kings Ratings'!$A$2:$C$1000,3,false),""Fishing""),""Yes"","""")"),"") | M10: =IFERROR(__xludf.DUMMYFUNCTION("if(REGEXMATCH(vlookup(B10,'Kings Ratings'!$A$2:$C$1000,3,false),""Crafting""),""Yes"","""")"),"Yes") -> Yes | N10: =IFERROR(__xludf.DUMMYFUNCTION("if(REGEXMATCH(vlookup(B10,'Kings Ratings'!$A$2:$C$1000,3,false),""Exploring""),""Yes"","""")"),"") | O10: =IFERROR(__xludf.DUMMYFUNCTION("if(REGEXMATCH(vlookup(B10,'Kings Ratings'!$A$2:$C$1000,3,false),""Farming""),""Yes"","""")"),"") | P10: =IFERROR(__xludf.DUMMYFUNCTION("if(REGEXMATCH(vlookup(B10,'Kings Ratings'!$A$2:$C$1000,3,false),""Cooking""),""Yes"","""")"),"") | Q10: =IFERROR(__xludf.DUMMYFUNCTION("if(REGEXMATCH(vlookup(B10,'Kings Ratings'!$A$2:$C$1000,3,false),""Event""),""Yes"","""")"),"")
A11: 117 | B11: Glass Bottle | C11: =CONCATENATE("((",B11,"))") -> ((Glass Bottle)) | D11: 53956 | E11: 27811 | F11: 10067 | G11: =VLOOKUP(B11,'Kings Ratings'!$A$2:$B$1000,2,false) -> 1 | H11: =if(G11=11,13,13-ROUNDDOWN(log(J11,4),0)) -> 0 | I11: =vlookup(A11,'202405 MM (Do Not Delete)'!$A$1:$G$1000,7,false) -> 269 | J11: =10000*F11+10*E11+D11 -> 101002066 | L11: =IFERROR(__xludf.DUMMYFUNCTION("if(REGEXMATCH(vlookup(B11,'Kings Ratings'!$A$2:$C$1000,3,false),""Fishing""),""Yes"","""")"),"") | M11: =IFERROR(__xludf.DUMMYFUNCTION("if(REGEXMATCH(vlookup(B11,'Kings Ratings'!$A$2:$C$1000,3,false),""Crafting""),""Yes"","""")"),"Yes") -> Yes | N11: =IFERROR(__xludf.DUMMYFUNCTION("if(REGEXMATCH(vlookup(B11,'Kings Ratings'!$A$2:$C$1000,3,false),""Exploring""),""Yes"","""")"),"") | O11: =IFERROR(__xludf.DUMMYFUNCTION("if(REGEXMATCH(vlookup(B11,'Kings Ratings'!$A$2:$C$1000,3,false),""Farming""),""Yes"","""")"),"") | P11: =IFERROR(__xludf.DUMMYFUNCTION("if(REGEXMATCH(vlookup(B11,'Kings Ratings'!$A$2:$C$1000,3,false),""Cooking""),""Yes"","""")"),"") | Q11: =IFERROR(__xludf.DUMMYFUNCTION("if(REGEXMATCH(vlookup(B11,'Kings Ratings'!$A$2:$C$1000,3,false),""Event""),""Yes"","""")"),"")
A12: 24 | B12: Yellow Perch | C12: =CONCATENATE("((",B12,"))") -> ((Yellow Perch)) | D12: 52952 | E12: 26633 | F12: 13370 | G12: =VLOOKUP(B12,'Kings Ratings'!$A$2:$B$1000,2,false) -> 1 | H12: =if(G12=11,13,13-ROUNDDOWN(log(J12,4),0)) -> 0 | I12: =vlookup(A12,'202405 MM (Do Not Delete)'!$A$1:$G$1000,7,false) -> 261 | J12: =10000*F12+10*E12+D12 -> 134019282 | L12: =IFERROR(__xludf.DUMMYFUNCTION("if(REGEXMATCH(vlookup(B12,'Kings Ratings'!$A$2:$C$1000,3,false),""Fishing""),""Yes"","""")"),"Yes") -> Yes | M12: =IFERROR(__xludf.DUMMYFUNCTION("if(REGEXMATCH(vlookup(B12,'Kings Ratings'!$A$2:$C$1000,3,false),""Crafting""),""Yes"","""")"),"") | N12: =IFERROR(__xludf.DUMMYFUNCTION("if(REGEXMATCH(vlookup(B12,'Kings Ratings'!$A$2:$C$1000,3,false),""Exploring""),""Yes"","""")"),"") | O12: =IFERROR(__xludf.DUMMYFUNCTION("if(REGEXMATCH(vlookup(B12,'Kings Ratings'!$A$2:$C$1000,3,false),""Farming""),""Yes"","""")"),"") | P12: =IFERROR(__xludf.DUMMYFUNCTION("if(REGEXMATCH(vlookup(B12,'Kings Ratings'!$A$2:$C$1000,3,false),""Cooking""),""Yes"","""")"),"") | Q12: =IFERROR(__xludf.DUMMYFUNCTION("if(REGEXMATCH(vlookup(B12,'Kings Ratings'!$A$2:$C$1000,3,false),""Event""),""Yes"","""")"),"")
A13: 231 | B13: Torch Fish | C13: =CONCATENATE("((",B13,"))") -> ((Torch Fish)) | D13: 51290 | E13: 28756 | F13: 14430 | G13: =VLOOKUP(B13,'Kings Ratings'!$A$2:$B$1000,2,false) -> 1 | H13: =if(G13=11,13,13-ROUNDDOWN(log(J13,4),0)) -> 0 | I13: =vlookup(A13,'202405 MM (Do Not Delete)'!$A$1:$G$1000,7,false) -> 215 | J13: =10000*F13+10*E13+D13 -> 144638850 | L13: =IFERROR(__xludf.DUMMYFUNCTION("if(REGEXMATCH(vlookup(B13,'Kings Ratings'!$A$2:$C$1000,3,false),""Fishing""),""Yes"","""")"),"Yes") -> Yes | M13: =IFERROR(__xludf.DUMMYFUNCTION("if(REGEXMATCH(vlookup(B13,'Kings Ratings'!$A$2:$C$1000,3,false),""Crafting""),""Yes"","""")"),"") | N13: =IFERROR(__xludf.DUMMYFUNCTION("if(REGEXMATCH(vlookup(B13,'Kings Ratings'!$A$2:$C$1000,3,false),""Exploring""),""Yes"","""")"),"") | O13: =IFERROR(__xludf.DUMMYFUNCTION("if(REGEXMATCH(vlookup(B13,'Kings Ratings'!$A$2:$C$1000,3,false),""Farming""),""Yes"","""")"),"") | P13: =IFERROR(__xludf.DUMMYFUNCTION("if(REGEXMATCH(vlookup(B13,'Kings Ratings'!$A$2:$C$1000,3,false),""Cooking""),""Yes"","""")"),"") | Q13: =IFERROR(__xludf.DUMMYFUNCTION("if(REGEXMATCH(vlookup(B13,'Kings Ratings'!$A$2:$C$1000,3,false),""Event""),""Yes"","""")"),"")
A14: 75 | B14: Mushroom Paste | C14: =CONCATENATE("((",B14,"))") -> ((Mushroom Paste)) | D14: 48836 | E14: 24253 | F14: 9654 | G14: =VLOOKUP(B14,'Kings Ratings'!$A$2:$B$1000,2,false) -> 1 | H14: =if(G14=11,13,13-ROUNDDOWN(log(J14,4),0)) -> 0 | I14: =vlookup(A14,'202405 MM (Do Not Delete)'!$A$1:$G$1000,7,false) -> 220 | J14: =10000*F14+10*E14+D14 -> 96831366 | L14: =IFERROR(__xludf.DUMMYFUNCTION("if(REGEXMATCH(vlookup(B14,'Kings Ratings'!$A$2:$C$1000,3,false),""Fishing""),""Yes"","""")"),"") | M14: =IFERROR(__xludf.DUMMYFUNCTION("if(REGEXMATCH(vlookup(B14,'Kings Ratings'!$A$2:$C$1000,3,false),""Crafting""),""Yes"","""")"),"Yes") -> Yes | N14: =IFERROR(__xludf.DUMMYFUNCTION("if(REGEXMATCH(vlookup(B14,'Kings Ratings'!$A$2:$C$1000,3,false),""Exploring""),""Yes"","""")"),"") | O14: =IFERROR(__xludf.DUMMYFUNCTION("if(REGEXMATCH(vlookup(B14,'Kings Ratings'!$A$2:$C$1000,3,false),""Farming""),""Yes"","""")"),"") | P14: =IFERROR(__xludf.DUMMYFUNCTION("if(REGEXMATCH(vlookup(B14,'Kings Ratings'!$A$2:$C$1000,3,false),""Cooking""),""Yes"","""")"),"") | Q14: =IFERROR(__xludf.DUMMYFUNCTION("if(REGEXMATCH(vlookup(B14,'Kings Ratings'!$A$2:$C$1000,3,false),""Event""),""Yes"","""")"),"")
A15: 77 | B15: Shimmer Stone | C15: =CONCATENATE("((",B15,"))") -> ((Shimmer Stone)) | D15: 47762 | E15: 21000 | F15: 7664 | G15: =VLOOKUP(B15,'Kings Ratings'!$A$2:$B$1000,2,false) -> 1 | H15: =if(G15=11,13,13-ROUNDDOWN(log(J15,4),0)) -> 0 | I15: =vlookup(A15,'202405 MM (Do Not Delete)'!$A$1:$G$1000,7,false) -> 227 | J15: =10000*F15+10*E15+D15 -> 76897762 | L15: =IFERROR(__xludf.DUMMYFUNCTION("if(REGEXMATCH(vlookup(B15,'Kings Ratings'!$A$2:$C$1000,3,false),""Fishing""),""Yes"","""")"),"") | M15: =IFERROR(__xludf.DUMMYFUNCTION("if(REGEXMATCH(vlookup(B15,'Kings Ratings'!$A$2:$C$1000,3,false),""Crafting""),""Yes"","""")"),"Yes") -> Yes | N15: =IFERROR(__xludf.DUMMYFUNCTION("if(REGEXMATCH(vlookup(B15,'Kings Ratings'!$A$2:$C$1000,3,false),""Exploring""),""Yes"","""")"),"") | O15: =IFERROR(__xludf.DUMMYFUNCTION("if(REGEXMATCH(vlookup(B15,'Kings Ratings'!$A$2:$C$1000,3,false),""Farming""),""Yes"","""")"),"") | P15: =IFERROR(__xludf.DUMMYFUNCTION("if(REGEXMATCH(vlookup(B15,'Kings Ratings'!$A$2:$C$1000,3,false),""Cooking""),""Yes"","""")"),"") | Q15: =IFERROR(__xludf.DUMMYFUNCTION("if(REGEXMATCH(vlookup(B15,'Kings Ratings'!$A$2:$C$1000,3,false),""Event""),""Yes"","""")"),"")
A16: 193 | B16: Rope | C16: =CONCATENATE("((",B16,"))") -> ((Rope)) | D16: 47364 | E16: 29729 | F16: 15253 | G16: =VLOOKUP(B16,'Kings Ratings'!$A$2:$B$1000,2,false) -> 1 | H16: =if(G16=11,13,13-ROUNDDOWN(log(J16,4),0)) -> 0 | I16: =vlookup(A16,'202405 MM (Do Not Delete)'!$A$1:$G$1000,7,false) -> 206 | J16: =10000*F16+10*E16+D16 -> 152874654 | L16: =IFERROR(__xludf.DUMMYFUNCTION("if(REGEXMATCH(vlookup(B16,'Kings Ratings'!$A$2:$C$1000,3,false),""Fishing""),""Yes"","""")"),"") | M16: =IFERROR(__xludf.DUMMYFUNCTION("if(REGEXMATCH(vlookup(B16,'Kings Ratings'!$A$2:$C$1000,3,false),""Crafting""),""Yes"","""")"),"Yes") -> Yes | N16: =IFERROR(__xludf.DUMMYFUNCTION("if(REGEXMATCH(vlookup(B16,'Kings Ratings'!$A$2:$C$1000,3,false),""Exploring""),""Yes"","""")"),"") | O16: =IFERROR(__xludf.DUMMYFUNCTION("if(REGEXMATCH(vlookup(B16,'Kings Ratings'!$A$2:$C$1000,3,false),""Farming""),""Yes"","""")"),"") | P16: =IFERROR(__xludf.DUMMYFUNCTION("if(REGEXMATCH(vlookup(B16,'Kings Ratings'!$A$2:$C$1000,3,false),""Cooking""),""Yes"","""")"),"") | Q16: =IFERROR(__xludf.DUMMYFUNCTION("if(REGEXMATCH(vlookup(B16,'Kings Ratings'!$A$2:$C$1000,3,false),""Event""),""Yes"","""")"),"")
A17: 145 | B17: Steel | C17: =CONCATENATE("((",B17,"))") -> ((Steel)) | D17: 46469 | E17: 27712 | F17: 12441 | G17: =VLOOKUP(B17,'Kings Ratings'!$A$2:$B$1000,2,false) -> 1 | H17: =if(G17=11,13,13-ROUNDDOWN(log(J17,4),0)) -> 0 | I17: =vlookup(A17,'202405 MM (Do Not Delete)'!$A$1:$G$1000,7,false) -> 251 | J17: =10000*F17+10*E17+D17 -> 124733589 | L17: =IFERROR(__xludf.DUMMYFUNCTION("if(REGEXMATCH(vlookup(B17,'Kings Ratings'!$A$2:$C$1000,3,false),""Fishing""),""Yes"","""")"),"") | M17: =IFERROR(__xludf.DUMMYFUNCTION("if(REGEXMATCH(vlookup(B17,'Kings Ratings'!$A$2:$C$1000,3,false),""Crafting""),""Yes"","""")"),"") | N17: =IFERROR(__xludf.DUMMYFUNCTION("if(REGEXMATCH(vlookup(B17,'Kings Ratings'!$A$2:$C$1000,3,false),""Exploring""),""Yes"","""")"),"") | O17: =IFERROR(__xludf.DUMMYFUNCTION("if(REGEXMATCH(vlookup(B17,'Kings Ratings'!$A$2:$C$1000,3,false),""Farming""),""Yes"","""")"),"") | P17: =IFERROR(__xludf.DUMMYFUNCTION("if(REGEXMATCH(vlookup(B17,'Kings Ratings'!$A$2:$C$1000,3,false),""Cooking""),""Yes"","""")"),"") | Q17: =IFERROR(__xludf.DUMMYFUNCTION("if(REGEXMATCH(vlookup(B17,'Kings Ratings'!$A$2:$C$1000,3,false),""Event""),""Yes"","""")"),"")
A18: 63 | B18: Trout | C18: =CONCATENATE("((",B18,"))") -> ((Trout)) | D18: 46177 | E18: 26256 | F18: 13373 | G18: =VLOOKUP(B18,'Kings Ratings'!$A$2:$B$1000,2,false) -> 1 | H18: =if(G18=11,13,13-ROUNDDOWN(log(J18,4),0)) -> 0 | I18: =vlookup(A18,'202405 MM (Do Not Delete)'!$A$1:$G$1000,7,false) -> 274 | J18: =10000*F18+10*E18+D18 -> 134038737 | L18: =IFERROR(__xludf.DUMMYFUNCTION("if(REGEXMATCH(vlookup(B18,'Kings Ratings'!$A$2:$C$1000,3,false),""Fishing""),""Yes"","""")"),"Yes") -> Yes | M18: =IFERROR(__xludf.DUMMYFUNCTION("if(REGEXMATCH(vlookup(B18,'Kings Ratings'!$A$2:$C$1000,3,false),""Crafting""),""Yes"","""")"),"") | N18: =IFERROR(__xludf.DUMMYFUNCTION("if(REGEXMATCH(vlookup(B18,'Kings Ratings'!$A$2:$C$1000,3,false),""Exploring""),""Yes"","""")"),"") | O18: =IFERROR(__xludf.DUMMYFUNCTION("if(REGEXMATCH(vlookup(B18,'Kings Ratings'!$A$2:$C$1000,3,false),""Farming""),""Yes"","""")"),"") | P18: =IFERROR(__xludf.DUMMYFUNCTION("if(REGEXMATCH(vlookup(B18,'Kings Ratings'!$A$2:$C$1000,3,false),""Cooking""),""Yes"","""")"),"") | Q18: =IFERROR(__xludf.DUMMYFUNCTION("if(REGEXMATCH(vlookup(B18,'Kings Ratings'!$A$2:$C$1000,3,false),""Event""),""Yes"","""")"),"")
A19: 25 | B19: Largemouth Bass | C19: =CONCATENATE("((",B19,"))") -> ((Largemouth Bass)) | D19: 45911 | E19: 23878 | F19: 12903 | G19: =VLOOKUP(B19,'Kings Ratings'!$A$2:$B$1000,2,false) -> 1 | H19: =if(G19=11,13,13-ROUNDDOWN(log(J19,4),0)) -> 0 | I19: =vlookup(A19,'202405 MM (Do Not Delete)'!$A$1:$G$1000,7,false) -> 254 | J19: =10000*F19+10*E19+D19 -> 129314691 | L19: =IFERROR(__xludf.DUMMYFUNCTION("if(REGEXMATCH(vlookup(B19,'Kings Ratings'!$A$2:$C$1000,3,false),""Fishing""),""Yes"","""")"),"Yes") -> Yes | M19: =IFERROR(__xludf.DUMMYFUNCTION("if(REGEXMATCH(vlookup(B19,'Kings Ratings'!$A$2:$C$1000,3,false),""Crafting""),""Yes"","""")"),"") | N19: =IFERROR(__xludf.DUMMYFUNCTION("if(REGEXMATCH(vlookup(B19,'Kings Ratings'!$A$2:$C$1000,3,false),""Exploring""),""Yes"","""")"),"") | O19: =IFERROR(__xludf.DUMMYFUNCTION("if(REGEXMATCH(vlookup(B19,'Kings Ratings'!$A$2:$C$1000,3,false),""Farming""),""Yes"","""")"),"") | P19: =IFERROR(__xludf.DUMMYFUNCTION("if(REGEXMATCH(vlookup(B19,'Kings Ratings'!$A$2:$C$1000,3,false),""Cooking""),""Yes"","""")"),"") | Q19: =IFERROR(__xludf.DUMMYFUNCTION("if(REGEXMATCH(vlookup(B19,'Kings Ratings'!$A$2:$C$1000,3,false),""Event""),""Yes"","""")"),"")
A20: 306 | B20: Swordfish | C20: =CONCATENATE("((",B20,"))") -> ((Swordfish)) | D20: 45848 | E20: 29791 | F20: 9867 | G20: =VLOOKUP(B20,'Kings Ratings'!$A$2:$B$1000,2,false) -> 1 | H20: =if(G20=11,13,13-ROUNDDOWN(log(J20,4),0)) -> 0 | I20: =vlookup(A20,'202405 MM (Do Not Delete)'!$A$1:$G$1000,7,false) -> 222 | J20: =10000*F20+10*E20+D20 -> 99013758 | L20: =IFERROR(__xludf.DUMMYFUNCTION("if(REGEXMATCH(vlookup(B20,'Kings Ratings'!$A$2:$C$1000,3,false),""Fishing""),""Yes"","""")"),"Yes") -> Yes | M20: =IFERROR(__xludf.DUMMYFUNCTION("if(REGEXMATCH(vlookup(B20,'Kings Ratings'!$A$2:$C$1000,3,false),""Crafting""),""Yes"","""")"),"") | N20: =IFERROR(__xludf.DUMMYFUNCTION("if(REGEXMATCH(vlookup(B20,'Kings Ratings'!$A$2:$C$1000,3,false),""Exploring""),""Yes"","""")"),"") | O20: =IFERROR(__xludf.DUMMYFUNCTION("if(REGEXMATCH(vlookup(B20,'Kings Ratings'!$A$2:$C$1000,3,false),""Farming""),""Yes"","""")"),"") | P20: =IFERROR(__xludf.DUMMYFUNCTION("if(REGEXMATCH(vlookup(B20,'Kings Ratings'!$A$2:$C$1000,3,false),""Cooking""),""Yes"","""")"),"") | Q20: =IFERROR(__xludf.DUMMYFUNCTION("if(REGEXMATCH(vlookup(B20,'Kings Ratings'!$A$2:$C$1000,3,false),""Event""),""Yes"","""")"),"")
A21: 194 | B21: Fishing Net | C21: =CONCATENATE("((",B21,"))") -> ((Fishing Net)) | D21: 45431 | E21: 27323 | F21: 13902 | G21: =VLOOKUP(B21,'Kings Ratings'!$A$2:$B$1000,2,false) -> 2 | H21: =if(G21=11,13,13-ROUNDDOWN(log(J21,4),0)) -> 0 | I21: =vlookup(A21,'202405 MM (Do Not Delete)'!$A$1:$G$1000,7,false) -> 211 | J21: =10000*F21+10*E21+D21 -> 139338661 | L21: =IFERROR(__xludf.DUMMYFUNCTION("if(REGEXMATCH(vlookup(B21,'Kings Ratings'!$A$2:$C$1000,3,false),""Fishing""),""Yes"","""")"),"") | M21: =IFERROR(__xludf.DUMMYFUNCTION("if(REGEXMATCH(vlookup(B21,'Kings Ratings'!$A$2:$C$1000,3,false),""Crafting""),""Yes"","""")"),"Yes") -> Yes | N21: =IFERROR(__xludf.DUMMYFUNCTION("if(REGEXMATCH(vlookup(B21,'Kings Ratings'!$A$2:$C$1000,3,false),""Exploring""),""Yes"","""")"),"") | O21: =IFERROR(__xludf.DUMMYFUNCTION("if(REGEXMATCH(vlookup(B21,'Kings Ratings'!$A$2:$C$1000,3,false),""Farming""),""Yes"","""")"),"") | P21: =IFERROR(__xludf.DUMMYFUNCTION("if(REGEXMATCH(vlookup(B21,'Kings Ratings'!$A$2:$C$1000,3,false),""Cooking""),""Yes"","""")"),"") | Q21: =IFERROR(__xludf.DUMMYFUNCTION("if(REGEXMATCH(vlookup(B21,'Kings Ratings'!$A$2:$C$1000,3,false),""Event""),""Yes"","""")"),"")
A22: 167 | B22: Sturdy Shield | C22: =CONCATENATE("((",B22,"))") -> ((Sturdy Shield)) | D22: 45023 | E22: 20631 | F22: 6417 | G22: =VLOOKUP(B22,'Kings Ratings'!$A$2:$B$1000,2,false) -> 1 | H22: =if(G22=11,13,13-ROUNDDOWN(log(J22,4),0)) -> 1 | I22: =vlookup(A22,'202405 MM (Do Not Delete)'!$A$1:$G$1000,7,false) -> 239 | J22: =10000*F22+10*E22+D22 -> 64421333 | L22: =IFERROR(__xludf.DUMMYFUNCTION("if(REGEXMATCH(vlookup(B22,'Kings Ratings'!$A$2:$C$1000,3,false),""Fishing""),""Yes"","""")"),"") | M22: =IFERROR(__xludf.DUMMYFUNCTION("if(REGEXMATCH(vlookup(B22,'Kings Ratings'!$A$2:$C$1000,3,false),""Crafting""),""Yes"","""")"),"Yes") -> Yes | N22: =IFERROR(__xludf.DUMMYFUNCTION("if(REGEXMATCH(vlookup(B22,'Kings Ratings'!$A$2:$C$1000,3,false),""Exploring""),""Yes"","""")"),"") | O22: =IFERROR(__xludf.DUMMYFUNCTION("if(REGEXMATCH(vlookup(B22,'Kings Ratings'!$A$2:$C$1000,3,false),""Farming""),""Yes"","""")"),"") | P22: =IFERROR(__xludf.DUMMYFUNCTION("if(REGEXMATCH(vlookup(B22,'Kings Ratings'!$A$2:$C$1000,3,false),""Cooking""),""Yes"","""")"),"") | Q22: =IFERROR(__xludf.DUMMYFUNCTION("if(REGEXMATCH(vlookup(B22,'Kings Ratings'!$A$2:$C$1000,3,false),""Event""),""Yes"","""")"),"")
A23: 307 | B23: Barracuda | C23: =CONCATENATE("((",B23,"))") -> ((Barracuda)) | D23: 44524 | E23: 27593 | F23: 8966 | G23: =VLOOKUP(B23,'Kings Ratings'!$A$2:$B$1000,2,false) -> 1 | H23: =if(G23=11,13,13-ROUNDDOWN(log(J23,4),0)) -> 0 | I23: =vlookup(A23,'202405 MM (Do Not Delete)'!$A$1:$G$1000,7,false) -> 225 | J23: =10000*F23+10*E23+D23 -> 89980454 | L23: =IFERROR(__xludf.DUMMYFUNCTION("if(REGEXMATCH(vlookup(B23,'Kings Ratings'!$A$2:$C$1000,3,false),""Fishing""),""Yes"","""")"),"Yes") -> Yes | M23: =IFERROR(__xludf.DUMMYFUNCTION("if(REGEXMATCH(vlookup(B23,'Kings Ratings'!$A$2:$C$1000,3,false),""Crafting""),""Yes"","""")"),"") | N23: =IFERROR(__xludf.DUMMYFUNCTION("if(REGEXMATCH(vlookup(B23,'Kings Ratings'!$A$2:$C$1000,3,false),""Exploring""),""Yes"","""")"),"") | O23: =IFERROR(__xludf.DUMMYFUNCTION("if(REGEXMATCH(vlookup(B23,'Kings Ratings'!$A$2:$C$1000,3,false),""Farming""),""Yes"","""")"),"") | P23: =IFERROR(__xludf.DUMMYFUNCTION("if(REGEXMATCH(vlookup(B23,'Kings Ratings'!$A$2:$C$1000,3,false),""Cooking""),""Yes"","""")"),"") | Q23: =IFERROR(__xludf.DUMMYFUNCTION("if(REGEXMATCH(vlookup(B23,'Kings Ratings'!$A$2:$C$1000,3,false),""Event""),""Yes"","""")"),"")
A24: 198 | B24: Mackerel | C24: =CONCATENATE("((",B24,"))") -> ((Mackerel)) | D24: 44464 | E24: 26145 | F24: 13806 | G24: =VLOOKUP(B24,'Kings Ratings'!$A$2:$B$1000,2,false) -> 1 | H24: =if(G24=11,13,13-ROUNDDOWN(log(J24,4),0)) -> 0 | I24: =vlookup(A24,'202405 MM (Do Not Delete)'!$A$1:$G$1000,7,false) -> 216 | J24: =10000*F24+10*E24+D24 -> 138365914 | L24: =IFERROR(__xludf.DUMMYFUNCTION("if(REGEXMATCH(vlookup(B24,'Kings Ratings'!$A$2:$C$1000,3,false),""Fishing""),""Yes"","""")"),"Yes") -> Yes | M24: =IFERROR(__xludf.DUMMYFUNCTION("if(REGEXMATCH(vlookup(B24,'Kings Ratings'!$A$2:$C$1000,3,false),""Crafting""),""Yes"","""")"),"") | N24: =IFERROR(__xludf.DUMMYFUNCTION("if(REGEXMATCH(vlookup(B24,'Kings Ratings'!$A$2:$C$1000,3,false),""Exploring""),""Yes"","""")"),"") | O24: =IFERROR(__xludf.DUMMYFUNCTION("if(REGEXMATCH(vlookup(B24,'Kings Ratings'!$A$2:$C$1000,3,false),""Farming""),""Yes"","""")"),"") | P24: =IFERROR(__xludf.DUMMYFUNCTION("if(REGEXMATCH(vlookup(B24,'Kings Ratings'!$A$2:$C$1000,3,false),""Cooking""),""Yes"","""")"),"") | Q24: =IFERROR(__xludf.DUMMYFUNCTION("if(REGEXMATCH(vlookup(B24,'Kings Ratings'!$A$2:$C$1000,3,false),""Event""),""Yes"","""")"),"")
A25: 65 | B25: Corn | C25: =CONCATENATE("((",B25,"))") -> ((Corn)) | D25: 43435 | E25: 10526 | F25: 786 | G25: =VLOOKUP(B25,'Kings Ratings'!$A$2:$B$1000,2,false) -> 7 | H25: =if(G25=11,13,13-ROUNDDOWN(log(J25,4),0)) -> 2 | I25: =vlookup(A25,'202405 MM (Do Not Delete)'!$A$1:$G$1000,7,false) | J25: =10000*F25+10*E25+D25 -> 8008695 | L25: =IFERROR(__xludf.DUMMYFUNCTION("if(REGEXMATCH(vlookup(B25,'Kings Ratings'!$A$2:$C$1000,3,false),""Fishing""),""Yes"","""")"),"") | M25: =IFERROR(__xludf.DUMMYFUNCTION("if(REGEXMATCH(vlookup(B25,'Kings Ratings'!$A$2:$C$1000,3,false),""Crafting""),""Yes"","""")"),"") | N25: =IFERROR(__xludf.DUMMYFUNCTION("if(REGEXMATCH(vlookup(B25,'Kings Ratings'!$A$2:$C$1000,3,false),""Exploring""),""Yes"","""")"),"") | O25: =IFERROR(__xludf.DUMMYFUNCTION("if(REGEXMATCH(vlookup(B25,'Kings Ratings'!$A$2:$C$1000,3,false),""Farming""),""Yes"","""")"),"Yes") -> Yes | P25: =IFERROR(__xludf.DUMMYFUNCTION("if(REGEXMATCH(vlookup(B25,'Kings Ratings'!$A$2:$C$1000,3,false),""Cooking""),""Yes"","""")"),"") | Q25: =IFERROR(__xludf.DUMMYFUNCTION("if(REGEXMATCH(vlookup(B25,'Kings Ratings'!$A$2:$C$1000,3,false),""Event""),""Yes"","""")"),"")
A26: 84 | B26: Orange Juice | C26: =CONCATENATE("((",B26,"))") -> ((Orange Juice)) | D26: 43373 | E26: 18514 | F26: 5315 | G26: =VLOOKUP(B26,'Kings Ratings'!$A$2:$B$1000,2,false) -> 3 | H26: =if(G26=11,13,13-ROUNDDOWN(log(J26,4),0)) -> 1 | I26: =vlookup(A26,'202405 MM (Do Not Delete)'!$A$1:$G$1000,7,false) -> 239 | J26: =10000*F26+10*E26+D26 -> 53378513 | L26: =IFERROR(__xludf.DUMMYFUNCTION("if(REGEXMATCH(vlookup(B26,'Kings Ratings'!$A$2:$C$1000,3,false),""Fishing""),""Yes"","""")"),"") | M26: =IFERROR(__xludf.DUMMYFUNCTION("if(REGEXMATCH(vlookup(B26,'Kings Ratings'!$A$2:$C$1000,3,false),""Crafting""),""Yes"","""")"),"Yes") -> Yes | N26: =IFERROR(__xludf.DUMMYFUNCTION("if(REGEXMATCH(vlookup(B26,'Kings Ratings'!$A$2:$C$1000,3,false),""Exploring""),""Yes"","""")"),"") | O26: =IFERROR(__xludf.DUMMYFUNCTION("if(REGEXMATCH(vlookup(B26,'Kings Ratings'!$A$2:$C$1000,3,false),""Farming""),""Yes"","""")"),"") | P26: =IFERROR(__xludf.DUMMYFUNCTION("if(REGEXMATCH(vlookup(B26,'Kings Ratings'!$A$2:$C$1000,3,false),""Cooking""),""Yes"","""")"),"") | Q26: =IFERROR(__xludf.DUMMYFUNCTION("if(REGEXMATCH(vlookup(B26,'Kings Ratings'!$A$2:$C$1000,3,false),""Event""),""Yes"","""")"),"")
A27: 308 | B27: Sea Catfish | C27: =CONCATENATE("((",B27,"))") -> ((Sea Catfish)) | D27: 43161 | E27: 25914 | F27: 8330 | G27: =VLOOKUP(B27,'Kings Ratings'!$A$2:$B$1000,2,false) -> 1 | H27: =if(G27=11,13,13-ROUNDDOWN(log(J27,4),0)) -> 0 | I27: =vlookup(A27,'202405 MM (Do Not Delete)'!$A$1:$G$1000,7,false) -> 229 | J27: =10000*F27+10*E27+D27 -> 83602301 | L27: =IFERROR(__xludf.DUMMYFUNCTION("if(REGEXMATCH(vlookup(B27,'Kings Ratings'!$A$2:$C$1000,3,false),""Fishing""),""Yes"","""")"),"Yes") -> Yes | M27: =IFERROR(__xludf.DUMMYFUNCTION("if(REGEXMATCH(vlookup(B27,'Kings Ratings'!$A$2:$C$1000,3,false),""Crafting""),""Yes"","""")"),"") | N27: =IFERROR(__xludf.DUMMYFUNCTION("if(REGEXMATCH(vlookup(B27,'Kings Ratings'!$A$2:$C$1000,3,false),""Exploring""),""Yes"","""")"),"") | O27: =IFERROR(__xludf.DUMMYFUNCTION("if(REGEXMATCH(vlookup(B27,'Kings Ratings'!$A$2:$C$1000,3,false),""Farming""),""Yes"","""")"),"") | P27: =IFERROR(__xludf.DUMMYFUNCTION("if(REGEXMATCH(vlookup(B27,'Kings Ratings'!$A$2:$C$1000,3,false),""Cooking""),""Yes"","""")"),"") | Q27: =IFERROR(__xludf.DUMMYFUNCTION("if(REGEXMATCH(vlookup(B27,'Kings Ratings'!$A$2:$C$1000,3,false),""Event""),""Yes"","""")"),"")
A28: 309 | B28: Plumbfish | C28: =CONCATENATE("((",B28,"))") -> ((Plumbfish)) | D28: 42655 | E28: 24898 | F28: 8153 | G28: =VLOOKUP(B28,'Kings Ratings'!$A$2:$B$1000,2,false) -> 1 | H28: =if(G28=11,13,13-ROUNDDOWN(log(J28,4),0)) -> 0 | I28: =vlookup(A28,'202405 MM (Do Not Delete)'!$A$1:$G$1000,7,false) -> 230 | J28: =10000*F28+10*E28+D28 -> 81821635 | L28: =IFERROR(__xludf.DUMMYFUNCTION("if(REGEXMATCH(vlookup(B28,'Kings Ratings'!$A$2:$C$1000,3,false),""Fishing""),""Yes"","""")"),"Yes") -> Yes | M28: =IFERROR(__xludf.DUMMYFUNCTION("if(REGEXMATCH(vlookup(B28,'Kings Ratings'!$A$2:$C$1000,3,false),""Crafting""),""Yes"","""")"),"") | N28: =IFERROR(__xludf.DUMMYFUNCTION("if(REGEXMATCH(vlookup(B28,'Kings Ratings'!$A$2:$C$1000,3,false),""Exploring""),""Yes"","""")"),"") | O28: =IFERROR(__xludf.DUMMYFUNCTION("if(REGEXMATCH(vlookup(B28,'Kings Ratings'!$A$2:$C$1000,3,false),""Farming""),""Yes"","""")"),"") | P28: =IFERROR(__xludf.DUMMYFUNCTION("if(REGEXMATCH(vlookup(B28,'Kings Ratings'!$A$2:$C$1000,3,false),""Cooking""),""Yes"","""")"),"") | Q28: =IFERROR(__xludf.DUMMYFUNCTION("if(REGEXMATCH(vlookup(B28,'Kings Ratings'!$A$2:$C$1000,3,false),""Event""),""Yes"","""")"),"")
A29: 368 | B29: Lantern | C29: =CONCATENATE("((",B29,"))") -> ((Lantern)) | D29: 41305 | E29: 13937 | F29: 2254 | G29: =VLOOKUP(B29,'Kings Ratings'!$A$2:$B$1000,2,false) -> 2 | H29: =if(G29=11,13,13-ROUNDDOWN(log(J29,4),0)) -> 1 | I29: =vlookup(A29,'202405 MM (Do Not Delete)'!$A$1:$G$1000,7,false) -> 280 | J29: =10000*F29+10*E29+D29 -> 22720675 | L29: =IFERROR(__xludf.DUMMYFUNCTION("if(REGEXMATCH(vlookup(B29,'Kings Ratings'!$A$2:$C$1000,3,false),""Fishing""),""Yes"","""")"),"") | M29: =IFERROR(__xludf.DUMMYFUNCTION("if(REGEXMATCH(vlookup(B29,'Kings Ratings'!$A$2:$C$1000,3,false),""Crafting""),""Yes"","""")"),"Yes") -> Yes | N29: =IFERROR(__xludf.DUMMYFUNCTION("if(REGEXMATCH(vlookup(B29,'Kings Ratings'!$A$2:$C$1000,3,false),""Exploring""),""Yes"","""")"),"") | O29: =IFERROR(__xludf.DUMMYFUNCTION("if(REGEXMATCH(vlookup(B29,'Kings Ratings'!$A$2:$C$1000,3,false),""Farming""),""Yes"","""")"),"") | P29: =IFERROR(__xludf.DUMMYFUNCTION("if(REGEXMATCH(vlookup(B29,'Kings Ratings'!$A$2:$C$1000,3,false),""Cooking""),""Yes"","""")"),"") | Q29: =IFERROR(__xludf.DUMMYFUNCTION("if(REGEXMATCH(vlookup(B29,'Kings Ratings'!$A$2:$C$1000,3,false),""Event""),""Yes"","""")"),"")
A30: 310 | B30: Spiral Shell | C30: =CONCATENATE("((",B30,"))") -> ((Spiral Shell)) | D30: 41236 | E30: 23820 | F30: 7719 | G30: =VLOOKUP(B30,'Kings Ratings'!$A$2:$B$1000,2,false) -> 1 | H30: =if(G30=11,13,13-ROUNDDOWN(log(J30,4),0)) -> 0 | I30: =vlookup(A30,'202405 MM (Do Not Delete)'!$A$1:$G$1000,7,false) -> 232 | J30: =10000*F30+10*E30+D30 -> 77469436 | L30: =IFERROR(__xludf.DUMMYFUNCTION("if(REGEXMATCH(vlookup(B30,'Kings Ratings'!$A$2:$C$1000,3,false),""Fishing""),""Yes"","""")"),"Yes") -> Yes | M30: =IFERROR(__xludf.DUMMYFUNCTION("if(REGEXMATCH(vlookup(B30,'Kings Ratings'!$A$2:$C$1000,3,false),""Crafting""),""Yes"","""")"),"") | N30: =IFERROR(__xludf.DUMMYFUNCTION("if(REGEXMATCH(vlookup(B30,'Kings Ratings'!$A$2:$C$1000,3,false),""Exploring""),""Yes"","""")"),"") | O30: =IFERROR(__xludf.DUMMYFUNCTION("if(REGEXMATCH(vlookup(B30,'Kings Ratings'!$A$2:$C$1000,3,false),""Farming""),""Yes"","""")"),"") | P30: =IFERROR(__xludf.DUMMYFUNCTION("if(REGEXMATCH(vlookup(B30,'Kings Ratings'!$A$2:$C$1000,3,false),""Cooking""),""Yes"","""")"),"") | Q30: =IFERROR(__xludf.DUMMYFUNCTION("if(REGEXMATCH(vlookup(B30,'Kings Ratings'!$A$2:$C$1000,3,false),""Event""),""Yes"","""")"),"")
A31: 110 | B31: Leather | C31: =CONCATENATE("((",B31,"))") -> ((Leather)) | D31: 41041 | E31: 18077 | F31: 6888 | G31: =VLOOKUP(B31,'Kings Ratings'!$A$2:$B$1000,2,false) -> 1 | H31: =if(G31=11,13,13-ROUNDDOWN(log(J31,4),0)) -> 0 | I31: =vlookup(A31,'202405 MM (Do Not Delete)'!$A$1:$G$1000,7,false) -> 231 | J31: =10000*F31+10*E31+D31 -> 69101811 | L31: =IFERROR(__xludf.DUMMYFUNCTION("if(REGEXMATCH(vlookup(B31,'Kings Ratings'!$A$2:$C$1000,3,false),""Fishing""),""Yes"","""")"),"") | M31: =IFERROR(__xludf.DUMMYFUNCTION("if(REGEXMATCH(vlookup(B31,'Kings Ratings'!$A$2:$C$1000,3,false),""Crafting""),""Yes"","""")"),"Yes") -> Yes | N31: =IFERROR(__xludf.DUMMYFUNCTION("if(REGEXMATCH(vlookup(B31,'Kings Ratings'!$A$2:$C$1000,3,false),""Exploring""),""Yes"","""")"),"") | O31: =IFERROR(__xludf.DUMMYFUNCTION("if(REGEXMATCH(vlookup(B31,'Kings Ratings'!$A$2:$C$1000,3,false),""Farming""),""Yes"","""")"),"") | P31: =IFERROR(__xludf.DUMMYFUNCTION("if(REGEXMATCH(vlookup(B31,'Kings Ratings'!$A$2:$C$1000,3,false),""Cooking""),""Yes"","""")"),"") | Q31: =IFERROR(__xludf.DUMMYFUNCTION("if(REGEXMATCH(vlookup(B31,'Kings Ratings'!$A$2:$C$1000,3,false),""Event""),""Yes"","""")"),"")
A32: 101 | B32: Conch Shell | C32: =CONCATENATE("((",B32,"))") -> ((Conch Shell)) | D32: 40922 | E32: 27718 | F32: 15021 | G32: =VLOOKUP(B32,'Kings Ratings'!$A$2:$B$1000,2,false) -> 1 | H32: =if(G32=11,13,13-ROUNDDOWN(log(J32,4),0)) -> 0 | I32: =vlookup(A32,'202405 MM (Do Not Delete)'!$A$1:$G$1000,7,false) -> 210 | J32: =10000*F32+10*E32+D32 -> 150528102 | L32: =IFERROR(__xludf.DUMMYFUNCTION("if(REGEXMATCH(vlookup(B32,'Kings Ratings'!$A$2:$C$1000,3,false),""Fishing""),""Yes"","""")"),"Yes") -> Yes | M32: =IFERROR(__xludf.DUMMYFUNCTION("if(REGEXMATCH(vlookup(B32,'Kings Ratings'!$A$2:$C$1000,3,false),""Crafting""),""Yes"","""")"),"") | N32: =IFERROR(__xludf.DUMMYFUNCTION("if(REGEXMATCH(vlookup(B32,'Kings Ratings'!$A$2:$C$1000,3,false),""Exploring""),""Yes"","""")"),"") | O32: =IFERROR(__xludf.DUMMYFUNCTION("if(REGEXMATCH(vlookup(B32,'Kings Ratings'!$A$2:$C$1000,3,false),""Farming""),""Yes"","""")"),"") | P32: =IFERROR(__xludf.DUMMYFUNCTION("if(REGEXMATCH(vlookup(B32,'Kings Ratings'!$A$2:$C$1000,3,false),""Cooking""),""Yes"","""")"),"") | Q32: =IFERROR(__xludf.DUMMYFUNCTION("if(REGEXMATCH(vlookup(B32,'Kings Ratings'!$A$2:$C$1000,3,false),""Event""),""Yes"","""")"),"")
A33: 97 | B33: Clam Shell | C33: =CONCATENATE("((",B33,"))") -> ((Clam Shell)) | D33: 40826 | E33: 27710 | F33: 15023 | G33: =VLOOKUP(B33,'Kings Ratings'!$A$2:$B$1000,2,false) -> 1 | H33: =if(G33=11,13,13-ROUNDDOWN(log(J33,4),0)) -> 0 | I33: =vlookup(A33,'202405 MM (Do Not Delete)'!$A$1:$G$1000,7,false) -> 209 | J33: =10000*F33+10*E33+D33 -> 150547926 | L33: =IFERROR(__xludf.DUMMYFUNCTION("if(REGEXMATCH(vlookup(B33,'Kings Ratings'!$A$2:$C$1000,3,false),""Fishing""),""Yes"","""")"),"Yes") -> Yes | M33: =IFERROR(__xludf.DUMMYFUNCTION("if(REGEXMATCH(vlookup(B33,'Kings Ratings'!$A$2:$C$1000,3,false),""Crafting""),""Yes"","""")"),"") | N33: =IFERROR(__xludf.DUMMYFUNCTION("if(REGEXMATCH(vlookup(B33,'Kings Ratings'!$A$2:$C$1000,3,false),""Exploring""),""Yes"","""")"),"") | O33: =IFERROR(__xludf.DUMMYFUNCTION("if(REGEXMATCH(vlookup(B33,'Kings Ratings'!$A$2:$C$1000,3,false),""Farming""),""Yes"","""")"),"") | P33: =IFERROR(__xludf.DUMMYFUNCTION("if(REGEXMATCH(vlookup(B33,'Kings Ratings'!$A$2:$C$1000,3,false),""Cooking""),""Yes"","""")"),"") | Q33: =IFERROR(__xludf.DUMMYFUNCTION("if(REGEXMATCH(vlookup(B33,'Kings Ratings'!$A$2:$C$1000,3,false),""Event""),""Yes"","""")"),"")
A34: 311 | B34: Serpent Eel | C34: =CONCATENATE("((",B34,"))") -> ((Serpent Eel)) | D34: 40515 | E34: 23251 | F34: 7618 | G34: =VLOOKUP(B34,'Kings Ratings'!$A$2:$B$1000,2,false) -> 1 | H34: =if(G34=11,13,13-ROUNDDOWN(log(J34,4),0)) -> 0 | I34: =vlookup(A34,'202405 MM (Do Not Delete)'!$A$1:$G$1000,7,false) -> 233 | J34: =10000*F34+10*E34+D34 -> 76453025 | L34: =IFERROR(__xludf.DUMMYFUNCTION("if(REGEXMATCH(vlookup(B34,'Kings Ratings'!$A$2:$C$1000,3,false),""Fishing""),""Yes"","""")"),"Yes") -> Yes | M34: =IFERROR(__xludf.DUMMYFUNCTION("if(REGEXMATCH(vlookup(B34,'Kings Ratings'!$A$2:$C$1000,3,false),""Crafting""),""Yes"","""")"),"") | N34: =IFERROR(__xludf.DUMMYFUNCTION("if(REGEXMATCH(vlookup(B34,'Kings Ratings'!$A$2:$C$1000,3,false),""Exploring""),""Yes"","""")"),"") | O34: =IFERROR(__xludf.DUMMYFUNCTION("if(REGEXMATCH(vlookup(B34,'Kings Ratings'!$A$2:$C$1000,3,false),""Farming""),""Yes"","""")"),"") | P34: =IFERROR(__xludf.DUMMYFUNCTION("if(REGEXMATCH(vlookup(B34,'Kings Ratings'!$A$2:$C$1000,3,false),""Cooking""),""Yes"","""")"),"") | Q34: =IFERROR(__xludf.DUMMYFUNCTION("if(REGEXMATCH(vlookup(B34,'Kings Ratings'!$A$2:$C$1000,3,false),""Event""),""Yes"","""")"),"")
A35: 301 | B35: Fancy Pipe | C35: =CONCATENATE("((",B35,"))") -> ((Fancy Pipe)) | D35: 40088 | E35: 18245 | F35: 5929 | G35: =VLOOKUP(B35,'Kings Ratings'!$A$2:$B$1000,2,false) -> 1 | H35: =if(G35=11,13,13-ROUNDDOWN(log(J35,4),0)) -> 1 | I35: =vlookup(A35,'202405 MM (Do Not Delete)'!$A$1:$G$1000,7,false) -> 241 | J35: =10000*F35+10*E35+D35 -> 59512538 | L35: =IFERROR(__xludf.DUMMYFUNCTION("if(REGEXMATCH(vlookup(B35,'Kings Ratings'!$A$2:$C$1000,3,false),""Fishing""),""Yes"","""")"),"") | M35: =IFERROR(__xludf.DUMMYFUNCTION("if(REGEXMATCH(vlookup(B35,'Kings Ratings'!$A$2:$C$1000,3,false),""Crafting""),""Yes"","""")"),"Yes") -> Yes | N35: =IFERROR(__xludf.DUMMYFUNCTION("if(REGEXMATCH(vlookup(B35,'Kings Ratings'!$A$2:$C$1000,3,false),""Exploring""),""Yes"","""")"),"") | O35: =IFERROR(__xludf.DUMMYFUNCTION("if(REGEXMATCH(vlookup(B35,'Kings Ratings'!$A$2:$C$1000,3,false),""Farming""),""Yes"","""")"),"") | P35: =IFERROR(__xludf.DUMMYFUNCTION("if(REGEXMATCH(vlookup(B35,'Kings Ratings'!$A$2:$C$1000,3,false),""Cooking""),""Yes"","""")"),"") | Q35: =IFERROR(__xludf.DUMMYFUNCTION("if(REGEXMATCH(vlookup(B35,'Kings Ratings'!$A$2:$C$1000,3,false),""Event""),""Yes"","""")"),"")
A36: 312 | B36: Ruby Coral | C36: =CONCATENATE("((",B36,"))") -> ((Ruby Coral)) | D36: 39805 | E36: 22649 | F36: 7345 | G36: =VLOOKUP(B36,'Kings Ratings'!$A$2:$B$1000,2,false) -> 1 | H36: =if(G36=11,13,13-ROUNDDOWN(log(J36,4),0)) -> 0 | I36: =vlookup(A36,'202405 MM (Do Not Delete)'!$A$1:$G$1000,7,false) -> 234 | J36: =10000*F36+10*E36+D36 -> 73716295 | L36: =IFERROR(__xludf.DUMMYFUNCTION("if(REGEXMATCH(vlookup(B36,'Kings Ratings'!$A$2:$C$1000,3,false),""Fishing""),""Yes"","""")"),"Yes") -> Yes | M36: =IFERROR(__xludf.DUMMYFUNCTION("if(REGEXMATCH(vlookup(B36,'Kings Ratings'!$A$2:$C$1000,3,false),""Crafting""),""Yes"","""")"),"") | N36: =IFERROR(__xludf.DUMMYFUNCTION("if(REGEXMATCH(vlookup(B36,'Kings Ratings'!$A$2:$C$1000,3,false),""Exploring""),""Yes"","""")"),"") | O36: =IFERROR(__xludf.DUMMYFUNCTION("if(REGEXMATCH(vlookup(B36,'Kings Ratings'!$A$2:$C$1000,3,false),""Farming""),""Yes"","""")"),"") | P36: =IFERROR(__xludf.DUMMYFUNCTION("if(REGEXMATCH(vlookup(B36,'Kings Ratings'!$A$2:$C$1000,3,false),""Cooking""),""Yes"","""")"),"") | Q36: =IFERROR(__xludf.DUMMYFUNCTION("if(REGEXMATCH(vlookup(B36,'Kings Ratings'!$A$2:$C$1000,3,false),""Event""),""Yes"","""")"),"")
A37: 232 | B37: Flamejack | C37: =CONCATENATE("((",B37,"))") -> ((Flamejack)) | D37: 39632 | E37: 20827 | F37: 9228 | G37: =VLOOKUP(B37,'Kings Ratings'!$A$2:$B$1000,2,false) -> 1 | H37: =if(G37=11,13,13-ROUNDDOWN(log(J37,4),0)) -> 0 | I37: =vlookup(A37,'202405 MM (Do Not Delete)'!$A$1:$G$1000,7,false) -> 224 | J37: =10000*F37+10*E37+D37 -> 92527902 | L37: =IFERROR(__xludf.DUMMYFUNCTION("if(REGEXMATCH(vlookup(B37,'Kings Ratings'!$A$2:$C$1000,3,false),""Fishing""),""Yes"","""")"),"Yes") -> Yes | M37: =IFERROR(__xludf.DUMMYFUNCTION("if(REGEXMATCH(vlookup(B37,'Kings Ratings'!$A$2:$C$1000,3,false),""Crafting""),""Yes"","""")"),"") | N37: =IFERROR(__xludf.DUMMYFUNCTION("if(REGEXMATCH(vlookup(B37,'Kings Ratings'!$A$2:$C$1000,3,false),""Exploring""),""Yes"","""")"),"") | O37: =IFERROR(__xludf.DUMMYFUNCTION("if(REGEXMATCH(vlookup(B37,'Kings Ratings'!$A$2:$C$1000,3,false),""Farming""),""Yes"","""")"),"") | P37: =IFERROR(__xludf.DUMMYFUNCTION("if(REGEXMATCH(vlookup(B37,'Kings Ratings'!$A$2:$C$1000,3,false),""Cooking""),""Yes"","""")"),"") | Q37: =IFERROR(__xludf.DUMMYFUNCTION("if(REGEXMATCH(vlookup(B37,'Kings Ratings'!$A$2:$C$1000,3,false),""Event""),""Yes"","""")"),"")
A38: 86 | B38: Lemonade | C38: =CONCATENATE("((",B38,"))") -> ((Lemonade)) | D38: 39332 | E38: 17342 | F38: 4893 | G38: =VLOOKUP(B38,'Kings Ratings'!$A$2:$B$1000,2,false) -> 3 | H38: =if(G38=11,13,13-ROUNDDOWN(log(J38,4),0)) -> 1 | I38: =vlookup(A38,'202405 MM (Do Not Delete)'!$A$1:$G$1000,7,false) -> 242 | J38: =10000*F38+10*E38+D38 -> 49142752 | L38: =IFERROR(__xludf.DUMMYFUNCTION("if(REGEXMATCH(vlookup(B38,'Kings Ratings'!$A$2:$C$1000,3,false),""Fishing""),""Yes"","""")"),"") | M38: =IFERROR(__xludf.DUMMYFUNCTION("if(REGEXMATCH(vlookup(B38,'Kings Ratings'!$A$2:$C$1000,3,false),""Crafting""),""Yes"","""")"),"Yes") -> Yes | N38: =IFERROR(__xludf.DUMMYFUNCTION("if(REGEXMATCH(vlookup(B38,'Kings Ratings'!$A$2:$C$1000,3,false),""Exploring""),""Yes"","""")"),"") | O38: =IFERROR(__xludf.DUMMYFUNCTION("if(REGEXMATCH(vlookup(B38,'Kings Ratings'!$A$2:$C$1000,3,false),""Farming""),""Yes"","""")"),"") | P38: =IFERROR(__xludf.DUMMYFUNCTION("if(REGEXMATCH(vlookup(B38,'Kings Ratings'!$A$2:$C$1000,3,false),""Cooking""),""Yes"","""")"),"") | Q38: =IFERROR(__xludf.DUMMYFUNCTION("if(REGEXMATCH(vlookup(B38,'Kings Ratings'!$A$2:$C$1000,3,false),""Event""),""Yes"","""")"),"")
A39: 58 | B39: Small Prawn | C39: =CONCATENATE("((",B39,"))") -> ((Small Prawn)) | D39: 37609 | E39: 24636 | F39: 12347 | G39: =VLOOKUP(B39,'Kings Ratings'!$A$2:$B$1000,2,false) -> 1 | H39: =if(G39=11,13,13-ROUNDDOWN(log(J39,4),0)) -> 0 | I39: =vlookup(A39,'202405 MM (Do Not Delete)'!$A$1:$G$1000,7,false) -> 256 | J39: =10000*F39+10*E39+D39 -> 123753969 | L39: =IFERROR(__xludf.DUMMYFUNCTION("if(REGEXMATCH(vlookup(B39,'Kings Ratings'!$A$2:$C$1000,3,false),""Fishing""),""Yes"","""")"),"Yes") -> Yes | M39: =IFERROR(__xludf.DUMMYFUNCTION("if(REGEXMATCH(vlookup(B39,'Kings Ratings'!$A$2:$C$1000,3,false),""Crafting""),""Yes"","""")"),"") | N39: =IFERROR(__xludf.DUMMYFUNCTION("if(REGEXMATCH(vlookup(B39,'Kings Ratings'!$A$2:$C$1000,3,false),""Exploring""),""Yes"","""")"),"") | O39: =IFERROR(__xludf.DUMMYFUNCTION("if(REGEXMATCH(vlookup(B39,'Kings Ratings'!$A$2:$C$1000,3,false),""Farming""),""Yes"","""")"),"") | P39: =IFERROR(__xludf.DUMMYFUNCTION("if(REGEXMATCH(vlookup(B39,'Kings Ratings'!$A$2:$C$1000,3,false),""Cooking""),""Yes"","""")"),"") | Q39: =IFERROR(__xludf.DUMMYFUNCTION("if(REGEXMATCH(vlookup(B39,'Kings Ratings'!$A$2:$C$1000,3,false),""Event""),""Yes"","""")"),"")
A40: 392 | B40: Steel Wire | C40: =CONCATENATE("((",B40,"))") -> ((Steel Wire)) | D40: 37444 | E40: 20411 | F40: 8791 | G40: =VLOOKUP(B40,'Kings Ratings'!$A$2:$B$1000,2,false) -> 2 | H40: =if(G40=11,13,13-ROUNDDOWN(log(J40,4),0)) -> 0 | I40: =vlookup(A40,'202405 MM (Do Not Delete)'!$A$1:$G$1000,7,false) -> 222 | J40: =10000*F40+10*E40+D40 -> 88151554 | L40: =IFERROR(__xludf.DUMMYFUNCTION("if(REGEXMATCH(vlookup(B40,'Kings Ratings'!$A$2:$C$1000,3,false),""Fishing""),""Yes"","""")"),"") | M40: =IFERROR(__xludf.DUMMYFUNCTION("if(REGEXMATCH(vlookup(B40,'Kings Ratings'!$A$2:$C$1000,3,false),""Crafting""),""Yes"","""")"),"") | N40: =IFERROR(__xludf.DUMMYFUNCTION("if(REGEXMATCH(vlookup(B40,'Kings Ratings'!$A$2:$C$1000,3,false),""Exploring""),""Yes"","""")"),"") | O40: =IFERROR(__xludf.DUMMYFUNCTION("if(REGEXMATCH(vlookup(B40,'Kings Ratings'!$A$2:$C$1000,3,false),""Farming""),""Yes"","""")"),"") | P40: =IFERROR(__xludf.DUMMYFUNCTION("if(REGEXMATCH(vlookup(B40,'Kings Ratings'!$A$2:$C$1000,3,false),""Cooking""),""Yes"","""")"),"") | Q40: =IFERROR(__xludf.DUMMYFUNCTION("if(REGEXMATCH(vlookup(B40,'Kings Ratings'!$A$2:$C$1000,3,false),""Event""),""Yes"","""")"),"")
A41: 141 | B41: Shrimp | C41: =CONCATENATE("((",B41,"))") -> ((Shrimp)) | D41: 36339 | E41: 19810 | F41: 12900 | G41: =VLOOKUP(B41,'Kings Ratings'!$A$2:$B$1000,2,false) -> 1 | H41: =if(G41=11,13,13-ROUNDDOWN(log(J41,4),0)) -> 0 | I41: =vlookup(A41,'202405 MM (Do Not Delete)'!$A$1:$G$1000,7,false) -> 253 | J41: =10000*F41+10*E41+D41 -> 129234439 | L41: =IFERROR(__xludf.DUMMYFUNCTION("if(REGEXMATCH(vlookup(B41,'Kings Ratings'!$A$2:$C$1000,3,false),""Fishing""),""Yes"","""")"),"Yes") -> Yes | M41: =IFERROR(__xludf.DUMMYFUNCTION("if(REGEXMATCH(vlookup(B41,'Kings Ratings'!$A$2:$C$1000,3,false),""Crafting""),""Yes"","""")"),"") | N41: =IFERROR(__xludf.DUMMYFUNCTION("if(REGEXMATCH(vlookup(B41,'Kings Ratings'!$A$2:$C$1000,3,false),""Exploring""),""Yes"","""")"),"") | O41: =IFERROR(__xludf.DUMMYFUNCTION("if(REGEXMATCH(vlookup(B41,'Kings Ratings'!$A$2:$C$1000,3,false),""Farming""),""Yes"","""")"),"") | P41: =IFERROR(__xludf.DUMMYFUNCTION("if(REGEXMATCH(vlookup(B41,'Kings Ratings'!$A$2:$C$1000,3,false),""Cooking""),""Yes"","""")"),"") | Q41: =IFERROR(__xludf.DUMMYFUNCTION("if(REGEXMATCH(vlookup(B41,'Kings Ratings'!$A$2:$C$1000,3,false),""Event""),""Yes"","""")"),"")
A42: 87 | B42: Bone Fish | C42: =CONCATENATE("((",B42,"))") -> ((Bone Fish)) | D42: 36308 | E42: 23891 | F42: 12732 | G42: =VLOOKUP(B42,'Kings Ratings'!$A$2:$B$1000,2,false) -> 1 | H42: =if(G42=11,13,13-ROUNDDOWN(log(J42,4),0)) -> 0 | I42: =vlookup(A42,'202405 MM (Do Not Delete)'!$A$1:$G$1000,7,false) -> 223 | J42: =10000*F42+10*E42+D42 -> 127595218 | L42: =IFERROR(__xludf.DUMMYFUNCTION("if(REGEXMATCH(vlookup(B42,'Kings Ratings'!$A$2:$C$1000,3,false),""Fishing""),""Yes"","""")"),"Yes") -> Yes | M42: =IFERROR(__xludf.DUMMYFUNCTION("if(REGEXMATCH(vlookup(B42,'Kings Ratings'!$A$2:$C$1000,3,false),""Crafting""),""Yes"","""")"),"") | N42: =IFERROR(__xludf.DUMMYFUNCTION("if(REGEXMATCH(vlookup(B42,'Kings Ratings'!$A$2:$C$1000,3,false),""Exploring""),""Yes"","""")"),"") | O42: =IFERROR(__xludf.DUMMYFUNCTION("if(REGEXMATCH(vlookup(B42,'Kings Ratings'!$A$2:$C$1000,3,false),""Farming""),""Yes"","""")"),"") | P42: =IFERROR(__xludf.DUMMYFUNCTION("if(REGEXMATCH(vlookup(B42,'Kings Ratings'!$A$2:$C$1000,3,false),""Cooking""),""Yes"","""")"),"") | Q42: =IFERROR(__xludf.DUMMYFUNCTION("if(REGEXMATCH(vlookup(B42,'Kings Ratings'!$A$2:$C$1000,3,false),""Event""),""Yes"","""")"),"")
A43: 88 | B43: Sunfish | C43: =CONCATENATE("((",B43,"))") -> ((Sunfish)) | D43: 35260 | E43: 23845 | F43: 12724 | G43: =VLOOKUP(B43,'Kings Ratings'!$A$2:$B$1000,2,false) -> 1 | H43: =if(G43=11,13,13-ROUNDDOWN(log(J43,4),0)) -> 0 | I43: =vlookup(A43,'202405 MM (Do Not Delete)'!$A$1:$G$1000,7,false) -> 223 | J43: =10000*F43+10*E43+D43 -> 127513710 | L43: =IFERROR(__xludf.DUMMYFUNCTION("if(REGEXMATCH(vlookup(B43,'Kings Ratings'!$A$2:$C$1000,3,false),""Fishing""),""Yes"","""")"),"Yes") -> Yes | M43: =IFERROR(__xludf.DUMMYFUNCTION("if(REGEXMATCH(vlookup(B43,'Kings Ratings'!$A$2:$C$1000,3,false),""Crafting""),""Yes"","""")"),"") | N43: =IFERROR(__xludf.DUMMYFUNCTION("if(REGEXMATCH(vlookup(B43,'Kings Ratings'!$A$2:$C$1000,3,false),""Exploring""),""Yes"","""")"),"") | O43: =IFERROR(__xludf.DUMMYFUNCTION("if(REGEXMATCH(vlookup(B43,'Kings Ratings'!$A$2:$C$1000,3,false),""Farming""),""Yes"","""")"),"") | P43: =IFERROR(__xludf.DUMMYFUNCTION("if(REGEXMATCH(vlookup(B43,'Kings Ratings'!$A$2:$C$1000,3,false),""Cooking""),""Yes"","""")"),"") | Q43: =IFERROR(__xludf.DUMMYFUNCTION("if(REGEXMATCH(vlookup(B43,'Kings Ratings'!$A$2:$C$1000,3,false),""Event""),""Yes"","""")"),"")
A44: 570 | B44: Purple Butterfly Fish | C44: =CONCATENATE("((",B44,"))") -> ((Purple Butterfly Fish)) | D44: 34993 | E44: 28186 | F44: 15317 | G44: =VLOOKUP(B44,'Kings Ratings'!$A$2:$B$1000,2,false) -> 1 | H44: =if(G44=11,13,13-ROUNDDOWN(log(J44,4),0)) -> 0 | I44: =vlookup(A44,'202405 MM (Do Not Delete)'!$A$1:$G$1000,7,false) -> 205 | J44: =10000*F44+10*E44+D44 -> 153486853 | L44: =IFERROR(__xludf.DUMMYFUNCTION("if(REGEXMATCH(vlookup(B44,'Kings Ratings'!$A$2:$C$1000,3,false),""Fishing""),""Yes"","""")"),"Yes") -> Yes | M44: =IFERROR(__xludf.DUMMYFUNCTION("if(REGEXMATCH(vlookup(B44,'Kings Ratings'!$A$2:$C$1000,3,false),""Crafting""),""Yes"","""")"),"") | N44: =IFERROR(__xludf.DUMMYFUNCTION("if(REGEXMATCH(vlookup(B44,'Kings Ratings'!$A$2:$C$1000,3,false),""Exploring""),""Yes"","""")"),"") | O44: =IFERROR(__xludf.DUMMYFUNCTION("if(REGEXMATCH(vlookup(B44,'Kings Ratings'!$A$2:$C$1000,3,false),""Farming""),""Yes"","""")"),"") | P44: =IFERROR(__xludf.DUMMYFUNCTION("if(REGEXMATCH(vlookup(B44,'Kings Ratings'!$A$2:$C$1000,3,false),""Cooking""),""Yes"","""")"),"") | Q44: =IFERROR(__xludf.DUMMYFUNCTION("if(REGEXMATCH(vlookup(B44,'Kings Ratings'!$A$2:$C$1000,3,false),""Event""),""Yes"","""")"),"")
A45: 574 | B45: Crab | C45: =CONCATENATE("((",B45,"))") -> ((Crab)) | D45: 34674 | E45: 27718 | F45: 14764 | G45: =VLOOKUP(B45,'Kings Ratings'!$A$2:$B$1000,2,false) -> 1 | H45: =if(G45=11,13,13-ROUNDDOWN(log(J45,4),0)) -> 0 | I45: =vlookup(A45,'202405 MM (Do Not Delete)'!$A$1:$G$1000,7,false) -> 207 | J45: =10000*F45+10*E45+D45 -> 147951854 | L45: =IFERROR(__xludf.DUMMYFUNCTION("if(REGEXMATCH(vlookup(B45,'Kings Ratings'!$A$2:$C$1000,3,false),""Fishing""),""Yes"","""")"),"Yes") -> Yes | M45: =IFERROR(__xludf.DUMMYFUNCTION("if(REGEXMATCH(vlookup(B45,'Kings Ratings'!$A$2:$C$1000,3,false),""Crafting""),""Yes"","""")"),"") | N45: =IFERROR(__xludf.DUMMYFUNCTION("if(REGEXMATCH(vlookup(B45,'Kings Ratings'!$A$2:$C$1000,3,false),""Exploring""),""Yes"","""")"),"") | O45: =IFERROR(__xludf.DUMMYFUNCTION("if(REGEXMATCH(vlookup(B45,'Kings Ratings'!$A$2:$C$1000,3,false),""Farming""),""Yes"","""")"),"") | P45: =IFERROR(__xludf.DUMMYFUNCTION("if(REGEXMATCH(vlookup(B45,'Kings Ratings'!$A$2:$C$1000,3,false),""Cooking""),""Yes"","""")"),"") | Q45: =IFERROR(__xludf.DUMMYFUNCTION("if(REGEXMATCH(vlookup(B45,'Kings Ratings'!$A$2:$C$1000,3,false),""Event""),""Yes"","""")"),"")
A46: 275 | B46: Feed | C46: =CONCATENATE("((",B46,"))") -> ((Feed)) | D46: 34547 | E46: 12119 | F46: 693 | G46: =VLOOKUP(B46,'Kings Ratings'!$A$2:$B$1000,2,false) -> 5 | H46: =if(G46=11,13,13-ROUNDDOWN(log(J46,4),0)) -> 2 | I46: =vlookup(A46,'202405 MM (Do Not Delete)'!$A$1:$G$1000,7,false) | J46: =10000*F46+10*E46+D46 -> 7085737 | L46: =IFERROR(__xludf.DUMMYFUNCTION("if(REGEXMATCH(vlookup(B46,'Kings Ratings'!$A$2:$C$1000,3,false),""Fishing""),""Yes"","""")"),"") | M46: =IFERROR(__xludf.DUMMYFUNCTION("if(REGEXMATCH(vlookup(B46,'Kings Ratings'!$A$2:$C$1000,3,false),""Crafting""),""Yes"","""")"),"") | N46: =IFERROR(__xludf.DUMMYFUNCTION("if(REGEXMATCH(vlookup(B46,'Kings Ratings'!$A$2:$C$1000,3,false),""Exploring""),""Yes"","""")"),"") | O46: =IFERROR(__xludf.DUMMYFUNCTION("if(REGEXMATCH(vlookup(B46,'Kings Ratings'!$A$2:$C$1000,3,false),""Farming""),""Yes"","""")"),"") | P46: =IFERROR(__xludf.DUMMYFUNCTION("if(REGEXMATCH(vlookup(B46,'Kings Ratings'!$A$2:$C$1000,3,false),""Cooking""),""Yes"","""")"),"") | Q46: =IFERROR(__xludf.DUMMYFUNCTION("if(REGEXMATCH(vlookup(B46,'Kings Ratings'!$A$2:$C$1000,3,false),""Event""),""Yes"","""")"),"")
A47: 575 | B47: Green Barracuda | C47: =CONCATENATE("((",B47,"))") -> ((Green Barracuda)) | D47: 34124 | E47: 26841 | F47: 13125 | G47: =VLOOKUP(B47,'Kings Ratings'!$A$2:$B$1000,2,false) -> 1 | H47: =if(G47=11,13,13-ROUNDDOWN(log(J47,4),0)) -> 0 | I47: =vlookup(A47,'202405 MM (Do Not Delete)'!$A$1:$G$1000,7,false) -> 217 | J47: =10000*F47+10*E47+D47 -> 131552534 | L47: =IFERROR(__xludf.DUMMYFUNCTION("if(REGEXMATCH(vlookup(B47,'Kings Ratings'!$A$2:$C$1000,3,false),""Fishing""),""Yes"","""")"),"Yes") -> Yes | M47: =IFERROR(__xludf.DUMMYFUNCTION("if(REGEXMATCH(vlookup(B47,'Kings Ratings'!$A$2:$C$1000,3,false),""Crafting""),""Yes"","""")"),"") | N47: =IFERROR(__xludf.DUMMYFUNCTION("if(REGEXMATCH(vlookup(B47,'Kings Ratings'!$A$2:$C$1000,3,false),""Exploring""),""Yes"","""")"),"") | O47: =IFERROR(__xludf.DUMMYFUNCTION("if(REGEXMATCH(vlookup(B47,'Kings Ratings'!$A$2:$C$1000,3,false),""Farming""),""Yes"","""")"),"") | P47: =IFERROR(__xludf.DUMMYFUNCTION("if(REGEXMATCH(vlookup(B47,'Kings Ratings'!$A$2:$C$1000,3,false),""Cooking""),""Yes"","""")"),"") | Q47: =IFERROR(__xludf.DUMMYFUNCTION("if(REGEXMATCH(vlookup(B47,'Kings Ratings'!$A$2:$C$1000,3,false),""Event""),""Yes"","""")"),"")
A48: 98 | B48: Starfish | C48: =CONCATENATE("((",B48,"))") -> ((Starfish)) | D48: 34063 | E48: 21144 | F48: 10007 | G48: =VLOOKUP(B48,'Kings Ratings'!$A$2:$B$1000,2,false) -> 1 | H48: =if(G48=11,13,13-ROUNDDOWN(log(J48,4),0)) -> 0 | I48: =vlookup(A48,'202405 MM (Do Not Delete)'!$A$1:$G$1000,7,false) -> 221 | J48: =10000*F48+10*E48+D48 -> 100315503 | L48: =IFERROR(__xludf.DUMMYFUNCTION("if(REGEXMATCH(vlookup(B48,'Kings Ratings'!$A$2:$C$1000,3,false),""Fishing""),""Yes"","""")"),"Yes") -> Yes | M48: =IFERROR(__xludf.DUMMYFUNCTION("if(REGEXMATCH(vlookup(B48,'Kings Ratings'!$A$2:$C$1000,3,false),""Crafting""),""Yes"","""")"),"") | N48: =IFERROR(__xludf.DUMMYFUNCTION("if(REGEXMATCH(vlookup(B48,'Kings Ratings'!$A$2:$C$1000,3,false),""Exploring""),""Yes"","""")"),"") | O48: =IFERROR(__xludf.DUMMYFUNCTION("if(REGEXMATCH(vlookup(B48,'Kings Ratings'!$A$2:$C$1000,3,false),""Farming""),""Yes"","""")"),"") | P48: =IFERROR(__xludf.DUMMYFUNCTION("if(REGEXMATCH(vlookup(B48,'Kings Ratings'!$A$2:$C$1000,3,false),""Cooking""),""Yes"","""")"),"") | Q48: =IFERROR(__xludf.DUMMYFUNCTION("if(REGEXMATCH(vlookup(B48,'Kings Ratings'!$A$2:$C$1000,3,false),""Event""),""Yes"","""")"),"")
A49: 39 | B49: Crappie | C49: =CONCATENATE("((",B49,"))") -> ((Crappie)) | D49: 33859 | E49: 17348 | F49: 7297 | G49: =VLOOKUP(B49,'Kings Ratings'!$A$2:$B$1000,2,false) -> 1 | H49: =if(G49=11,13,13-ROUNDDOWN(log(J49,4),0)) -> 0 | I49: =vlookup(A49,'202405 MM (Do Not Delete)'!$A$1:$G$1000,7,false) -> 234 | J49: =10000*F49+10*E49+D49 -> 73177339 | L49: =IFERROR(__xludf.DUMMYFUNCTION("if(REGEXMATCH(vlookup(B49,'Kings Ratings'!$A$2:$C$1000,3,false),""Fishing""),""Yes"","""")"),"Yes") -> Yes | M49: =IFERROR(__xludf.DUMMYFUNCTION("if(REGEXMATCH(vlookup(B49,'Kings Ratings'!$A$2:$C$1000,3,false),""Crafting""),""Yes"","""")"),"") | N49: =IFERROR(__xludf.DUMMYFUNCTION("if(REGEXMATCH(vlookup(B49,'Kings Ratings'!$A$2:$C$1000,3,false),""Exploring""),""Yes"","""")"),"") | O49: =IFERROR(__xludf.DUMMYFUNCTION("if(REGEXMATCH(vlookup(B49,'Kings Ratings'!$A$2:$C$1000,3,false),""Farming""),""Yes"","""")"),"") | P49: =IFERROR(__xludf.DUMMYFUNCTION("if(REGEXMATCH(vlookup(B49,'Kings Ratings'!$A$2:$C$1000,3,false),""Cooking""),""Yes"","""")"),"") | Q49: =IFERROR(__xludf.DUMMYFUNCTION("if(REGEXMATCH(vlookup(B49,'Kings Ratings'!$A$2:$C$1000,3,false),""Event""),""Yes"","""")"),"")
A50: 104 | B50: Black Powder | C50: =CONCATENATE("((",B50,"))") -> ((Black Powder)) | D50: 33771 | E50: 15663 | F50: 5583 | G50: =VLOOKUP(B50,'Kings Ratings'!$A$2:$B$1000,2,false) -> 2 | H50: =if(G50=11,13,13-ROUNDDOWN(log(J50,4),0)) -> 1 | I50: =vlookup(A50,'202405 MM (Do Not Delete)'!$A$1:$G$1000,7,false) -> 243 | J50: =10000*F50+10*E50+D50 -> 56020401 | L50: =IFERROR(__xludf.DUMMYFUNCTION("if(REGEXMATCH(vlookup(B50,'Kings Ratings'!$A$2:$C$1000,3,false),""Fishing""),""Yes"","""")"),"") | M50: =IFERROR(__xludf.DUMMYFUNCTION("if(REGEXMATCH(vlookup(B50,'Kings Ratings'!$A$2:$C$1000,3,false),""Crafting""),""Yes"","""")"),"Yes") -> Yes | N50: =IFERROR(__xludf.DUMMYFUNCTION("if(REGEXMATCH(vlookup(B50,'Kings Ratings'!$A$2:$C$1000,3,false),""Exploring""),""Yes"","""")"),"") | O50: =IFERROR(__xludf.DUMMYFUNCTION("if(REGEXMATCH(vlookup(B50,'Kings Ratings'!$A$2:$C$1000,3,false),""Farming""),""Yes"","""")"),"") | P50: =IFERROR(__xludf.DUMMYFUNCTION("if(REGEXMATCH(vlookup(B50,'Kings Ratings'!$A$2:$C$1000,3,false),""Cooking""),""Yes"","""")"),"") | Q50: =IFERROR(__xludf.DUMMYFUNCTION("if(REGEXMATCH(vlookup(B50,'Kings Ratings'!$A$2:$C$1000,3,false),""Event""),""Yes"","""")"),"")
A51: 576 | B51: Mulberry Snapper | C51: =CONCATENATE("((",B51,"))") -> ((Mulberry Snapper)) | D51: 33592 | E51: 26201 | F51: 11902 | G51: =VLOOKUP(B51,'Kings Ratings'!$A$2:$B$1000,2,false) -> 1 | H51: =if(G51=11,13,13-ROUNDDOWN(log(J51,4),0)) -> 0 | I51: =vlookup(A51,'202405 MM (Do Not Delete)'!$A$1:$G$1000,7,false) -> 278 | J51: =10000*F51+10*E51+D51 -> 119315602 | L51: =IFERROR(__xludf.DUMMYFUNCTION("if(REGEXMATCH(vlookup(B51,'Kings Ratings'!$A$2:$C$1000,3,false),""Fishing""),""Yes"","""")"),"Yes") -> Yes | M51: =IFERROR(__xludf.DUMMYFUNCTION("if(REGEXMATCH(vlookup(B51,'Kings Ratings'!$A$2:$C$1000,3,false),""Crafting""),""Yes"","""")"),"") | N51: =IFERROR(__xludf.DUMMYFUNCTION("if(REGEXMATCH(vlookup(B51,'Kings Ratings'!$A$2:$C$1000,3,false),""Exploring""),""Yes"","""")"),"") | O51: =IFERROR(__xludf.DUMMYFUNCTION("if(REGEXMATCH(vlookup(B51,'Kings Ratings'!$A$2:$C$1000,3,false),""Farming""),""Yes"","""")"),"") | P51: =IFERROR(__xludf.DUMMYFUNCTION("if(REGEXMATCH(vlookup(B51,'Kings Ratings'!$A$2:$C$1000,3,false),""Cooking""),""Yes"","""")"),"") | Q51: =IFERROR(__xludf.DUMMYFUNCTION("if(REGEXMATCH(vlookup(B51,'Kings Ratings'!$A$2:$C$1000,3,false),""Event""),""Yes"","""")"),"")
A52: 56 | B52: Green Chromis | C52: =CONCATENATE("((",B52,"))") -> ((Green Chromis)) | D52: 33566 | E52: 18911 | F52: 7947 | G52: =VLOOKUP(B52,'Kings Ratings'!$A$2:$B$1000,2,false) -> 1 | H52: =if(G52=11,13,13-ROUNDDOWN(log(J52,4),0)) -> 0 | I52: =vlookup(A52,'202405 MM (Do Not Delete)'!$A$1:$G$1000,7,false) -> 228 | J52: =10000*F52+10*E52+D52 -> 79692676 | L52: =IFERROR(__xludf.DUMMYFUNCTION("if(REGEXMATCH(vlookup(B52,'Kings Ratings'!$A$2:$C$1000,3,false),""Fishing""),""Yes"","""")"),"Yes") -> Yes | M52: =IFERROR(__xludf.DUMMYFUNCTION("if(REGEXMATCH(vlookup(B52,'Kings Ratings'!$A$2:$C$1000,3,false),""Crafting""),""Yes"","""")"),"") | N52: =IFERROR(__xludf.DUMMYFUNCTION("if(REGEXMATCH(vlookup(B52,'Kings Ratings'!$A$2:$C$1000,3,false),""Exploring""),""Yes"","""")"),"") | O52: =IFERROR(__xludf.DUMMYFUNCTION("if(REGEXMATCH(vlookup(B52,'Kings Ratings'!$A$2:$C$1000,3,false),""Farming""),""Yes"","""")"),"") | P52: =IFERROR(__xludf.DUMMYFUNCTION("if(REGEXMATCH(vlookup(B52,'Kings Ratings'!$A$2:$C$1000,3,false),""Cooking""),""Yes"","""")"),"") | Q52: =IFERROR(__xludf.DUMMYFUNCTION("if(REGEXMATCH(vlookup(B52,'Kings Ratings'!$A$2:$C$1000,3,false),""Event""),""Yes"","""")"),"")
A53: 81 | B53: White Parchment | C53: =CONCATENATE("((",B53,"))") -> ((White Parchment)) | D53: 33381 | E53: 16679 | F53: 6158 | G53: =VLOOKUP(B53,'Kings Ratings'!$A$2:$B$1000,2,false) -> 1 | H53: =if(G53=11,13,13-ROUNDDOWN(log(J53,4),0)) -> 1 | I53: =vlookup(A53,'202405 MM (Do Not Delete)'!$A$1:$G$1000,7,false) -> 235 | J53: =10000*F53+10*E53+D53 -> 61780171 | L53: =IFERROR(__xludf.DUMMYFUNCTION("if(REGEXMATCH(vlookup(B53,'Kings Ratings'!$A$2:$C$1000,3,false),""Fishing""),""Yes"","""")"),"") | M53: =IFERROR(__xludf.DUMMYFUNCTION("if(REGEXMATCH(vlookup(B53,'Kings Ratings'!$A$2:$C$1000,3,false),""Crafting""),""Yes"","""")"),"Yes") -> Yes | N53: =IFERROR(__xludf.DUMMYFUNCTION("if(REGEXMATCH(vlookup(B53,'Kings Ratings'!$A$2:$C$1000,3,false),""Exploring""),""Yes"","""")"),"") | O53: =IFERROR(__xludf.DUMMYFUNCTION("if(REGEXMATCH(vlookup(B53,'Kings Ratings'!$A$2:$C$1000,3,false),""Farming""),""Yes"","""")"),"") | P53: =IFERROR(__xludf.DUMMYFUNCTION("if(REGEXMATCH(vlookup(B53,'Kings Ratings'!$A$2:$C$1000,3,false),""Cooking""),""Yes"","""")"),"") | Q53: =IFERROR(__xludf.DUMMYFUNCTION("if(REGEXMATCH(vlookup(B53,'Kings Ratings'!$A$2:$C$1000,3,false),""Event""),""Yes"","""")"),"")
A54: 387 | B54: Sand | C54: =CONCATENATE("((",B54,"))") -> ((Sand)) | D54: 33238 | E54: 25523 | F54: 14315 | G54: =VLOOKUP(B54,'Kings Ratings'!$A$2:$B$1000,2,false) -> 1 | H54: =if(G54=11,13,13-ROUNDDOWN(log(J54,4),0)) -> 0 | I54: =vlookup(A54,'202405 MM (Do Not Delete)'!$A$1:$G$1000,7,false) -> 212 | J54: =10000*F54+10*E54+D54 -> 143438468 | L54: =IFERROR(__xludf.DUMMYFUNCTION("if(REGEXMATCH(vlookup(B54,'Kings Ratings'!$A$2:$C$1000,3,false),""Fishing""),""Yes"","""")"),"") | M54: =IFERROR(__xludf.DUMMYFUNCTION("if(REGEXMATCH(vlookup(B54,'Kings Ratings'!$A$2:$C$1000,3,false),""Crafting""),""Yes"","""")"),"") | N54: =IFERROR(__xludf.DUMMYFUNCTION("if(REGEXMATCH(vlookup(B54,'Kings Ratings'!$A$2:$C$1000,3,false),""Exploring""),""Yes"","""")"),"Yes") -> Yes | O54: =IFERROR(__xludf.DUMMYFUNCTION("if(REGEXMATCH(vlookup(B54,'Kings Ratings'!$A$2:$C$1000,3,false),""Farming""),""Yes"","""")"),"") | P54: =IFERROR(__xludf.DUMMYFUNCTION("if(REGEXMATCH(vlookup(B54,'Kings Ratings'!$A$2:$C$1000,3,false),""Cooking""),""Yes"","""")"),"") | Q54: =IFERROR(__xludf.DUMMYFUNCTION("if(REGEXMATCH(vlookup(B54,'Kings Ratings'!$A$2:$C$1000,3,false),""Event""),""Yes"","""")"),"")
A55: 138 | B55: Green Jellyfish | C55: =CONCATENATE("((",B55,"))") -> ((Green Jellyfish)) | D55: 33222 | E55: 18209 | F55: 10242 | G55: =VLOOKUP(B55,'Kings Ratings'!$A$2:$B$1000,2,false) -> 2 | H55: =if(G55=11,13,13-ROUNDDOWN(log(J55,4),0)) -> 0 | I55: =vlookup(A55,'202405 MM (Do Not Delete)'!$A$1:$G$1000,7,false) -> 221 | J55: =10000*F55+10*E55+D55 -> 102635312 | L55: =IFERROR(__xludf.DUMMYFUNCTION("if(REGEXMATCH(vlookup(B55,'Kings Ratings'!$A$2:$C$1000,3,false),""Fishing""),""Yes"","""")"),"Yes") -> Yes | M55: =IFERROR(__xludf.DUMMYFUNCTION("if(REGEXMATCH(vlookup(B55,'Kings Ratings'!$A$2:$C$1000,3,false),""Crafting""),""Yes"","""")"),"") | N55: =IFERROR(__xludf.DUMMYFUNCTION("if(REGEXMATCH(vlookup(B55,'Kings Ratings'!$A$2:$C$1000,3,false),""Exploring""),""Yes"","""")"),"") | O55: =IFERROR(__xludf.DUMMYFUNCTION("if(REGEXMATCH(vlookup(B55,'Kings Ratings'!$A$2:$C$1000,3,false),""Farming""),""Yes"","""")"),"") | P55: =IFERROR(__xludf.DUMMYFUNCTION("if(REGEXMATCH(vlookup(B55,'Kings Ratings'!$A$2:$C$1000,3,false),""Cooking""),""Yes"","""")"),"") | Q55: =IFERROR(__xludf.DUMMYFUNCTION("if(REGEXMATCH(vlookup(B55,'Kings Ratings'!$A$2:$C$1000,3,false),""Event""),""Yes"","""")"),"")
A56: 577 | B56: Jumbo Fish | C56: =CONCATENATE("((",B56,"))") -> ((Jumbo Fish)) | D56: 33173 | E56: 25724 | F56: 11348 | G56: =VLOOKUP(B56,'Kings Ratings'!$A$2:$B$1000,2,false) -> 1 | H56: =if(G56=11,13,13-ROUNDDOWN(log(J56,4),0)) -> 0 | I56: =vlookup(A56,'202405 MM (Do Not Delete)'!$A$1:$G$1000,7,false) -> 264 | J56: =10000*F56+10*E56+D56 -> 113770413 | L56: =IFERROR(__xludf.DUMMYFUNCTION("if(REGEXMATCH(vlookup(B56,'Kings Ratings'!$A$2:$C$1000,3,false),""Fishing""),""Yes"","""")"),"Yes") -> Yes | M56: =IFERROR(__xludf.DUMMYFUNCTION("if(REGEXMATCH(vlookup(B56,'Kings Ratings'!$A$2:$C$1000,3,false),""Crafting""),""Yes"","""")"),"") | N56: =IFERROR(__xludf.DUMMYFUNCTION("if(REGEXMATCH(vlookup(B56,'Kings Ratings'!$A$2:$C$1000,3,false),""Exploring""),""Yes"","""")"),"") | O56: =IFERROR(__xludf.DUMMYFUNCTION("if(REGEXMATCH(vlookup(B56,'Kings Ratings'!$A$2:$C$1000,3,false),""Farming""),""Yes"","""")"),"") | P56: =IFERROR(__xludf.DUMMYFUNCTION("if(REGEXMATCH(vlookup(B56,'Kings Ratings'!$A$2:$C$1000,3,false),""Cooking""),""Yes"","""")"),"") | Q56: =IFERROR(__xludf.DUMMYFUNCTION("if(REGEXMATCH(vlookup(B56,'Kings Ratings'!$A$2:$C$1000,3,false),""Event""),""Yes"","""")"),"")
A57: 57 | B57: Blue Crab | C57: =CONCATENATE("((",B57,"))") -> ((Blue Crab)) | D57: 33137 | E57: 18856 | F57: 7936 | G57: =VLOOKUP(B57,'Kings Ratings'!$A$2:$B$1000,2,false) -> 2 | H57: =if(G57=11,13,13-ROUNDDOWN(log(J57,4),0)) -> 0 | I57: =vlookup(A57,'202405 MM (Do Not Delete)'!$A$1:$G$1000,7,false) -> 229 | J57: =10000*F57+10*E57+D57 -> 79581697 | L57: =IFERROR(__xludf.DUMMYFUNCTION("if(REGEXMATCH(vlookup(B57,'Kings Ratings'!$A$2:$C$1000,3,false),""Fishing""),""Yes"","""")"),"Yes") -> Yes | M57: =IFERROR(__xludf.DUMMYFUNCTION("if(REGEXMATCH(vlookup(B57,'Kings Ratings'!$A$2:$C$1000,3,false),""Crafting""),""Yes"","""")"),"") | N57: =IFERROR(__xludf.DUMMYFUNCTION("if(REGEXMATCH(vlookup(B57,'Kings Ratings'!$A$2:$C$1000,3,false),""Exploring""),""Yes"","""")"),"") | O57: =IFERROR(__xludf.DUMMYFUNCTION("if(REGEXMATCH(vlookup(B57,'Kings Ratings'!$A$2:$C$1000,3,false),""Farming""),""Yes"","""")"),"") | P57: =IFERROR(__xludf.DUMMYFUNCTION("if(REGEXMATCH(vlookup(B57,'Kings Ratings'!$A$2:$C$1000,3,false),""Cooking""),""Yes"","""")"),"") | Q57: =IFERROR(__xludf.DUMMYFUNCTION("if(REGEXMATCH(vlookup(B57,'Kings Ratings'!$A$2:$C$1000,3,false),""Event""),""Yes"","""")"),"")
A58: 579 | B58: Orcafish | C58: =CONCATENATE("((",B58,"))") -> ((Orcafish)) | D58: 32751 | E58: 25220 | F58: 10620 | G58: =VLOOKUP(B58,'Kings Ratings'!$A$2:$B$1000,2,false) -> 1 | H58: =if(G58=11,13,13-ROUNDDOWN(log(J58,4),0)) -> 0 | I58: =vlookup(A58,'202405 MM (Do Not Delete)'!$A$1:$G$1000,7,false) -> 266 | J58: =10000*F58+10*E58+D58 -> 106484951 | L58: =IFERROR(__xludf.DUMMYFUNCTION("if(REGEXMATCH(vlookup(B58,'Kings Ratings'!$A$2:$C$1000,3,false),""Fishing""),""Yes"","""")"),"Yes") -> Yes | M58: =IFERROR(__xludf.DUMMYFUNCTION("if(REGEXMATCH(vlookup(B58,'Kings Ratings'!$A$2:$C$1000,3,false),""Crafting""),""Yes"","""")"),"") | N58: =IFERROR(__xludf.DUMMYFUNCTION("if(REGEXMATCH(vlookup(B58,'Kings Ratings'!$A$2:$C$1000,3,false),""Exploring""),""Yes"","""")"),"") | O58: =IFERROR(__xludf.DUMMYFUNCTION("if(REGEXMATCH(vlookup(B58,'Kings Ratings'!$A$2:$C$1000,3,false),""Farming""),""Yes"","""")"),"") | P58: =IFERROR(__xludf.DUMMYFUNCTION("if(REGEXMATCH(vlookup(B58,'Kings Ratings'!$A$2:$C$1000,3,false),""Cooking""),""Yes"","""")"),"") | Q58: =IFERROR(__xludf.DUMMYFUNCTION("if(REGEXMATCH(vlookup(B58,'Kings Ratings'!$A$2:$C$1000,3,false),""Event""),""Yes"","""")"),"")
A59: 133 | B59: Blue Sea Bass | C59: =CONCATENATE("((",B59,"))") -> ((Blue Sea Bass)) | D59: 32618 | E59: 18049 | F59: 9339 | G59: =VLOOKUP(B59,'Kings Ratings'!$A$2:$B$1000,2,false) -> 2 | H59: =if(G59=11,13,13-ROUNDDOWN(log(J59,4),0)) -> 0 | I59: =vlookup(A59,'202405 MM (Do Not Delete)'!$A$1:$G$1000,7,false) -> 224 | J59: =10000*F59+10*E59+D59 -> 93603108 | L59: =IFERROR(__xludf.DUMMYFUNCTION("if(REGEXMATCH(vlookup(B59,'Kings Ratings'!$A$2:$C$1000,3,false),""Fishing""),""Yes"","""")"),"Yes") -> Yes | M59: =IFERROR(__xludf.DUMMYFUNCTION("if(REGEXMATCH(vlookup(B59,'Kings Ratings'!$A$2:$C$1000,3,false),""Crafting""),""Yes"","""")"),"") | N59: =IFERROR(__xludf.DUMMYFUNCTION("if(REGEXMATCH(vlookup(B59,'Kings Ratings'!$A$2:$C$1000,3,false),""Exploring""),""Yes"","""")"),"") | O59: =IFERROR(__xludf.DUMMYFUNCTION("if(REGEXMATCH(vlookup(B59,'Kings Ratings'!$A$2:$C$1000,3,false),""Farming""),""Yes"","""")"),"") | P59: =IFERROR(__xludf.DUMMYFUNCTION("if(REGEXMATCH(vlookup(B59,'Kings Ratings'!$A$2:$C$1000,3,false),""Cooking""),""Yes"","""")"),"") | Q59: =IFERROR(__xludf.DUMMYFUNCTION("if(REGEXMATCH(vlookup(B59,'Kings Ratings'!$A$2:$C$1000,3,false),""Event""),""Yes"","""")"),"")
A60: 578 | B60: Speckled Grouper | C60: =CONCATENATE("((",B60,"))") -> ((Speckled Grouper)) | D60: 32389 | E60: 24796 | F60: 10305 | G60: =VLOOKUP(B60,'Kings Ratings'!$A$2:$B$1000,2,false) -> 1 | H60: =if(G60=11,13,13-ROUNDDOWN(log(J60,4),0)) -> 0 | I60: =vlookup(A60,'202405 MM (Do Not Delete)'!$A$1:$G$1000,7,false) -> 268 | J60: =10000*F60+10*E60+D60 -> 103330349 | L60: =IFERROR(__xludf.DUMMYFUNCTION("if(REGEXMATCH(vlookup(B60,'Kings Ratings'!$A$2:$C$1000,3,false),""Fishing""),""Yes"","""")"),"Yes") -> Yes | M60: =IFERROR(__xludf.DUMMYFUNCTION("if(REGEXMATCH(vlookup(B60,'Kings Ratings'!$A$2:$C$1000,3,false),""Crafting""),""Yes"","""")"),"") | N60: =IFERROR(__xludf.DUMMYFUNCTION("if(REGEXMATCH(vlookup(B60,'Kings Ratings'!$A$2:$C$1000,3,false),""Exploring""),""Yes"","""")"),"") | O60: =IFERROR(__xludf.DUMMYFUNCTION("if(REGEXMATCH(vlookup(B60,'Kings Ratings'!$A$2:$C$1000,3,false),""Farming""),""Yes"","""")"),"") | P60: =IFERROR(__xludf.DUMMYFUNCTION("if(REGEXMATCH(vlookup(B60,'Kings Ratings'!$A$2:$C$1000,3,false),""Cooking""),""Yes"","""")"),"") | Q60: =IFERROR(__xludf.DUMMYFUNCTION("if(REGEXMATCH(vlookup(B60,'Kings Ratings'!$A$2:$C$1000,3,false),""Event""),""Yes"","""")"),"")
A61: 90 | B61: Blue Shell | C61: =CONCATENATE("((",B61,"))") -> ((Blue Shell)) | D61: 32063 | E61: 16832 | F61: 6867 | G61: =VLOOKUP(B61,'Kings Ratings'!$A$2:$B$1000,2,false) -> 3 | H61: =if(G61=11,13,13-ROUNDDOWN(log(J61,4),0)) -> 0 | I61: =vlookup(A61,'202405 MM (Do Not Delete)'!$A$1:$G$1000,7,false) -> 235 | J61: =10000*F61+10*E61+D61 -> 68870383 | L61: =IFERROR(__xludf.DUMMYFUNCTION("if(REGEXMATCH(vlookup(B61,'Kings Ratings'!$A$2:$C$1000,3,false),""Fishing""),""Yes"","""")"),"Yes") -> Yes | M61: =IFERROR(__xludf.DUMMYFUNCTION("if(REGEXMATCH(vlookup(B61,'Kings Ratings'!$A$2:$C$1000,3,false),""Crafting""),""Yes"","""")"),"") | N61: =IFERROR(__xludf.DUMMYFUNCTION("if(REGEXMATCH(vlookup(B61,'Kings Ratings'!$A$2:$C$1000,3,false),""Exploring""),""Yes"","""")"),"") | O61: =IFERROR(__xludf.DUMMYFUNCTION("if(REGEXMATCH(vlookup(B61,'Kings Ratings'!$A$2:$C$1000,3,false),""Farming""),""Yes"","""")"),"") | P61: =IFERROR(__xludf.DUMMYFUNCTION("if(REGEXMATCH(vlookup(B61,'Kings Ratings'!$A$2:$C$1000,3,false),""Cooking""),""Yes"","""")"),"") | Q61: =IFERROR(__xludf.DUMMYFUNCTION("if(REGEXMATCH(vlookup(B61,'Kings Ratings'!$A$2:$C$1000,3,false),""Event""),""Yes"","""")"),"")
A62: 317 | B62: Garnet | C62: =CONCATENATE("((",B62,"))") -> ((Garnet)) | D62: 32053 | E62: 14094 | F62: 4315 | G62: =VLOOKUP(B62,'Kings Ratings'!$A$2:$B$1000,2,false) -> 2 | H62: =if(G62=11,13,13-ROUNDDOWN(log(J62,4),0)) -> 1 | I62: =vlookup(A62,'202405 MM (Do Not Delete)'!$A$1:$G$1000,7,false) -> 247 | J62: =10000*F62+10*E62+D62 -> 43322993 | L62: =IFERROR(__xludf.DUMMYFUNCTION("if(REGEXMATCH(vlookup(B62,'Kings Ratings'!$A$2:$C$1000,3,false),""Fishing""),""Yes"","""")"),"") | M62: =IFERROR(__xludf.DUMMYFUNCTION("if(REGEXMATCH(vlookup(B62,'Kings Ratings'!$A$2:$C$1000,3,false),""Crafting""),""Yes"","""")"),"Yes") -> Yes | N62: =IFERROR(__xludf.DUMMYFUNCTION("if(REGEXMATCH(vlookup(B62,'Kings Ratings'!$A$2:$C$1000,3,false),""Exploring""),""Yes"","""")"),"") | O62: =IFERROR(__xludf.DUMMYFUNCTION("if(REGEXMATCH(vlookup(B62,'Kings Ratings'!$A$2:$C$1000,3,false),""Farming""),""Yes"","""")"),"") | P62: =IFERROR(__xludf.DUMMYFUNCTION("if(REGEXMATCH(vlookup(B62,'Kings Ratings'!$A$2:$C$1000,3,false),""Cooking""),""Yes"","""")"),"") | Q62: =IFERROR(__xludf.DUMMYFUNCTION("if(REGEXMATCH(vlookup(B62,'Kings Ratings'!$A$2:$C$1000,3,false),""Event""),""Yes"","""")"),"")
A63: 99 | B63: Clownfish | C63: =CONCATENATE("((",B63,"))") -> ((Clownfish)) | D63: 31552 | E63: 18362 | F63: 8669 | G63: =VLOOKUP(B63,'Kings Ratings'!$A$2:$B$1000,2,false) -> 2 | H63: =if(G63=11,13,13-ROUNDDOWN(log(J63,4),0)) -> 0 | I63: =vlookup(A63,'202405 MM (Do Not Delete)'!$A$1:$G$1000,7,false) -> 225 | J63: =10000*F63+10*E63+D63 -> 86905172 | L63: =IFERROR(__xludf.DUMMYFUNCTION("if(REGEXMATCH(vlookup(B63,'Kings Ratings'!$A$2:$C$1000,3,false),""Fishing""),""Yes"","""")"),"Yes") -> Yes | M63: =IFERROR(__xludf.DUMMYFUNCTION("if(REGEXMATCH(vlookup(B63,'Kings Ratings'!$A$2:$C$1000,3,false),""Crafting""),""Yes"","""")"),"") | N63: =IFERROR(__xludf.DUMMYFUNCTION("if(REGEXMATCH(vlookup(B63,'Kings Ratings'!$A$2:$C$1000,3,false),""Exploring""),""Yes"","""")"),"") | O63: =IFERROR(__xludf.DUMMYFUNCTION("if(REGEXMATCH(vlookup(B63,'Kings Ratings'!$A$2:$C$1000,3,false),""Farming""),""Yes"","""")"),"") | P63: =IFERROR(__xludf.DUMMYFUNCTION("if(REGEXMATCH(vlookup(B63,'Kings Ratings'!$A$2:$C$1000,3,false),""Cooking""),""Yes"","""")"),"") | Q63: =IFERROR(__xludf.DUMMYFUNCTION("if(REGEXMATCH(vlookup(B63,'Kings Ratings'!$A$2:$C$1000,3,false),""Event""),""Yes"","""")"),"")
A64: 134 | B64: Stingray | C64: =CONCATENATE("((",B64,"))") -> ((Stingray)) | D64: 31338 | E64: 17925 | F64: 8747 | G64: =VLOOKUP(B64,'Kings Ratings'!$A$2:$B$1000,2,false) -> 2 | H64: =if(G64=11,13,13-ROUNDDOWN(log(J64,4),0)) -> 0 | I64: =vlookup(A64,'202405 MM (Do Not Delete)'!$A$1:$G$1000,7,false) -> 226 | J64: =10000*F64+10*E64+D64 -> 87680588 | L64: =IFERROR(__xludf.DUMMYFUNCTION("if(REGEXMATCH(vlookup(B64,'Kings Ratings'!$A$2:$C$1000,3,false),""Fishing""),""Yes"","""")"),"Yes") -> Yes | M64: =IFERROR(__xludf.DUMMYFUNCTION("if(REGEXMATCH(vlookup(B64,'Kings Ratings'!$A$2:$C$1000,3,false),""Crafting""),""Yes"","""")"),"") | N64: =IFERROR(__xludf.DUMMYFUNCTION("if(REGEXMATCH(vlookup(B64,'Kings Ratings'!$A$2:$C$1000,3,false),""Exploring""),""Yes"","""")"),"") | O64: =IFERROR(__xludf.DUMMYFUNCTION("if(REGEXMATCH(vlookup(B64,'Kings Ratings'!$A$2:$C$1000,3,false),""Farming""),""Yes"","""")"),"") | P64: =IFERROR(__xludf.DUMMYFUNCTION("if(REGEXMATCH(vlookup(B64,'Kings Ratings'!$A$2:$C$1000,3,false),""Cooking""),""Yes"","""")"),"") | Q64: =IFERROR(__xludf.DUMMYFUNCTION("if(REGEXMATCH(vlookup(B64,'Kings Ratings'!$A$2:$C$1000,3,false),""Event""),""Yes"","""")"),"")
A65: 205 | B65: Red Starfish | C65: =CONCATENATE("((",B65,"))") -> ((Red Starfish)) | D65: 30987 | E65: 18326 | F65: 8666 | G65: =VLOOKUP(B65,'Kings Ratings'!$A$2:$B$1000,2,false) -> 2 | H65: =if(G65=11,13,13-ROUNDDOWN(log(J65,4),0)) -> 0 | I65: =vlookup(A65,'202405 MM (Do Not Delete)'!$A$1:$G$1000,7,false) -> 226 | J65: =10000*F65+10*E65+D65 -> 86874247 | L65: =IFERROR(__xludf.DUMMYFUNCTION("if(REGEXMATCH(vlookup(B65,'Kings Ratings'!$A$2:$C$1000,3,false),""Fishing""),""Yes"","""")"),"Yes") -> Yes | M65: =IFERROR(__xludf.DUMMYFUNCTION("if(REGEXMATCH(vlookup(B65,'Kings Ratings'!$A$2:$C$1000,3,false),""Crafting""),""Yes"","""")"),"") | N65: =IFERROR(__xludf.DUMMYFUNCTION("if(REGEXMATCH(vlookup(B65,'Kings Ratings'!$A$2:$C$1000,3,false),""Exploring""),""Yes"","""")"),"") | O65: =IFERROR(__xludf.DUMMYFUNCTION("if(REGEXMATCH(vlookup(B65,'Kings Ratings'!$A$2:$C$1000,3,false),""Farming""),""Yes"","""")"),"") | P65: =IFERROR(__xludf.DUMMYFUNCTION("if(REGEXMATCH(vlookup(B65,'Kings Ratings'!$A$2:$C$1000,3,false),""Cooking""),""Yes"","""")"),"") | Q65: =IFERROR(__xludf.DUMMYFUNCTION("if(REGEXMATCH(vlookup(B65,'Kings Ratings'!$A$2:$C$1000,3,false),""Event""),""Yes"","""")"),"")
A66: 119 | B66: Jellyfish | C66: =CONCATENATE("((",B66,"))") -> ((Jellyfish)) | D66: 30823 | E66: 17425 | F66: 7859 | G66: =VLOOKUP(B66,'Kings Ratings'!$A$2:$B$1000,2,false) -> 2 | H66: =if(G66=11,13,13-ROUNDDOWN(log(J66,4),0)) -> 0 | I66: =vlookup(A66,'202405 MM (Do Not Delete)'!$A$1:$G$1000,7,false) -> 231 | J66: =10000*F66+10*E66+D66 -> 78795073 | L66: =IFERROR(__xludf.DUMMYFUNCTION("if(REGEXMATCH(vlookup(B66,'Kings Ratings'!$A$2:$C$1000,3,false),""Fishing""),""Yes"","""")"),"Yes") -> Yes | M66: =IFERROR(__xludf.DUMMYFUNCTION("if(REGEXMATCH(vlookup(B66,'Kings Ratings'!$A$2:$C$1000,3,false),""Crafting""),""Yes"","""")"),"") | N66: =IFERROR(__xludf.DUMMYFUNCTION("if(REGEXMATCH(vlookup(B66,'Kings Ratings'!$A$2:$C$1000,3,false),""Exploring""),""Yes"","""")"),"") | O66: =IFERROR(__xludf.DUMMYFUNCTION("if(REGEXMATCH(vlookup(B66,'Kings Ratings'!$A$2:$C$1000,3,false),""Farming""),""Yes"","""")"),"") | P66: =IFERROR(__xludf.DUMMYFUNCTION("if(REGEXMATCH(vlookup(B66,'Kings Ratings'!$A$2:$C$1000,3,false),""Cooking""),""Yes"","""")"),"") | Q66: =IFERROR(__xludf.DUMMYFUNCTION("if(REGEXMATCH(vlookup(B66,'Kings Ratings'!$A$2:$C$1000,3,false),""Event""),""Yes"","""")"),"")
A67: 233 | B67: Redgill | C67: =CONCATENATE("((",B67,"))") -> ((Redgill)) | D67: 30695 | E67: 17046 | F67: 6730 | G67: =VLOOKUP(B67,'Kings Ratings'!$A$2:$B$1000,2,false) -> 1 | H67: =if(G67=11,13,13-ROUNDDOWN(log(J67,4),0)) -> 0 | I67: =vlookup(A67,'202405 MM (Do Not Delete)'!$A$1:$G$1000,7,false) -> 236 | J67: =10000*F67+10*E67+D67 -> 67501155 | L67: =IFERROR(__xludf.DUMMYFUNCTION("if(REGEXMATCH(vlookup(B67,'Kings Ratings'!$A$2:$C$1000,3,false),""Fishing""),""Yes"","""")"),"Yes") -> Yes | M67: =IFERROR(__xludf.DUMMYFUNCTION("if(REGEXMATCH(vlookup(B67,'Kings Ratings'!$A$2:$C$1000,3,false),""Crafting""),""Yes"","""")"),"") | N67: =IFERROR(__xludf.DUMMYFUNCTION("if(REGEXMATCH(vlookup(B67,'Kings Ratings'!$A$2:$C$1000,3,false),""Exploring""),""Yes"","""")"),"") | O67: =IFERROR(__xludf.DUMMYFUNCTION("if(REGEXMATCH(vlookup(B67,'Kings Ratings'!$A$2:$C$1000,3,false),""Farming""),""Yes"","""")"),"") | P67: =IFERROR(__xludf.DUMMYFUNCTION("if(REGEXMATCH(vlookup(B67,'Kings Ratings'!$A$2:$C$1000,3,false),""Cooking""),""Yes"","""")"),"") | Q67: =IFERROR(__xludf.DUMMYFUNCTION("if(REGEXMATCH(vlookup(B67,'Kings Ratings'!$A$2:$C$1000,3,false),""Event""),""Yes"","""")"),"")
A68: 100 | B68: Pearl | C68: =CONCATENATE("((",B68,"))") -> ((Pearl)) | D68: 30650 | E68: 18275 | F68: 8050 | G68: =VLOOKUP(B68,'Kings Ratings'!$A$2:$B$1000,2,false) -> 1 | H68: =if(G68=11,13,13-ROUNDDOWN(log(J68,4),0)) -> 0 | I68: =vlookup(A68,'202405 MM (Do Not Delete)'!$A$1:$G$1000,7,false) -> 228 | J68: =10000*F68+10*E68+D68 -> 80713400 | L68: =IFERROR(__xludf.DUMMYFUNCTION("if(REGEXMATCH(vlookup(B68,'Kings Ratings'!$A$2:$C$1000,3,false),""Fishing""),""Yes"","""")"),"Yes") -> Yes | M68: =IFERROR(__xludf.DUMMYFUNCTION("if(REGEXMATCH(vlookup(B68,'Kings Ratings'!$A$2:$C$1000,3,false),""Crafting""),""Yes"","""")"),"") | N68: =IFERROR(__xludf.DUMMYFUNCTION("if(REGEXMATCH(vlookup(B68,'Kings Ratings'!$A$2:$C$1000,3,false),""Exploring""),""Yes"","""")"),"") | O68: =IFERROR(__xludf.DUMMYFUNCTION("if(REGEXMATCH(vlookup(B68,'Kings Ratings'!$A$2:$C$1000,3,false),""Farming""),""Yes"","""")"),"") | P68: =IFERROR(__xludf.DUMMYFUNCTION("if(REGEXMATCH(vlookup(B68,'Kings Ratings'!$A$2:$C$1000,3,false),""Cooking""),""Yes"","""")"),"") | Q68: =IFERROR(__xludf.DUMMYFUNCTION("if(REGEXMATCH(vlookup(B68,'Kings Ratings'!$A$2:$C$1000,3,false),""Event""),""Yes"","""")"),"")
A69: 200 | B69: Blue Tiger Fish | C69: =CONCATENATE("((",B69,"))") -> ((Blue Tiger Fish)) | D69: 29738 | E69: 17200 | F69: 7446 | G69: =VLOOKUP(B69,'Kings Ratings'!$A$2:$B$1000,2,false) -> 2 | H69: =if(G69=11,13,13-ROUNDDOWN(log(J69,4),0)) -> 0 | I69: =vlookup(A69,'202405 MM (Do Not Delete)'!$A$1:$G$1000,7,false) -> 232 | J69: =10000*F69+10*E69+D69 -> 74661738 | L69: =IFERROR(__xludf.DUMMYFUNCTION("if(REGEXMATCH(vlookup(B69,'Kings Ratings'!$A$2:$C$1000,3,false),""Fishing""),""Yes"","""")"),"Yes") -> Yes | M69: =IFERROR(__xludf.DUMMYFUNCTION("if(REGEXMATCH(vlookup(B69,'Kings Ratings'!$A$2:$C$1000,3,false),""Crafting""),""Yes"","""")"),"") | N69: =IFERROR(__xludf.DUMMYFUNCTION("if(REGEXMATCH(vlookup(B69,'Kings Ratings'!$A$2:$C$1000,3,false),""Exploring""),""Yes"","""")"),"") | O69: =IFERROR(__xludf.DUMMYFUNCTION("if(REGEXMATCH(vlookup(B69,'Kings Ratings'!$A$2:$C$1000,3,false),""Farming""),""Yes"","""")"),"") | P69: =IFERROR(__xludf.DUMMYFUNCTION("if(REGEXMATCH(vlookup(B69,'Kings Ratings'!$A$2:$C$1000,3,false),""Cooking""),""Yes"","""")"),"") | Q69: =IFERROR(__xludf.DUMMYFUNCTION("if(REGEXMATCH(vlookup(B69,'Kings Ratings'!$A$2:$C$1000,3,false),""Event""),""Yes"","""")"),"")
A70: 236 | B70: Hammer | C70: =CONCATENATE("((",B70,"))") -> ((Hammer)) | D70: 28607 | E70: 12771 | F70: 2337 | G70: =VLOOKUP(B70,'Kings Ratings'!$A$2:$B$1000,2,false) -> 1 | H70: =if(G70=11,13,13-ROUNDDOWN(log(J70,4),0)) -> 1 | I70: =vlookup(A70,'202405 MM (Do Not Delete)'!$A$1:$G$1000,7,false) -> 289 | J70: =10000*F70+10*E70+D70 -> 23526317 | L70: =IFERROR(__xludf.DUMMYFUNCTION("if(REGEXMATCH(vlookup(B70,'Kings Ratings'!$A$2:$C$1000,3,false),""Fishing""),""Yes"","""")"),"") | M70: =IFERROR(__xludf.DUMMYFUNCTION("if(REGEXMATCH(vlookup(B70,'Kings Ratings'!$A$2:$C$1000,3,false),""Crafting""),""Yes"","""")"),"Yes") -> Yes | N70: =IFERROR(__xludf.DUMMYFUNCTION("if(REGEXMATCH(vlookup(B70,'Kings Ratings'!$A$2:$C$1000,3,false),""Exploring""),""Yes"","""")"),"") | O70: =IFERROR(__xludf.DUMMYFUNCTION("if(REGEXMATCH(vlookup(B70,'Kings Ratings'!$A$2:$C$1000,3,false),""Farming""),""Yes"","""")"),"") | P70: =IFERROR(__xludf.DUMMYFUNCTION("if(REGEXMATCH(vlookup(B70,'Kings Ratings'!$A$2:$C$1000,3,false),""Cooking""),""Yes"","""")"),"") | Q70: =IFERROR(__xludf.DUMMYFUNCTION("if(REGEXMATCH(vlookup(B70,'Kings Ratings'!$A$2:$C$1000,3,false),""Event""),""Yes"","""")"),"")
A71: 201 | B71: Fluorifish | C71: =CONCATENATE("((",B71,"))") -> ((Fluorifish)) | D71: 28119 | E71: 16707 | F71: 6720 | G71: =VLOOKUP(B71,'Kings Ratings'!$A$2:$B$1000,2,false) -> 3 | H71: =if(G71=11,13,13-ROUNDDOWN(log(J71,4),0)) -> 0 | I71: =vlookup(A71,'202405 MM (Do Not Delete)'!$A$1:$G$1000,7,false) -> 238 | J71: =10000*F71+10*E71+D71 -> 67395189 | L71: =IFERROR(__xludf.DUMMYFUNCTION("if(REGEXMATCH(vlookup(B71,'Kings Ratings'!$A$2:$C$1000,3,false),""Fishing""),""Yes"","""")"),"Yes") -> Yes | M71: =IFERROR(__xludf.DUMMYFUNCTION("if(REGEXMATCH(vlookup(B71,'Kings Ratings'!$A$2:$C$1000,3,false),""Crafting""),""Yes"","""")"),"") | N71: =IFERROR(__xludf.DUMMYFUNCTION("if(REGEXMATCH(vlookup(B71,'Kings Ratings'!$A$2:$C$1000,3,false),""Exploring""),""Yes"","""")"),"") | O71: =IFERROR(__xludf.DUMMYFUNCTION("if(REGEXMATCH(vlookup(B71,'Kings Ratings'!$A$2:$C$1000,3,false),""Farming""),""Yes"","""")"),"") | P71: =IFERROR(__xludf.DUMMYFUNCTION("if(REGEXMATCH(vlookup(B71,'Kings Ratings'!$A$2:$C$1000,3,false),""Cooking""),""Yes"","""")"),"") | Q71: =IFERROR(__xludf.DUMMYFUNCTION("if(REGEXMATCH(vlookup(B71,'Kings Ratings'!$A$2:$C$1000,3,false),""Event""),""Yes"","""")"),"")
A72: 19 | B72: Carrot | C72: =CONCATENATE("((",B72,"))") -> ((Carrot)) | D72: 28046 | E72: 10587 | F72: 2001 | G72: =VLOOKUP(B72,'Kings Ratings'!$A$2:$B$1000,2,false) -> 3 | H72: =if(G72=11,13,13-ROUNDDOWN(log(J72,4),0)) -> 1 | I72: =vlookup(A72,'202405 MM (Do Not Delete)'!$A$1:$G$1000,7,false) -> 283 | J72: =10000*F72+10*E72+D72 -> 20143916 | L72: =IFERROR(__xludf.DUMMYFUNCTION("if(REGEXMATCH(vlookup(B72,'Kings Ratings'!$A$2:$C$1000,3,false),""Fishing""),""Yes"","""")"),"") | M72: =IFERROR(__xludf.DUMMYFUNCTION("if(REGEXMATCH(vlookup(B72,'Kings Ratings'!$A$2:$C$1000,3,false),""Crafting""),""Yes"","""")"),"") | N72: =IFERROR(__xludf.DUMMYFUNCTION("if(REGEXMATCH(vlookup(B72,'Kings Ratings'!$A$2:$C$1000,3,false),""Exploring""),""Yes"","""")"),"") | O72: =IFERROR(__xludf.DUMMYFUNCTION("if(REGEXMATCH(vlookup(B72,'Kings Ratings'!$A$2:$C$1000,3,false),""Farming""),""Yes"","""")"),"Yes") -> Yes | P72: =IFERROR(__xludf.DUMMYFUNCTION("if(REGEXMATCH(vlookup(B72,'Kings Ratings'!$A$2:$C$1000,3,false),""Cooking""),""Yes"","""")"),"") | Q72: =IFERROR(__xludf.DUMMYFUNCTION("if(REGEXMATCH(vlookup(B72,'Kings Ratings'!$A$2:$C$1000,3,false),""Event""),""Yes"","""")"),"")
A73: 143 | B73: Emerald | C73: =CONCATENATE("((",B73,"))") -> ((Emerald)) | D73: 27939 | E73: 15316 | F73: 5759 | G73: =VLOOKUP(B73,'Kings Ratings'!$A$2:$B$1000,2,false) -> 1 | H73: =if(G73=11,13,13-ROUNDDOWN(log(J73,4),0)) -> 1 | I73: =vlookup(A73,'202405 MM (Do Not Delete)'!$A$1:$G$1000,7,false) -> 238 | J73: =10000*F73+10*E73+D73 -> 57771099 | L73: =IFERROR(__xludf.DUMMYFUNCTION("if(REGEXMATCH(vlookup(B73,'Kings Ratings'!$A$2:$C$1000,3,false),""Fishing""),""Yes"","""")"),"") | M73: =IFERROR(__xludf.DUMMYFUNCTION("if(REGEXMATCH(vlookup(B73,'Kings Ratings'!$A$2:$C$1000,3,false),""Crafting""),""Yes"","""")"),"Yes") -> Yes | N73: =IFERROR(__xludf.DUMMYFUNCTION("if(REGEXMATCH(vlookup(B73,'Kings Ratings'!$A$2:$C$1000,3,false),""Exploring""),""Yes"","""")"),"") | O73: =IFERROR(__xludf.DUMMYFUNCTION("if(REGEXMATCH(vlookup(B73,'Kings Ratings'!$A$2:$C$1000,3,false),""Farming""),""Yes"","""")"),"") | P73: =IFERROR(__xludf.DUMMYFUNCTION("if(REGEXMATCH(vlookup(B73,'Kings Ratings'!$A$2:$C$1000,3,false),""Cooking""),""Yes"","""")"),"") | Q73: =IFERROR(__xludf.DUMMYFUNCTION("if(REGEXMATCH(vlookup(B73,'Kings Ratings'!$A$2:$C$1000,3,false),""Event""),""Yes"","""")"),"")
A74: 199 | B74: Globber | C74: =CONCATENATE("((",B74,"))") -> ((Globber)) | D74: 27932 | E74: 17339 | F74: 7981 | G74: =VLOOKUP(B74,'Kings Ratings'!$A$2:$B$1000,2,false) -> 4 | H74: =if(G74=11,13,13-ROUNDDOWN(log(J74,4),0)) -> 0 | I74: =vlookup(A74,'202405 MM (Do Not Delete)'!$A$1:$G$1000,7,false) -> 244 | J74: =10000*F74+10*E74+D74 -> 80011322 | L74: =IFERROR(__xludf.DUMMYFUNCTION("if(REGEXMATCH(vlookup(B74,'Kings Ratings'!$A$2:$C$1000,3,false),""Fishing""),""Yes"","""")"),"Yes") -> Yes | M74: =IFERROR(__xludf.DUMMYFUNCTION("if(REGEXMATCH(vlookup(B74,'Kings Ratings'!$A$2:$C$1000,3,false),""Crafting""),""Yes"","""")"),"") | N74: =IFERROR(__xludf.DUMMYFUNCTION("if(REGEXMATCH(vlookup(B74,'Kings Ratings'!$A$2:$C$1000,3,false),""Exploring""),""Yes"","""")"),"") | O74: =IFERROR(__xludf.DUMMYFUNCTION("if(REGEXMATCH(vlookup(B74,'Kings Ratings'!$A$2:$C$1000,3,false),""Farming""),""Yes"","""")"),"") | P74: =IFERROR(__xludf.DUMMYFUNCTION("if(REGEXMATCH(vlookup(B74,'Kings Ratings'!$A$2:$C$1000,3,false),""Cooking""),""Yes"","""")"),"") | Q74: =IFERROR(__xludf.DUMMYFUNCTION("if(REGEXMATCH(vlookup(B74,'Kings Ratings'!$A$2:$C$1000,3,false),""Event""),""Yes"","""")"),"")
A75: 130 | B75: Iron Cup | C75: =CONCATENATE("((",B75,"))") -> ((Iron Cup)) | D75: 27793 | E75: 17761 | F75: 8356 | G75: =VLOOKUP(B75,'Kings Ratings'!$A$2:$B$1000,2,false) -> 1 | H75: =if(G75=11,13,13-ROUNDDOWN(log(J75,4),0)) -> 0 | I75: =vlookup(A75,'202405 MM (Do Not Delete)'!$A$1:$G$1000,7,false) -> 227 | J75: =10000*F75+10*E75+D75 -> 83765403 | L75: =IFERROR(__xludf.DUMMYFUNCTION("if(REGEXMATCH(vlookup(B75,'Kings Ratings'!$A$2:$C$1000,3,false),""Fishing""),""Yes"","""")"),"") | M75: =IFERROR(__xludf.DUMMYFUNCTION("if(REGEXMATCH(vlookup(B75,'Kings Ratings'!$A$2:$C$1000,3,false),""Crafting""),""Yes"","""")"),"Yes") -> Yes | N75: =IFERROR(__xludf.DUMMYFUNCTION("if(REGEXMATCH(vlookup(B75,'Kings Ratings'!$A$2:$C$1000,3,false),""Exploring""),""Yes"","""")"),"") | O75: =IFERROR(__xludf.DUMMYFUNCTION("if(REGEXMATCH(vlookup(B75,'Kings Ratings'!$A$2:$C$1000,3,false),""Farming""),""Yes"","""")"),"") | P75: =IFERROR(__xludf.DUMMYFUNCTION("if(REGEXMATCH(vlookup(B75,'Kings Ratings'!$A$2:$C$1000,3,false),""Cooking""),""Yes"","""")"),"") | Q75: =IFERROR(__xludf.DUMMYFUNCTION("if(REGEXMATCH(vlookup(B75,'Kings Ratings'!$A$2:$C$1000,3,false),""Event""),""Yes"","""")"),"")
A76: 114 | B76: Marlin | C76: =CONCATENATE("((",B76,"))") -> ((Marlin)) | D76: 27473 | E76: 16255 | F76: 6277 | G76: =VLOOKUP(B76,'Kings Ratings'!$A$2:$B$1000,2,false) -> 3 | H76: =if(G76=11,13,13-ROUNDDOWN(log(J76,4),0)) -> 1 | I76: =vlookup(A76,'202405 MM (Do Not Delete)'!$A$1:$G$1000,7,false) -> 240 | J76: =10000*F76+10*E76+D76 -> 62960023 | L76: =IFERROR(__xludf.DUMMYFUNCTION("if(REGEXMATCH(vlookup(B76,'Kings Ratings'!$A$2:$C$1000,3,false),""Fishing""),""Yes"","""")"),"Yes") -> Yes | M76: =IFERROR(__xludf.DUMMYFUNCTION("if(REGEXMATCH(vlookup(B76,'Kings Ratings'!$A$2:$C$1000,3,false),""Crafting""),""Yes"","""")"),"") | N76: =IFERROR(__xludf.DUMMYFUNCTION("if(REGEXMATCH(vlookup(B76,'Kings Ratings'!$A$2:$C$1000,3,false),""Exploring""),""Yes"","""")"),"") | O76: =IFERROR(__xludf.DUMMYFUNCTION("if(REGEXMATCH(vlookup(B76,'Kings Ratings'!$A$2:$C$1000,3,false),""Farming""),""Yes"","""")"),"") | P76: =IFERROR(__xludf.DUMMYFUNCTION("if(REGEXMATCH(vlookup(B76,'Kings Ratings'!$A$2:$C$1000,3,false),""Cooking""),""Yes"","""")"),"") | Q76: =IFERROR(__xludf.DUMMYFUNCTION("if(REGEXMATCH(vlookup(B76,'Kings Ratings'!$A$2:$C$1000,3,false),""Event""),""Yes"","""")"),"")
A77: 316 | B77: Garnet Ring | C77: =CONCATENATE("((",B77,"))") -> ((Garnet Ring)) | D77: 27454 | E77: 12906 | F77: 3717 | G77: =VLOOKUP(B77,'Kings Ratings'!$A$2:$B$1000,2,false) -> 3 | H77: =if(G77=11,13,13-ROUNDDOWN(log(J77,4),0)) -> 1 | I77: =vlookup(A77,'202405 MM (Do Not Delete)'!$A$1:$G$1000,7,false) -> 257 | J77: =10000*F77+10*E77+D77 -> 37326514 | L77: =IFERROR(__xludf.DUMMYFUNCTION("if(REGEXMATCH(vlookup(B77,'Kings Ratings'!$A$2:$C$1000,3,false),""Fishing""),""Yes"","""")"),"") | M77: =IFERROR(__xludf.DUMMYFUNCTION("if(REGEXMATCH(vlookup(B77,'Kings Ratings'!$A$2:$C$1000,3,false),""Crafting""),""Yes"","""")"),"Yes") -> Yes | N77: =IFERROR(__xludf.DUMMYFUNCTION("if(REGEXMATCH(vlookup(B77,'Kings Ratings'!$A$2:$C$1000,3,false),""Exploring""),""Yes"","""")"),"") | O77: =IFERROR(__xludf.DUMMYFUNCTION("if(REGEXMATCH(vlookup(B77,'Kings Ratings'!$A$2:$C$1000,3,false),""Farming""),""Yes"","""")"),"") | P77: =IFERROR(__xludf.DUMMYFUNCTION("if(REGEXMATCH(vlookup(B77,'Kings Ratings'!$A$2:$C$1000,3,false),""Cooking""),""Yes"","""")"),"") | Q77: =IFERROR(__xludf.DUMMYFUNCTION("if(REGEXMATCH(vlookup(B77,'Kings Ratings'!$A$2:$C$1000,3,false),""Event""),""Yes"","""")"),"")
A78: 115 | B78: Puffer | C78: =CONCATENATE("((",B78,"))") -> ((Puffer)) | D78: 27399 | E78: 16085 | F78: 6332 | G78: =VLOOKUP(B78,'Kings Ratings'!$A$2:$B$1000,2,false) -> 3 | H78: =if(G78=11,13,13-ROUNDDOWN(log(J78,4),0)) -> 1 | I78: =vlookup(A78,'202405 MM (Do Not Delete)'!$A$1:$G$1000,7,false) -> 237 | J78: =10000*F78+10*E78+D78 -> 63508249 | L78: =IFERROR(__xludf.DUMMYFUNCTION("if(REGEXMATCH(vlookup(B78,'Kings Ratings'!$A$2:$C$1000,3,false),""Fishing""),""Yes"","""")"),"Yes") -> Yes | M78: =IFERROR(__xludf.DUMMYFUNCTION("if(REGEXMATCH(vlookup(B78,'Kings Ratings'!$A$2:$C$1000,3,false),""Crafting""),""Yes"","""")"),"") | N78: =IFERROR(__xludf.DUMMYFUNCTION("if(REGEXMATCH(vlookup(B78,'Kings Ratings'!$A$2:$C$1000,3,false),""Exploring""),""Yes"","""")"),"") | O78: =IFERROR(__xludf.DUMMYFUNCTION("if(REGEXMATCH(vlookup(B78,'Kings Ratings'!$A$2:$C$1000,3,false),""Farming""),""Yes"","""")"),"") | P78: =IFERROR(__xludf.DUMMYFUNCTION("if(REGEXMATCH(vlookup(B78,'Kings Ratings'!$A$2:$C$1000,3,false),""Cooking""),""Yes"","""")"),"") | Q78: =IFERROR(__xludf.DUMMYFUNCTION("if(REGEXMATCH(vlookup(B78,'Kings Ratings'!$A$2:$C$1000,3,false),""Event""),""Yes"","""")"),"")
A79: 89 | B79: Blue Catfish | C79: =CONCATENATE("((",B79,"))") -> ((Blue Catfish)) | D79: 27394 | E79: 17452 | F79: 8274 | G79: =VLOOKUP(B79,'Kings Ratings'!$A$2:$B$1000,2,false) -> 3 | H79: =if(G79=11,13,13-ROUNDDOWN(log(J79,4),0)) -> 0 | I79: =vlookup(A79,'202405 MM (Do Not Delete)'!$A$1:$G$1000,7,false) -> 245 | J79: =10000*F79+10*E79+D79 -> 82941914 | L79: =IFERROR(__xludf.DUMMYFUNCTION("if(REGEXMATCH(vlookup(B79,'Kings Ratings'!$A$2:$C$1000,3,false),""Fishing""),""Yes"","""")"),"Yes") -> Yes | M79: =IFERROR(__xludf.DUMMYFUNCTION("if(REGEXMATCH(vlookup(B79,'Kings Ratings'!$A$2:$C$1000,3,false),""Crafting""),""Yes"","""")"),"") | N79: =IFERROR(__xludf.DUMMYFUNCTION("if(REGEXMATCH(vlookup(B79,'Kings Ratings'!$A$2:$C$1000,3,false),""Exploring""),""Yes"","""")"),"") | O79: =IFERROR(__xludf.DUMMYFUNCTION("if(REGEXMATCH(vlookup(B79,'Kings Ratings'!$A$2:$C$1000,3,false),""Farming""),""Yes"","""")"),"") | P79: =IFERROR(__xludf.DUMMYFUNCTION("if(REGEXMATCH(vlookup(B79,'Kings Ratings'!$A$2:$C$1000,3,false),""Cooking""),""Yes"","""")"),"") | Q79: =IFERROR(__xludf.DUMMYFUNCTION("if(REGEXMATCH(vlookup(B79,'Kings Ratings'!$A$2:$C$1000,3,false),""Event""),""Yes"","""")"),"")
A80: 203 | B80: Green Dye | C80: =CONCATENATE("((",B80,"))") -> ((Green Dye)) | D80: 27175 | E80: 12070 | F80: 2590 | G80: =VLOOKUP(B80,'Kings Ratings'!$A$2:$B$1000,2,false) -> 2 | H80: =if(G80=11,13,13-ROUNDDOWN(log(J80,4),0)) -> 1 | I80: =vlookup(A80,'202405 MM (Do Not Delete)'!$A$1:$G$1000,7,false) -> 280 | J80: =10000*F80+10*E80+D80 -> 26047875 | L80: =IFERROR(__xludf.DUMMYFUNCTION("if(REGEXMATCH(vlookup(B80,'Kings Ratings'!$A$2:$C$1000,3,false),""Fishing""),""Yes"","""")"),"") | M80: =IFERROR(__xludf.DUMMYFUNCTION("if(REGEXMATCH(vlookup(B80,'Kings Ratings'!$A$2:$C$1000,3,false),""Crafting""),""Yes"","""")"),"Yes") -> Yes | N80: =IFERROR(__xludf.DUMMYFUNCTION("if(REGEXMATCH(vlookup(B80,'Kings Ratings'!$A$2:$C$1000,3,false),""Exploring""),""Yes"","""")"),"") | O80: =IFERROR(__xludf.DUMMYFUNCTION("if(REGEXMATCH(vlookup(B80,'Kings Ratings'!$A$2:$C$1000,3,false),""Farming""),""Yes"","""")"),"") | P80: =IFERROR(__xludf.DUMMYFUNCTION("if(REGEXMATCH(vlookup(B80,'Kings Ratings'!$A$2:$C$1000,3,false),""Cooking""),""Yes"","""")"),"") | Q80: =IFERROR(__xludf.DUMMYFUNCTION("if(REGEXMATCH(vlookup(B80,'Kings Ratings'!$A$2:$C$1000,3,false),""Event""),""Yes"","""")"),"")
A81: 45 | B81: Fish Bones | C81: =CONCATENATE("((",B81,"))") -> ((Fish Bones)) | D81: 27087 | E81: 14110 | F81: 5404 | G81: =VLOOKUP(B81,'Kings Ratings'!$A$2:$B$1000,2,false) -> 4 | H81: =if(G81=11,13,13-ROUNDDOWN(log(J81,4),0)) -> 1 | I81: =vlookup(A81,'202405 MM (Do Not Delete)'!$A$1:$G$1000,7,false) -> 270 | J81: =10000*F81+10*E81+D81 -> 54208187 | L81: =IFERROR(__xludf.DUMMYFUNCTION("if(REGEXMATCH(vlookup(B81,'Kings Ratings'!$A$2:$C$1000,3,false),""Fishing""),""Yes"","""")"),"Yes") -> Yes | M81: =IFERROR(__xludf.DUMMYFUNCTION("if(REGEXMATCH(vlookup(B81,'Kings Ratings'!$A$2:$C$1000,3,false),""Crafting""),""Yes"","""")"),"") | N81: =IFERROR(__xludf.DUMMYFUNCTION("if(REGEXMATCH(vlookup(B81,'Kings Ratings'!$A$2:$C$1000,3,false),""Exploring""),""Yes"","""")"),"") | O81: =IFERROR(__xludf.DUMMYFUNCTION("if(REGEXMATCH(vlookup(B81,'Kings Ratings'!$A$2:$C$1000,3,false),""Farming""),""Yes"","""")"),"") | P81: =IFERROR(__xludf.DUMMYFUNCTION("if(REGEXMATCH(vlookup(B81,'Kings Ratings'!$A$2:$C$1000,3,false),""Cooking""),""Yes"","""")"),"") | Q81: =IFERROR(__xludf.DUMMYFUNCTION("if(REGEXMATCH(vlookup(B81,'Kings Ratings'!$A$2:$C$1000,3,false),""Event""),""Yes"","""")"),"")
A82: 132 | B82: Carp | C82: =CONCATENATE("((",B82,"))") -> ((Carp)) | D82: 26904 | E82: 14482 | F82: 5515 | G82: =VLOOKUP(B82,'Kings Ratings'!$A$2:$B$1000,2,false) -> 3 | H82: =if(G82=11,13,13-ROUNDDOWN(log(J82,4),0)) -> 1 | I82: =vlookup(A82,'202405 MM (Do Not Delete)'!$A$1:$G$1000,7,false) -> 245 | J82: =10000*F82+10*E82+D82 -> 55321724 | L82: =IFERROR(__xludf.DUMMYFUNCTION("if(REGEXMATCH(vlookup(B82,'Kings Ratings'!$A$2:$C$1000,3,false),""Fishing""),""Yes"","""")"),"Yes") -> Yes | M82: =IFERROR(__xludf.DUMMYFUNCTION("if(REGEXMATCH(vlookup(B82,'Kings Ratings'!$A$2:$C$1000,3,false),""Crafting""),""Yes"","""")"),"") | N82: =IFERROR(__xludf.DUMMYFUNCTION("if(REGEXMATCH(vlookup(B82,'Kings Ratings'!$A$2:$C$1000,3,false),""Exploring""),""Yes"","""")"),"") | O82: =IFERROR(__xludf.DUMMYFUNCTION("if(REGEXMATCH(vlookup(B82,'Kings Ratings'!$A$2:$C$1000,3,false),""Farming""),""Yes"","""")"),"") | P82: =IFERROR(__xludf.DUMMYFUNCTION("if(REGEXMATCH(vlookup(B82,'Kings Ratings'!$A$2:$C$1000,3,false),""Cooking""),""Yes"","""")"),"") | Q82: =IFERROR(__xludf.DUMMYFUNCTION("if(REGEXMATCH(vlookup(B82,'Kings Ratings'!$A$2:$C$1000,3,false),""Event""),""Yes"","""")"),"")
A83: 46 | B83: Hops | C83: =CONCATENATE("((",B83,"))") -> ((Hops)) | D83: 26886 | E83: 2348 | F83: 14 | G83: =VLOOKUP(B83,'Kings Ratings'!$A$2:$B$1000,2,false) -> 8 | H83: =if(G83=11,13,13-ROUNDDOWN(log(J83,4),0)) -> 5 | I83: =vlookup(A83,'202405 MM (Do Not Delete)'!$A$1:$G$1000,7,false) | J83: =10000*F83+10*E83+D83 -> 190366 | L83: =IFERROR(__xludf.DUMMYFUNCTION("if(REGEXMATCH(vlookup(B83,'Kings Ratings'!$A$2:$C$1000,3,false),""Fishing""),""Yes"","""")"),"") | M83: =IFERROR(__xludf.DUMMYFUNCTION("if(REGEXMATCH(vlookup(B83,'Kings Ratings'!$A$2:$C$1000,3,false),""Crafting""),""Yes"","""")"),"") | N83: =IFERROR(__xludf.DUMMYFUNCTION("if(REGEXMATCH(vlookup(B83,'Kings Ratings'!$A$2:$C$1000,3,false),""Exploring""),""Yes"","""")"),"") | O83: =IFERROR(__xludf.DUMMYFUNCTION("if(REGEXMATCH(vlookup(B83,'Kings Ratings'!$A$2:$C$1000,3,false),""Farming""),""Yes"","""")"),"Yes") -> Yes | P83: =IFERROR(__xludf.DUMMYFUNCTION("if(REGEXMATCH(vlookup(B83,'Kings Ratings'!$A$2:$C$1000,3,false),""Cooking""),""Yes"","""")"),"") | Q83: =IFERROR(__xludf.DUMMYFUNCTION("if(REGEXMATCH(vlookup(B83,'Kings Ratings'!$A$2:$C$1000,3,false),""Event""),""Yes"","""")"),"")
A84: 427 | B84: Yarn | C84: =CONCATENATE("((",B84,"))") -> ((Yarn)) | D84: 26874 | E84: 15173 | F84: 6704 | G84: =VLOOKUP(B84,'Kings Ratings'!$A$2:$B$1000,2,false) -> 1 | H84: =if(G84=11,13,13-ROUNDDOWN(log(J84,4),0)) -> 0 | I84: =vlookup(A84,'202405 MM (Do Not Delete)'!$A$1:$G$1000,7,false) -> 236 | J84: =10000*F84+10*E84+D84 -> 67218604 | L84: =IFERROR(__xludf.DUMMYFUNCTION("if(REGEXMATCH(vlookup(B84,'Kings Ratings'!$A$2:$C$1000,3,false),""Fishing""),""Yes"","""")"),"") | M84: =IFERROR(__xludf.DUMMYFUNCTION("if(REGEXMATCH(vlookup(B84,'Kings Ratings'!$A$2:$C$1000,3,false),""Crafting""),""Yes"","""")"),"Yes") -> Yes | N84: =IFERROR(__xludf.DUMMYFUNCTION("if(REGEXMATCH(vlookup(B84,'Kings Ratings'!$A$2:$C$1000,3,false),""Exploring""),""Yes"","""")"),"") | O84: =IFERROR(__xludf.DUMMYFUNCTION("if(REGEXMATCH(vlookup(B84,'Kings Ratings'!$A$2:$C$1000,3,false),""Farming""),""Yes"","""")"),"") | P84: =IFERROR(__xludf.DUMMYFUNCTION("if(REGEXMATCH(vlookup(B84,'Kings Ratings'!$A$2:$C$1000,3,false),""Cooking""),""Yes"","""")"),"") | Q84: =IFERROR(__xludf.DUMMYFUNCTION("if(REGEXMATCH(vlookup(B84,'Kings Ratings'!$A$2:$C$1000,3,false),""Event""),""Yes"","""")"),"")
A85: 248 | B85: Shimmer Topaz | C85: =CONCATENATE("((",B85,"))") -> ((Shimmer Topaz)) | D85: 26859 | E85: 14286 | F85: 4567 | G85: =VLOOKUP(B85,'Kings Ratings'!$A$2:$B$1000,2,false) -> 1 | H85: =if(G85=11,13,13-ROUNDDOWN(log(J85,4),0)) -> 1 | I85: =vlookup(A85,'202405 MM (Do Not Delete)'!$A$1:$G$1000,7,false) -> 246 | J85: =10000*F85+10*E85+D85 -> 45839719 | L85: =IFERROR(__xludf.DUMMYFUNCTION("if(REGEXMATCH(vlookup(B85,'Kings Ratings'!$A$2:$C$1000,3,false),""Fishing""),""Yes"","""")"),"") | M85: =IFERROR(__xludf.DUMMYFUNCTION("if(REGEXMATCH(vlookup(B85,'Kings Ratings'!$A$2:$C$1000,3,false),""Crafting""),""Yes"","""")"),"Yes") -> Yes | N85: =IFERROR(__xludf.DUMMYFUNCTION("if(REGEXMATCH(vlookup(B85,'Kings Ratings'!$A$2:$C$1000,3,false),""Exploring""),""Yes"","""")"),"") | O85: =IFERROR(__xludf.DUMMYFUNCTION("if(REGEXMATCH(vlookup(B85,'Kings Ratings'!$A$2:$C$1000,3,false),""Farming""),""Yes"","""")"),"") | P85: =IFERROR(__xludf.DUMMYFUNCTION("if(REGEXMATCH(vlookup(B85,'Kings Ratings'!$A$2:$C$1000,3,false),""Cooking""),""Yes"","""")"),"") | Q85: =IFERROR(__xludf.DUMMYFUNCTION("if(REGEXMATCH(vlookup(B85,'Kings Ratings'!$A$2:$C$1000,3,false),""Event""),""Yes"","""")"),"")
A86: 94 | B86: Ruby | C86: =CONCATENATE("((",B86,"))") -> ((Ruby)) | D86: 26798 | E86: 15137 | F86: 5171 | G86: =VLOOKUP(B86,'Kings Ratings'!$A$2:$B$1000,2,false) -> 1 | H86: =if(G86=11,13,13-ROUNDDOWN(log(J86,4),0)) -> 1 | I86: =vlookup(A86,'202405 MM (Do Not Delete)'!$A$1:$G$1000,7,false) -> 242 | J86: =10000*F86+10*E86+D86 -> 51888168 | L86: =IFERROR(__xludf.DUMMYFUNCTION("if(REGEXMATCH(vlookup(B86,'Kings Ratings'!$A$2:$C$1000,3,false),""Fishing""),""Yes"","""")"),"") | M86: =IFERROR(__xludf.DUMMYFUNCTION("if(REGEXMATCH(vlookup(B86,'Kings Ratings'!$A$2:$C$1000,3,false),""Crafting""),""Yes"","""")"),"Yes") -> Yes | N86: =IFERROR(__xludf.DUMMYFUNCTION("if(REGEXMATCH(vlookup(B86,'Kings Ratings'!$A$2:$C$1000,3,false),""Exploring""),""Yes"","""")"),"") | O86: =IFERROR(__xludf.DUMMYFUNCTION("if(REGEXMATCH(vlookup(B86,'Kings Ratings'!$A$2:$C$1000,3,false),""Farming""),""Yes"","""")"),"") | P86: =IFERROR(__xludf.DUMMYFUNCTION("if(REGEXMATCH(vlookup(B86,'Kings Ratings'!$A$2:$C$1000,3,false),""Cooking""),""Yes"","""")"),"") | Q86: =IFERROR(__xludf.DUMMYFUNCTION("if(REGEXMATCH(vlookup(B86,'Kings Ratings'!$A$2:$C$1000,3,false),""Event""),""Yes"","""")"),"")
A87: 206 | B87: Seahorse | C87: =CONCATENATE("((",B87,"))") -> ((Seahorse)) | D87: 26758 | E87: 16073 | F87: 6331 | G87: =VLOOKUP(B87,'Kings Ratings'!$A$2:$B$1000,2,false) -> 3 | H87: =if(G87=11,13,13-ROUNDDOWN(log(J87,4),0)) -> 1 | I87: =vlookup(A87,'202405 MM (Do Not Delete)'!$A$1:$G$1000,7,false) -> 237 | J87: =10000*F87+10*E87+D87 -> 63497488 | L87: =IFERROR(__xludf.DUMMYFUNCTION("if(REGEXMATCH(vlookup(B87,'Kings Ratings'!$A$2:$C$1000,3,false),""Fishing""),""Yes"","""")"),"Yes") -> Yes | M87: =IFERROR(__xludf.DUMMYFUNCTION("if(REGEXMATCH(vlookup(B87,'Kings Ratings'!$A$2:$C$1000,3,false),""Crafting""),""Yes"","""")"),"") | N87: =IFERROR(__xludf.DUMMYFUNCTION("if(REGEXMATCH(vlookup(B87,'Kings Ratings'!$A$2:$C$1000,3,false),""Exploring""),""Yes"","""")"),"") | O87: =IFERROR(__xludf.DUMMYFUNCTION("if(REGEXMATCH(vlookup(B87,'Kings Ratings'!$A$2:$C$1000,3,false),""Farming""),""Yes"","""")"),"") | P87: =IFERROR(__xludf.DUMMYFUNCTION("if(REGEXMATCH(vlookup(B87,'Kings Ratings'!$A$2:$C$1000,3,false),""Cooking""),""Yes"","""")"),"") | Q87: =IFERROR(__xludf.DUMMYFUNCTION("if(REGEXMATCH(vlookup(B87,'Kings Ratings'!$A$2:$C$1000,3,false),""Event""),""Yes"","""")"),"")
A88: 174 | B88: Ruby Fish | C88: =CONCATENATE("((",B88,"))") -> ((Ruby Fish)) | D88: 26435 | E88: 16209 | F88: 6258 | G88: =VLOOKUP(B88,'Kings Ratings'!$A$2:$B$1000,2,false) -> 3 | H88: =if(G88=11,13,13-ROUNDDOWN(log(J88,4),0)) -> 1 | I88: =vlookup(A88,'202405 MM (Do Not Delete)'!$A$1:$G$1000,7,false) -> 240 | J88: =10000*F88+10*E88+D88 -> 62768525 | L88: =IFERROR(__xludf.DUMMYFUNCTION("if(REGEXMATCH(vlookup(B88,'Kings Ratings'!$A$2:$C$1000,3,false),""Fishing""),""Yes"","""")"),"Yes") -> Yes | M88: =IFERROR(__xludf.DUMMYFUNCTION("if(REGEXMATCH(vlookup(B88,'Kings Ratings'!$A$2:$C$1000,3,false),""Crafting""),""Yes"","""")"),"") | N88: =IFERROR(__xludf.DUMMYFUNCTION("if(REGEXMATCH(vlookup(B88,'Kings Ratings'!$A$2:$C$1000,3,false),""Exploring""),""Yes"","""")"),"") | O88: =IFERROR(__xludf.DUMMYFUNCTION("if(REGEXMATCH(vlookup(B88,'Kings Ratings'!$A$2:$C$1000,3,false),""Farming""),""Yes"","""")"),"") | P88: =IFERROR(__xludf.DUMMYFUNCTION("if(REGEXMATCH(vlookup(B88,'Kings Ratings'!$A$2:$C$1000,3,false),""Cooking""),""Yes"","""")"),"") | Q88: =IFERROR(__xludf.DUMMYFUNCTION("if(REGEXMATCH(vlookup(B88,'Kings Ratings'!$A$2:$C$1000,3,false),""Event""),""Yes"","""")"),"")
A89: 23 | B89: Bucket | C89: =CONCATENATE("((",B89,"))") -> ((Bucket)) | D89: 25856 | E89: 13648 | F89: 5334 | G89: =VLOOKUP(B89,'Kings Ratings'!$A$2:$B$1000,2,false) -> 1 | H89: =if(G89=11,13,13-ROUNDDOWN(log(J89,4),0)) -> 1 | I89: =vlookup(A89,'202405 MM (Do Not Delete)'!$A$1:$G$1000,7,false) -> 243 | J89: =10000*F89+10*E89+D89 -> 53502336 | L89: =IFERROR(__xludf.DUMMYFUNCTION("if(REGEXMATCH(vlookup(B89,'Kings Ratings'!$A$2:$C$1000,3,false),""Fishing""),""Yes"","""")"),"") | M89: =IFERROR(__xludf.DUMMYFUNCTION("if(REGEXMATCH(vlookup(B89,'Kings Ratings'!$A$2:$C$1000,3,false),""Crafting""),""Yes"","""")"),"Yes") -> Yes | N89: =IFERROR(__xludf.DUMMYFUNCTION("if(REGEXMATCH(vlookup(B89,'Kings Ratings'!$A$2:$C$1000,3,false),""Exploring""),""Yes"","""")"),"") | O89: =IFERROR(__xludf.DUMMYFUNCTION("if(REGEXMATCH(vlookup(B89,'Kings Ratings'!$A$2:$C$1000,3,false),""Farming""),""Yes"","""")"),"") | P89: =IFERROR(__xludf.DUMMYFUNCTION("if(REGEXMATCH(vlookup(B89,'Kings Ratings'!$A$2:$C$1000,3,false),""Cooking""),""Yes"","""")"),"") | Q89: =IFERROR(__xludf.DUMMYFUNCTION("if(REGEXMATCH(vlookup(B89,'Kings Ratings'!$A$2:$C$1000,3,false),""Event""),""Yes"","""")"),"")
A90: 131 | B90: Bluegill | C90: =CONCATENATE("((",B90,"))") -> ((Bluegill)) | D90: 25689 | E90: 14390 | F90: 7599 | G90: =VLOOKUP(B90,'Kings Ratings'!$A$2:$B$1000,2,false) -> 2 | H90: =if(G90=11,13,13-ROUNDDOWN(log(J90,4),0)) -> 0 | I90: =vlookup(A90,'202405 MM (Do Not Delete)'!$A$1:$G$1000,7,false) -> 230 | J90: =10000*F90+10*E90+D90 -> 76159589 | L90: =IFERROR(__xludf.DUMMYFUNCTION("if(REGEXMATCH(vlookup(B90,'Kings Ratings'!$A$2:$C$1000,3,false),""Fishing""),""Yes"","""")"),"Yes") -> Yes | M90: =IFERROR(__xludf.DUMMYFUNCTION("if(REGEXMATCH(vlookup(B90,'Kings Ratings'!$A$2:$C$1000,3,false),""Crafting""),""Yes"","""")"),"") | N90: =IFERROR(__xludf.DUMMYFUNCTION("if(REGEXMATCH(vlookup(B90,'Kings Ratings'!$A$2:$C$1000,3,false),""Exploring""),""Yes"","""")"),"") | O90: =IFERROR(__xludf.DUMMYFUNCTION("if(REGEXMATCH(vlookup(B90,'Kings Ratings'!$A$2:$C$1000,3,false),""Farming""),""Yes"","""")"),"") | P90: =IFERROR(__xludf.DUMMYFUNCTION("if(REGEXMATCH(vlookup(B90,'Kings Ratings'!$A$2:$C$1000,3,false),""Cooking""),""Yes"","""")"),"") | Q90: =IFERROR(__xludf.DUMMYFUNCTION("if(REGEXMATCH(vlookup(B90,'Kings Ratings'!$A$2:$C$1000,3,false),""Event""),""Yes"","""")"),"")
A91: 48 | B91: Potato | C91: =CONCATENATE("((",B91,"))") -> ((Potato)) | D91: 25485 | E91: 11184 | F91: 1757 | G91: =VLOOKUP(B91,'Kings Ratings'!$A$2:$B$1000,2,false) -> 4 | H91: =if(G91=11,13,13-ROUNDDOWN(log(J91,4),0)) -> 1 | I91: =vlookup(A91,'202405 MM (Do Not Delete)'!$A$1:$G$1000,7,false) -> 290 | J91: =10000*F91+10*E91+D91 -> 17707325 | L91: =IFERROR(__xludf.DUMMYFUNCTION("if(REGEXMATCH(vlookup(B91,'Kings Ratings'!$A$2:$C$1000,3,false),""Fishing""),""Yes"","""")"),"") | M91: =IFERROR(__xludf.DUMMYFUNCTION("if(REGEXMATCH(vlookup(B91,'Kings Ratings'!$A$2:$C$1000,3,false),""Crafting""),""Yes"","""")"),"") | N91: =IFERROR(__xludf.DUMMYFUNCTION("if(REGEXMATCH(vlookup(B91,'Kings Ratings'!$A$2:$C$1000,3,false),""Exploring""),""Yes"","""")"),"") | O91: =IFERROR(__xludf.DUMMYFUNCTION("if(REGEXMATCH(vlookup(B91,'Kings Ratings'!$A$2:$C$1000,3,false),""Farming""),""Yes"","""")"),"Yes") -> Yes | P91: =IFERROR(__xludf.DUMMYFUNCTION("if(REGEXMATCH(vlookup(B91,'Kings Ratings'!$A$2:$C$1000,3,false),""Cooking""),""Yes"","""")"),"") | Q91: =IFERROR(__xludf.DUMMYFUNCTION("if(REGEXMATCH(vlookup(B91,'Kings Ratings'!$A$2:$C$1000,3,false),""Event""),""Yes"","""")"),"")
A92: 500 | B92: Large Net | C92: =CONCATENATE("((",B92,"))") -> ((Large Net)) | D92: 25438 | E92: 13271 | F92: 3975 | G92: =VLOOKUP(B92,'Kings Ratings'!$A$2:$B$1000,2,false) -> 4 | H92: =if(G92=11,13,13-ROUNDDOWN(log(J92,4),0)) -> 1 | I92: =vlookup(A92,'202405 MM (Do Not Delete)'!$A$1:$G$1000,7,false) -> 250 | J92: =10000*F92+10*E92+D92 -> 39908148 | L92: =IFERROR(__xludf.DUMMYFUNCTION("if(REGEXMATCH(vlookup(B92,'Kings Ratings'!$A$2:$C$1000,3,false),""Fishing""),""Yes"","""")"),"") | M92: =IFERROR(__xludf.DUMMYFUNCTION("if(REGEXMATCH(vlookup(B92,'Kings Ratings'!$A$2:$C$1000,3,false),""Crafting""),""Yes"","""")"),"Yes") -> Yes | N92: =IFERROR(__xludf.DUMMYFUNCTION("if(REGEXMATCH(vlookup(B92,'Kings Ratings'!$A$2:$C$1000,3,false),""Exploring""),""Yes"","""")"),"") | O92: =IFERROR(__xludf.DUMMYFUNCTION("if(REGEXMATCH(vlookup(B92,'Kings Ratings'!$A$2:$C$1000,3,false),""Farming""),""Yes"","""")"),"") | P92: =IFERROR(__xludf.DUMMYFUNCTION("if(REGEXMATCH(vlookup(B92,'Kings Ratings'!$A$2:$C$1000,3,false),""Cooking""),""Yes"","""")"),"") | Q92: =IFERROR(__xludf.DUMMYFUNCTION("if(REGEXMATCH(vlookup(B92,'Kings Ratings'!$A$2:$C$1000,3,false),""Event""),""Yes"","""")"),"")
A93: 264 | B93: Jade | C93: =CONCATENATE("((",B93,"))") -> ((Jade)) | D93: 25176 | E93: 13955 | F93: 4495 | G93: =VLOOKUP(B93,'Kings Ratings'!$A$2:$B$1000,2,false) -> 2 | H93: =if(G93=11,13,13-ROUNDDOWN(log(J93,4),0)) -> 1 | I93: =vlookup(A93,'202405 MM (Do Not Delete)'!$A$1:$G$1000,7,false) -> 247 | J93: =10000*F93+10*E93+D93 -> 45114726 | L93: =IFERROR(__xludf.DUMMYFUNCTION("if(REGEXMATCH(vlookup(B93,'Kings Ratings'!$A$2:$C$1000,3,false),""Fishing""),""Yes"","""")"),"") | M93: =IFERROR(__xludf.DUMMYFUNCTION("if(REGEXMATCH(vlookup(B93,'Kings Ratings'!$A$2:$C$1000,3,false),""Crafting""),""Yes"","""")"),"") | N93: =IFERROR(__xludf.DUMMYFUNCTION("if(REGEXMATCH(vlookup(B93,'Kings Ratings'!$A$2:$C$1000,3,false),""Exploring""),""Yes"","""")"),"") | O93: =IFERROR(__xludf.DUMMYFUNCTION("if(REGEXMATCH(vlookup(B93,'Kings Ratings'!$A$2:$C$1000,3,false),""Farming""),""Yes"","""")"),"") | P93: =IFERROR(__xludf.DUMMYFUNCTION("if(REGEXMATCH(vlookup(B93,'Kings Ratings'!$A$2:$C$1000,3,false),""Cooking""),""Yes"","""")"),"") | Q93: =IFERROR(__xludf.DUMMYFUNCTION("if(REGEXMATCH(vlookup(B93,'Kings Ratings'!$A$2:$C$1000,3,false),""Event""),""Yes"","""")"),"")
A94: 217 | B94: Horseshoe | C94: =CONCATENATE("((",B94,"))") -> ((Horseshoe)) | D94: 24822 | E94: 15808 | F94: 7283 | G94: =VLOOKUP(B94,'Kings Ratings'!$A$2:$B$1000,2,false) -> 1 | H94: =if(G94=11,13,13-ROUNDDOWN(log(J94,4),0)) -> 0 | I94: =vlookup(A94,'202405 MM (Do Not Delete)'!$A$1:$G$1000,7,false) -> 233 | J94: =10000*F94+10*E94+D94 -> 73012902 | L94: =IFERROR(__xludf.DUMMYFUNCTION("if(REGEXMATCH(vlookup(B94,'Kings Ratings'!$A$2:$C$1000,3,false),""Fishing""),""Yes"","""")"),"") | M94: =IFERROR(__xludf.DUMMYFUNCTION("if(REGEXMATCH(vlookup(B94,'Kings Ratings'!$A$2:$C$1000,3,false),""Crafting""),""Yes"","""")"),"Yes") -> Yes | N94: =IFERROR(__xludf.DUMMYFUNCTION("if(REGEXMATCH(vlookup(B94,'Kings Ratings'!$A$2:$C$1000,3,false),""Exploring""),""Yes"","""")"),"") | O94: =IFERROR(__xludf.DUMMYFUNCTION("if(REGEXMATCH(vlookup(B94,'Kings Ratings'!$A$2:$C$1000,3,false),""Farming""),""Yes"","""")"),"") | P94: =IFERROR(__xludf.DUMMYFUNCTION("if(REGEXMATCH(vlookup(B94,'Kings Ratings'!$A$2:$C$1000,3,false),""Cooking""),""Yes"","""")"),"") | Q94: =IFERROR(__xludf.DUMMYFUNCTION("if(REGEXMATCH(vlookup(B94,'Kings Ratings'!$A$2:$C$1000,3,false),""Event""),""Yes"","""")"),"")
A95: 11 | B95: Peppers | C95: =CONCATENATE("((",B95,"))") -> ((Peppers)) | D95: 24715 | E95: 9600 | F95: 2440 | G95: =VLOOKUP(B95,'Kings Ratings'!$A$2:$B$1000,2,false) -> 1 | H95: =if(G95=11,13,13-ROUNDDOWN(log(J95,4),0)) -> 1 | I95: =vlookup(A95,'202405 MM (Do Not Delete)'!$A$1:$G$1000,7,false) -> 275 | J95: =10000*F95+10*E95+D95 -> 24520715 | L95: =IFERROR(__xludf.DUMMYFUNCTION("if(REGEXMATCH(vlookup(B95,'Kings Ratings'!$A$2:$C$1000,3,false),""Fishing""),""Yes"","""")"),"") | M95: =IFERROR(__xludf.DUMMYFUNCTION("if(REGEXMATCH(vlookup(B95,'Kings Ratings'!$A$2:$C$1000,3,false),""Crafting""),""Yes"","""")"),"") | N95: =IFERROR(__xludf.DUMMYFUNCTION("if(REGEXMATCH(vlookup(B95,'Kings Ratings'!$A$2:$C$1000,3,false),""Exploring""),""Yes"","""")"),"") | O95: =IFERROR(__xludf.DUMMYFUNCTION("if(REGEXMATCH(vlookup(B95,'Kings Ratings'!$A$2:$C$1000,3,false),""Farming""),""Yes"","""")"),"Yes") -> Yes | P95: =IFERROR(__xludf.DUMMYFUNCTION("if(REGEXMATCH(vlookup(B95,'Kings Ratings'!$A$2:$C$1000,3,false),""Cooking""),""Yes"","""")"),"") | Q95: =IFERROR(__xludf.DUMMYFUNCTION("if(REGEXMATCH(vlookup(B95,'Kings Ratings'!$A$2:$C$1000,3,false),""Event""),""Yes"","""")"),"")
A96: 234 | B96: Flarefin | C96: =CONCATENATE("((",B96,"))") -> ((Flarefin)) | D96: 24397 | E96: 14795 | F96: 5117 | G96: =VLOOKUP(B96,'Kings Ratings'!$A$2:$B$1000,2,false) -> 3 | H96: =if(G96=11,13,13-ROUNDDOWN(log(J96,4),0)) -> 1 | I96: =vlookup(A96,'202405 MM (Do Not Delete)'!$A$1:$G$1000,7,false) -> 246 | J96: =10000*F96+10*E96+D96 -> 51342347 | L96: =IFERROR(__xludf.DUMMYFUNCTION("if(REGEXMATCH(vlookup(B96,'Kings Ratings'!$A$2:$C$1000,3,false),""Fishing""),""Yes"","""")"),"Yes") -> Yes | M96: =IFERROR(__xludf.DUMMYFUNCTION("if(REGEXMATCH(vlookup(B96,'Kings Ratings'!$A$2:$C$1000,3,false),""Crafting""),""Yes"","""")"),"") | N96: =IFERROR(__xludf.DUMMYFUNCTION("if(REGEXMATCH(vlookup(B96,'Kings Ratings'!$A$2:$C$1000,3,false),""Exploring""),""Yes"","""")"),"") | O96: =IFERROR(__xludf.DUMMYFUNCTION("if(REGEXMATCH(vlookup(B96,'Kings Ratings'!$A$2:$C$1000,3,false),""Farming""),""Yes"","""")"),"") | P96: =IFERROR(__xludf.DUMMYFUNCTION("if(REGEXMATCH(vlookup(B96,'Kings Ratings'!$A$2:$C$1000,3,false),""Cooking""),""Yes"","""")"),"") | Q96: =IFERROR(__xludf.DUMMYFUNCTION("if(REGEXMATCH(vlookup(B96,'Kings Ratings'!$A$2:$C$1000,3,false),""Event""),""Yes"","""")"),"")
A97: 276 | B97: Flour | C97: =CONCATENATE("((",B97,"))") -> ((Flour)) | D97: 23747 | E97: 7747 | F97: 495 | G97: =VLOOKUP(B97,'Kings Ratings'!$A$2:$B$1000,2,false) -> 6 | H97: =if(G97=11,13,13-ROUNDDOWN(log(J97,4),0)) -> 2 | I97: =vlookup(A97,'202405 MM (Do Not Delete)'!$A$1:$G$1000,7,false) | J97: =10000*F97+10*E97+D97 -> 5051217 | L97: =IFERROR(__xludf.DUMMYFUNCTION("if(REGEXMATCH(vlookup(B97,'Kings Ratings'!$A$2:$C$1000,3,false),""Fishing""),""Yes"","""")"),"") | M97: =IFERROR(__xludf.DUMMYFUNCTION("if(REGEXMATCH(vlookup(B97,'Kings Ratings'!$A$2:$C$1000,3,false),""Crafting""),""Yes"","""")"),"") | N97: =IFERROR(__xludf.DUMMYFUNCTION("if(REGEXMATCH(vlookup(B97,'Kings Ratings'!$A$2:$C$1000,3,false),""Exploring""),""Yes"","""")"),"") | O97: =IFERROR(__xludf.DUMMYFUNCTION("if(REGEXMATCH(vlookup(B97,'Kings Ratings'!$A$2:$C$1000,3,false),""Farming""),""Yes"","""")"),"") | P97: =IFERROR(__xludf.DUMMYFUNCTION("if(REGEXMATCH(vlookup(B97,'Kings Ratings'!$A$2:$C$1000,3,false),""Cooking""),""Yes"","""")"),"") | Q97: =IFERROR(__xludf.DUMMYFUNCTION("if(REGEXMATCH(vlookup(B97,'Kings Ratings'!$A$2:$C$1000,3,false),""Event""),""Yes"","""")"),"")
A98: 237 | B98: Axe | C98: =CONCATENATE("((",B98,"))") -> ((Axe)) | D98: 23660 | E98: 11215 | F98: 1825 | G98: =VLOOKUP(B98,'Kings Ratings'!$A$2:$B$1000,2,false) -> 2 | H98: =if(G98=11,13,13-ROUNDDOWN(log(J98,4),0)) -> 1 | I98: =vlookup(A98,'202405 MM (Do Not Delete)'!$A$1:$G$1000,7,false) -> 289 | J98: =10000*F98+10*E98+D98 -> 18385810 | L98: =IFERROR(__xludf.DUMMYFUNCTION("if(REGEXMATCH(vlookup(B98,'Kings Ratings'!$A$2:$C$1000,3,false),""Fishing""),""Yes"","""")"),"") | M98: =IFERROR(__xludf.DUMMYFUNCTION("if(REGEXMATCH(vlookup(B98,'Kings Ratings'!$A$2:$C$1000,3,false),""Crafting""),""Yes"","""")"),"Yes") -> Yes | N98: =IFERROR(__xludf.DUMMYFUNCTION("if(REGEXMATCH(vlookup(B98,'Kings Ratings'!$A$2:$C$1000,3,false),""Exploring""),""Yes"","""")"),"") | O98: =IFERROR(__xludf.DUMMYFUNCTION("if(REGEXMATCH(vlookup(B98,'Kings Ratings'!$A$2:$C$1000,3,false),""Farming""),""Yes"","""")"),"") | P98: =IFERROR(__xludf.DUMMYFUNCTION("if(REGEXMATCH(vlookup(B98,'Kings Ratings'!$A$2:$C$1000,3,false),""Cooking""),""Yes"","""")"),"") | Q98: =IFERROR(__xludf.DUMMYFUNCTION("if(REGEXMATCH(vlookup(B98,'Kings Ratings'!$A$2:$C$1000,3,false),""Event""),""Yes"","""")"),"")
A99: 535 | B99: Blue Dye | C99: =CONCATENATE("((",B99,"))") -> ((Blue Dye)) | D99: 23063 | E99: 11869 | F99: 2272 | G99: =VLOOKUP(B99,'Kings Ratings'!$A$2:$B$1000,2,false) -> 3 | H99: =if(G99=11,13,13-ROUNDDOWN(log(J99,4),0)) -> 1 | I99: =vlookup(A99,'202405 MM (Do Not Delete)'!$A$1:$G$1000,7,false) -> 281 | J99: =10000*F99+10*E99+D99 -> 22861753 | L99: =IFERROR(__xludf.DUMMYFUNCTION("if(REGEXMATCH(vlookup(B99,'Kings Ratings'!$A$2:$C$1000,3,false),""Fishing""),""Yes"","""")"),"") | M99: =IFERROR(__xludf.DUMMYFUNCTION("if(REGEXMATCH(vlookup(B99,'Kings Ratings'!$A$2:$C$1000,3,false),""Crafting""),""Yes"","""")"),"Yes") -> Yes | N99: =IFERROR(__xludf.DUMMYFUNCTION("if(REGEXMATCH(vlookup(B99,'Kings Ratings'!$A$2:$C$1000,3,false),""Exploring""),""Yes"","""")"),"") | O99: =IFERROR(__xludf.DUMMYFUNCTION("if(REGEXMATCH(vlookup(B99,'Kings Ratings'!$A$2:$C$1000,3,false),""Farming""),""Yes"","""")"),"") | P99: =IFERROR(__xludf.DUMMYFUNCTION("if(REGEXMATCH(vlookup(B99,'Kings Ratings'!$A$2:$C$1000,3,false),""Cooking""),""Yes"","""")"),"") | Q99: =IFERROR(__xludf.DUMMYFUNCTION("if(REGEXMATCH(vlookup(B99,'Kings Ratings'!$A$2:$C$1000,3,false),""Event""),""Yes"","""")"),"")
A100: 176 | B100: Magicite | C100: =CONCATENATE("((",B100,"))") -> ((Magicite)) | D100: 23018 | E100: 9771 | F100: 1703 | G100: =VLOOKUP(B100,'Kings Ratings'!$A$2:$B$1000,2,false) -> 5 | H100: =if(G100=11,13,13-ROUNDDOWN(log(J100,4),0)) -> 1 | I100: =vlookup(A100,'202405 MM (Do Not Delete)'!$A$1:$G$1000,7,false) -> 288 | J100: =10000*F100+10*E100+D100 -> 17150728 | L100: =IFERROR(__xludf.DUMMYFUNCTION("if(REGEXMATCH(vlookup(B100,'Kings Ratings'!$A$2:$C$1000,3,false),""Fishing""),""Yes"","""")"),"") | M100: =IFERROR(__xludf.DUMMYFUNCTION("if(REGEXMATCH(vlookup(B100,'Kings Ratings'!$A$2:$C$1000,3,false),""Crafting""),""Yes"","""")"),"Yes") -> Yes | N100: =IFERROR(__xludf.DUMMYFUNCTION("if(REGEXMATCH(vlookup(B100,'Kings Ratings'!$A$2:$C$1000,3,false),""Exploring""),""Yes"","""")"),"Yes") -> Yes | O100: =IFERROR(__xludf.DUMMYFUNCTION("if(REGEXMATCH(vlookup(B100,'Kings Ratings'!$A$2:$C$1000,3,false),""Farming""),""Yes"","""")"),"") | P100: =IFERROR(__xludf.DUMMYFUNCTION("if(REGEXMATCH(vlookup(B100,'Kings Ratings'!$A$2:$C$1000,3,false),""Cooking""),""Yes"","""")"),"") | Q100: =IFERROR(__xludf.DUMMYFUNCTION("if(REGEXMATCH(vlookup(B100,'Kings Ratings'!$A$2:$C$1000,3,false),""Event""),""Yes"","""")"),"")
...

Sheet Ignore -->
A2: Totals
A4: Date | B4: M | C4: GM | D4: MM | F4: days since last | G4: Daily inc M | H4: Daily Inc GM | I4: Daily Inc MM | Q4: Date | R4: M | S4: GM | T4: MM
A5: 46169 | B5: 6649613 | C5: 3126043 | D5: 1141625 | F5: =A5-A6 -> 80 | G5: =(B5-B6)/$F5 -> 4979.625 | H5: =(C5-C6)/$F5 -> 2663.05 | I5: =(D5-D6)/$F5 -> 1280.5375 | Q5: =A5 -> 46169 | R5: =B5/$B$19 -> 2.1657586 | S5: =C5/$C$19 -> 2.3188888 | T5: =D5/$D$19 -> 3.5054118
A6: 46089 | B6: =sum('Export 260308'!C2:C492) -> 6251243 | C6: =sum('Export 260308'!D2:D492) -> 2912999 | D6: =sum('Export 260308'!E2:E492) -> 1039182 | F6: =A6-A7 -> 104 | G6: =(B6-B7)/$F6 -> 5296.9904 | H6: =(C6-C7)/$F6 -> 2495.1538 | I6: =(D6-D7)/$F6 -> 1188.375 | Q6: =A6 -> 46089 | R6: =B6/$B$19 -> 2.0360107 | S6: =C6/$C$19 -> 2.1608535 | T6: =D6/$D$19 -> 3.1908559
A7: 45985 | B7: 5700356 | C7: 2653503 | D7: 915591 | F7: =A7-A8 -> 102 | G7: =(B7-B8)/$F7 -> 3826.0882 | H7: =(C7-C8)/$F7 -> 1948.1078 | I7: =(D7-D8)/$F7 -> 1041.4118 | Q7: =A7 -> 45985 | R7: =B7/$B$19 -> 1.8565885 | S7: =C7/$C$19 -> 1.9683601 | T7: =D7/$D$19 -> 2.8113641
A8: 45883 | B8: 5310095 | C8: 2454796 | D8: 809367 | F8: =A8-A9 -> 43 | G8: =(B8-B9)/$F8 -> 3950.2326 | H8: =(C8-C9)/$F8 -> 2111.5349 | I8: =(D8-D9)/$F8 -> 1240.5116 | Q8: =A8 -> 45883 | R8: =B8/$B$19 -> 1.7294817 | S8: =C8/$C$19 -> 1.8209599 | T8: =D8/$D$19 -> 2.4851984
A9: 45840 | B9: 5140235 | C9: 2364000 | D9: 756025 | F9: =A9-A10 -> 38 | G9: =(B9-B10)/$F9 -> 4298.0526 | H9: =(C9-C10)/$F9 -> 2303.1579 | I9: =(D9-D10)/$F9 -> 1158.7632 | Q9: =A9 -> 45840 | R9: =B9/$B$19 -> 1.6741588 | S9: =C9/$C$19 -> 1.7536077 | T9: =D9/$D$19 -> 2.3214094
A10: 45802 | B10: 4976909 | C10: 2276480 | D10: 711992 | F10: =A10-A11 -> 41 | G10: =(B10-B11)/$F10 -> 5240.0488 | H10: =(C10-C11)/$F10 -> 2680.4634 | I10: =(D10-D11)/$F10 -> 1204.0488 | Q10: =A10 -> 45802 | R10: =B10/$B$19 -> 1.620964 | S10: =C10/$C$19 -> 1.6886857 | T10: =D10/$D$19 -> 2.186204
A11: 45761 | B11: 4762067 | C11: 2166581 | D11: 662626 | F11: =A11-A12 -> 72 | G11: =(B11-B12)/$F11 -> 4649.8889 | H11: =(C11-C12)/$F11 -> 2284.3333 | I11: =(D11-D12)/$F11 -> 1029.9306 | Q11: =A11 -> 45761 | R11: =B11/$B$19 -> 1.5509906 | S11: =C11/$C$19 -> 1.6071629 | T11: =D11/$D$19 -> 2.0346235
A12: 45689 | B12: 4427275 | C12: 2002109 | D12: 588471 | F12: =A12-A13 -> 30 | G12: =(B12-B13)/$F12 -> 4955.2667 | H12: =(C12-C13)/$F12 -> 2587.0667 | I12: =(D12-D13)/$F12 -> 1202.6667 | Q12: =A12 -> 45689 | R12: =B12/$B$19 -> 1.4419499 | S12: =C12/$C$19 -> 1.4851581 | T12: =D12/$D$19 -> 1.8069272
A13: 45659 | B13: 4278617 | C13: 1924497 | D13: 552391 | F13: =A13-A14 -> 31 | G13: =(B13-B14)/$F13 -> 7213.6129 | H13: =(C13-C14)/$F13 -> 3241.7742 | I13: =(D13-D14)/$F13 -> 1227.4194 | Q13: =A13 -> 45659 | R13: =B13/$B$19 -> 1.3935324 | S13: =C13/$C$19 -> 1.4275858 | T13: =D13/$D$19 -> 1.6961419
A14: 45628 | B14: 4054995 | C14: 1824002 | D14: 514341 | F14: =A14-A15 -> 31 | G14: =(B14-B15)/$F14 -> 4921.5161 | H14: =(C14-C15)/$F14 -> 2340 | I14: =(D14-D15)/$F14 -> 993.09677 | Q14: =A14 -> 45628 | R14: =B14/$B$19 -> 1.3206994 | S14: =C14/$C$19 -> 1.3530389 | T14: =D14/$D$19 -> 1.5793076
A15: 45597 | B15: 3902428 | C15: 1751462 | D15: 483555 | F15: =A15-A16 -> 31 | G15: =(B15-B16)/$F15 -> 5272.4516 | H15: =(C15-C16)/$F15 -> 2543.4839 | I15: =(D15-D16)/$F15 -> 1040.9355 | Q15: =A15 -> 45597 | R15: =B15/$B$19 -> 1.2710088 | S15: =C15/$C$19 -> 1.299229 | T15: =D15/$D$19 -> 1.4847778
A16: 45566 | B16: 3738982 | C16: 1672614 | D16: 451286 | F16: =A16-A17 -> 50 | G16: =(B16-B17)/$F16 -> 4805.26 | H16: =(C16-C17)/$F16 -> 2448.1 | I16: =(D16-D17)/$F16 -> 1019.3 | Q16: =A16 -> 45566 | R16: =B16/$B$19 -> 1.217775 | S16: =C16/$C$19 -> 1.2407398 | T16: =D16/$D$19 -> 1.3856943
A17: 45516 | B17: 3498719 | C17: 1550209 | D17: 400321 | F17: =A17-A18 -> 40 | G17: =(B17-B18)/$F17 -> 4668.375 | H17: =(C17-C18)/$F17 -> 2350.325 | I17: =(D17-D18)/$F17 -> 875.85 | Q17: =A17 -> 45516 | R17: =B17/$B$19 -> 1.1395221 | S17: =C17/$C$19 -> 1.1499401 | T17: =D17/$D$19 -> 1.229204
A18: 45476 | B18: 3311984 | C18: 1456196 | D18: 365287 | F18: =A18-A19 -> 41 | G18: =(B18-B19)/$F18 -> 5893.7805 | H18: =(C18-C19)/$F18 -> 2637.0244 | I18: =(D18-D19)/$F18 -> 966.14634 | Q18: =A18 -> 45476 | R18: =B18/$B$19 -> 1.078703 | S18: =C18/$C$19 -> 1.0802016 | T18: =D18/$D$19 -> 1.1216305
A19: 45435 | B19: 3070339 | C19: 1348078 | D19: 325675 | Q19: =A19 -> 45435 | R19: =B19/$B$19 -> 1 | S19: =C19/$C$19 -> 1 | T19: =D19/$D$19 -> 1

Sheet Kings Ratings
A1: Item | B1: Difficulty Rating | C1: Best Method | D1: Notes
A2: Acorn Butter | B2: 10 | C2: Crafting | D2: Good way to use up , but it needs so many that GM will take a long long time. Always make sure you're tossing them here instead of voiding though.
A3: Amber Cane | B3: 10 | C3: Crafting | D3: Requires , which is a Super Rare, and costly to explore for. You get it from your Lemur at level 6, but not enough to go for GM, or even mastery really.
A4: Amethyst Necklace | B4: 2 | C4: Crafting | D4: Quick to gm, or MM, while working on other Highland Hills masteries. Can also get from opening , 5 each.
A5: Apple Cider | B5: 8 | C5: Crafting, Quests | D5: Fairly easy to master, but GM will take some time. You also get a good amount from quests and some from pets over time. If you care about GM, use when claiming large amounts from quests.
A6: Aquamarine Ring | B6: 3 | C6: Crafting | D6: Needs paste, but pretty cheap and quick overall. Not much else to do in Small Spring though while collecting , so try to make the most of the you get while working on this. Can also get from opening , 5 each.
A7: Arnold Palmer | B7: 8 | C7: Crafting, Quests | D7: You will always want to turn your lemonade into AP, but this will probably take a long time to GM. If you care about GM on this, make sure you're using for quests that reward more than a few hundred.
A8: Awl | B8: 1 | C8: Crafting | D8: Very cheap and simple. Can be done entirely passively.
A9: Axe | B9: 2 | C9: Crafting | D9: Very easy GM or MM, able to be worked on at any point in the game. It's best to use your axes for Exchange Center trades, or send to Vincent for friendship XP. You can also explore Small Cave and turn these directly into as well, provided you can keep up production.
A10: Barracuda | B10: 1 | C10: Fishing | D10: Very very low effort, just use and in Large Island. Make sure to sell these for silver.
A11: Beet | B11: 5 | C11: Farming | D11: You should only really work on this with and ; either from your Strange Onion pet, or the Exchange Center. Make sure to use and it will be pretty quick. Sell, don't void, since they're worth a lot.
A12: Belt Drive | B12: 7 | C12: Crafting | D12: You will definitely want to be working on these when exploring Jundland Desert. If possible, use them to make , but those can be quite costly so in my opinion it's fine to sell extras if you can't.
A13: Black Powder | B13: 2 | C13: Crafting | D13: Can be done actively via exploring, or passively via Quarry. Either use it for , , or Beatrix friendship XP.
A14: Block of Wood | B14: 10 | C14: Crafting
A15: Blue Catfish | B15: 3 | C15: Fishing | D15: One of the slower Crystal River masteries, but still quite easy... just spam nets.
A16: Blue Crab | B16: 2 | C16: Fishing | D16: There are lots of fish to master at Small Island and this is one of the quicker ones. Send these to Captain Thomas or Geist for friendship xp.
A17: Blue Diary | B17: 2 | C17: Crafting | D17: Fairly simple, but useless.
A18: Blue Dye | B18: 3 | C18: Crafting | D18: One of the main reasons to explore Misty Forest. You should turn these into so you can make a lot of silver. If you don't have those unlocked yet, or have already finished, you can knock out ((Fancy Pan Flutes)) pretty wuickly, if you can keep up with the needed.
A19: Blue Parchment | B19: 2 | C19: Crafting | D19: Less use than , but slightly cheaper. Turn it into diaries.
A20: Blue Purse | B20: 4 | C20: Crafting | D20: Work on this while doing and to make some easy silver.
A21: Blue Sea Bass | B21: 2 | C21: Fishing | D21: Drops from Small Island or Vast Ocean. The rates are pretty low from both, but you should make good progress while GMing the easiesr fish in each zone.
A22: Blue Shell | B22: 3 | C22: Fishing | D22: Medium difficulty Small Island fish, just keep throwing nets at the zone.
A23: Blue Tiger Fish | B23: 2 | C23: Fishing | D23: One of the slower Emerald Beach Fish, but not the slowest.
A24: Blue Twine | B24: 3 | C24: Crafting | D24: Throw some on twine and call it a day.
A25: Bluegill | B25: 2 | C25: Fishing | D25: Forest Pond is a great fishing zone for friendship xp, and a few quick fishing GMs. Send these to Holger.
A26: Board | B26: 1 | C26: Crafting, Sawmill | D26: Boards are most people's first mastery and GM. Upgrading your sawmill is essential for Sawmill Silver and many masteries. Check out kings page for lots of craftworks ideas for how to use these entirely passively.
... A39: Cabbage Stew | B39: 10 | C39: Cooking | D39: Very high resource cost (it's mostly , which take forever to grow).
A40: Candy Corn | B40: 11
A41: Cannon | B41: 10 | C41: Crafting
A42: Canoe | B42: 9 | C42: Crafting | D42: The amount of needed for these is insane. They also need a good amount of which can get annoying fast. Most people that have GMed these just did it because they were bored, genuinely. Plus side is, you'll get loads of while working on it.
A43: Carp | B43: 3 | C43: Fishing | D43: Most people overlook this fish, even though it's pretty easy. That's likely because the other easy Farm Pond fish also come from other locations, and they normally get GMed from those. Send these to Holger or Thomas.
A44: Carrot | B44: 3 | C44: Farming | D44: Don't work on this GM until you have access to , whether by cooking it yourself, or trading. It's rather painless with the meal, just a bunch of clicking. Send your spares to frank, or Rosalie/Charles Horsington III.
A45: Cat's Meow | B45: 9 | C45: Cooking | D45: Lower-cook time meal, which means tasting gives less mastery, but relatively cheap. Gm will take a long time.
A46: Catfish | B46: 5 | C46: Fishing, Locksmith | D46: Catfish have a pretty low drop rate from fishing in the Farm Pond. Luckily you can also get them from opening , which you get from fishing in the Forest Pond. So don't stress.
A47: Christmas Tree | B47: 11
A48: Chum | B48: 3 | C48: Crafting | D48: Can be worked on entirely from passive production. Make sure you upgrade your Trout/Bait Farm and Worm Habitat to keep production flowing. These sell for decent silver as well.
A49: Clam Shell | B49: 1 | C49: Fishing | D49: Very easy Emerald Beach fishing mastery.
A50: Clownfish | B50: 2 | C50: Fishing | D50: Fairly quick Emerald Beach mastery.
A51: Coin Purse | B51: 5 | C51: Crafting | D51: Make sure you turn these into as much as possible, because the silver is really good.
A52: Compass | B52: 10 | C52: Crafting | D52: The only way to craft is to toss them into the Wishing Well, then recraft with the you get back. It's very expensive, as each costs 4x and your free tosses into the well are limited. It's is somewhat reasonable (although expensive) to master over a long period of time. GM is out of the question.
A53: Conch Shell | B53: 1 | C53: Fishing | D53: Very easy Emerald Beach fishing mastery.
A54: Concord Grape Pie | B54: 8 | C54: Cooking | D54: Long cook time, which means you get mastery progress quickly from actions. Also good for cooking xp.
A55: Control Box | B55: 7 | C55: Crafting | D55: If you don't have a stockpile of , this is the single most stam-intensive craft currently in the game. It's quite costly, but you should definitely be crafting these up into as you go.
A56: Cooking Pot | B56: 9 | C56: Crafting | D56: Requires a ton of . Going for mastery on this is reasonable, but GM is just a flex goal at this point, in my opinion.
A57: Corn | B57: 7 | C57: Farming, Locksmith | D57: You will naturally master this just trying to do quests. There are plenty of uses for corn, between cooking, rfc, and , so if you want to knock it out as a GM, you can fish in Pirate's Cove and open the to help out.
A58: Corn Husk Doll | B58: 10 | C58: Crafting | D58: Requires multiple and , so very slow mastery. Quite a few are needed for quests, so you will need to make some, but GM/MM are not super attainable.
A59: Corn Oil | B59: 9 | C59: Crafting | D59: The main drawback on with this is the high cost. Mastery is expensive, but you can get it done in a reasonable time. GM is out of the question in my opinion.
... A65: Crowfish | B65: 1 | C65: Fishing | D65: Should come very quickly once you unlock Glacier Lake.
A66: Crunchy Omelette | B66: 11 | C66: Cooking, Event
A67: Cucumber | B67: 2 | C67: Farming | D67: You shouldn't bother with this until you have access to . But with that buff it should come pretty quickly, just a matter or clicking a lot. Send your extras to Mariya or wait until it is the CC item.
A68: Drum | B68: 1 | C68: Fishing | D68: A very quick fish mastery. It drops in all 4 of the first fishing zones.
A69: Eggplant | B69: 2 | C69: Farming | D69: You shouldn't bother with this until you have access to . But with that buff it should come pretty quickly. Send your extras to Mariya for friendship xp, or sacrifice them in the Temple of Reward for small rewards.
A70: Emerald | B70: 1 | C70: Locksmith, Crafting | D70: You shouldn't really worry about crafting these much, unless you spend a lot of time in Mount Banon. You'll get more than enough to GM from opening for .
A71: Emerald Ring | B71: 2 | C71: Crafting | D71: It takes a lot of , but you should always try to craft your gems into rings when you open .
A72: Energy Coil | B72: 9 | C72: Crafting | D72: A lot goes into this craft, but the main limiting factor is probably going to be as you go. Mastery will take a while, GM will take forever.
A73: Engine | B73: 10 | C73: Crafting | D73: The amount of stamina and mental drain to craft these will drive you mad. Many different components, with many different zones necessary. The biggest cost is all of the and you will end up needing.
A74: Essence of Slime | B74: 3 | C74: Crafting | D74: Quite cheap and painless. Great use for so work on this while you work on those. Sells for decent silver too.
A75: Explosive | B75: 3 | C75: Crafting | D75: The harder of the two masteries, as it uses instead of , but still pretty cheap overall. Save working on this until you can mail them, and send them to Beatrix for friendship xp.
A76: Fancy Chair | B76: 9 | C76: Crafting | D76: THe hardest part of this is the . At 6 per chair you will need a significant amount. I would recommend using daily grape juice for the cotton, along with any crop multiplying meals on .
A77: Fancy Drum | B77: 6 | C77: Crafting | D77: Uses both and , which are side products of exploring in the Forest, but sadly uses too, which you cant make at the same time because you'll need the straw for rope to make nets. I suggest working on this either from trading for the paste/leather, or off an on when not actively exploring forest for nets.
A78: Fancy Guitar | B78: 6 | C78: Crafting | D78: Fairly cheap, but slow, if you wait for passive from steelworks. If you actively explore for it, you can get it done way quicker, but the cost increases a lot.
... A81: Fancy Table | B81: 9 | C81: Crafting | D81: Requires both and , as well as tons of . The only upside is the sell price.
A82: Fancy Violin | B82: 10 | C82: Crafting
A83: Feed | B83: 5 | C83: Feed Mill | D83: The biggest drawback is just waiting for it to process. Dump whatever extra crops you might be voiding in, or daily from pets is great too. There is a perk to make the mill process twice as fast, if you want to go for MM it's a good investment, otherwise don't bother.
A84: Fish Bones | B84: 4 | C84: Fishing | D84: Low rates, but you can get them from a few zones. Good for cooking or Mummy friendship xp.
A85: Fishing Net | B85: 2 | C85: Crafting | D85: You will definitely GM or even MM these at some point. Daily from your Raptor Pen after you unlock Whispering Creek, and exploring the Forest for them is the main way to make silver late game. Remember, you can't have a without a .
A86: Flamejack | B86: 1 | C86: Fishing | D86: Quick Lake Minerva mastery. Make sure you sell as you go.
A87: Flarefin | B87: 3 | C87: Fishing | D87: The hardest Lake Minerva fish (besides golden). But still not that bad. You should get a good bit of while GMing this.
A88: Flier | B88: 5 | C88: Fishing | D88: Definitely a harder fishing mastery. But at the end of day it's still just making and using more large nets.
A89: Flour | B89: 6 | C89: Flour Mill | D89: Each wheat makes 14 flour, so you don't need a crazy amount of wheat to GM this. There's a perk that makes the flour mill process twice as fast. Probably don't buy it unless you're rich or want to MM flour.
A90: Fluorifish | B90: 3 | C90: Fishing | D90: Medium speed Vast Ocean fish. Much quicker than octopus or squid.
A91: Flying Machine | B91: 10 | C91: Crafting | D91: One of the most expensive crafts in the game, even moreso than .
A92: Flywheel | B92: 10 | C92: Crafting | D92: are quite limited and/or costly, so GM will be a long road. Mastery is still very rough, but doable with time. Steelworks also occassionally produces these.
A93: Frost Shield | B93: 10 | C93: Crafting | D93: Requires , which is an SR from Glacier Lake, or the Spotted Seal pet. Not practical to work on GM, or even mastery really.
A94: Frosteye | B94: 1 | C94: Fishing | D94: A quick and painless Glacier Lake mastery. Should be the first or second you get once unlocking the zone.
A95: Frozen Bones | B95: 11 | C95: Fishing, Event
A96: Frozen Book | B96: 11 | C96: Fishing, Event
A97: Frozen Starfish | B97: 11 | C97: Fishing, Event
A98: Fruit Punch | B98: 10 | C98: Crafting | D98: Mastery and GM are both very expensive, and very not necessary. FP has little use, so working on this is purely to flex.
A99: Garnet | B99: 2 | C99: Crafting | D99: You should be crafting these as you explore Whispering Creek for and levels. You really want to craft if you can, but sometimes the paste need is too high, in which case you can just sell.
A100: Garnet Ring | B100: 3 | C100: Crafting | D100: Try to make these when exploring Whispering Creek for and xp. They sell quite nicely.
A101: Giant Squid | B101: 7 | C101: Fishing | D101: Slow Vast Ocean GM... But at the end of the day it's still just tossing nets, so low effort.
A102: Glass Bottle | B102: 1 | C102: Crafting | D102: You don't need to worry about focusing bottles specifically, you will naturally GM them by crafting daily juices and working on
A103: Glass Orb | B103: 1 | C103: Crafting | D103: You will naturally master these while working on other GMs/daily production. Glass.
A104: Glassback | B104: 1 | C104: Fishing | D104: Quick Glacier Lake mastery.
A105: Globber | B105: 4 | C105: Fishing | D105: A medium speed Lake Tempest/Crystal River fish, and you can suppliment progress a tiny bit with from the Small Cave.
A106: Gold Carrot | B106: 10 | C106: Farming | D106: Mastery will take a bit, but isn't that bad with and gold seeds from quests. GM will be pretty rough unless you have cookies to boost harvest amount.
A107: Gold Carrot | B107: 10 | C107: Farming
A108: Gold Catfish | B108: 10 | C108: Fishing
A109: Gold Coral | B109: 10 | C109: Fishing
A110: Gold Cucumber | B110: 8 | C110: Farming, Locksmith | D110: Grown from , if you have them, or a rare chance from . Also you can get these from which is from fishing at the Forest Pond. This is the easiest gold crop because of this.
A111: Gold Cucumber | B111: 8 | C111: Farming
A112: Gold Drum | B112: 10 | C112: Fishing
A113: Gold Eggplant | B113: 10 | C113: Farming | D113: Mastery will take a bit, but isn't that bad with and gold seeds from quests. GM will be pretty rough unless you have cookies to boost harvest amount.
A114: Gold Eggplant | B114: 10 | C114: Farming
A115: Gold Flier | B115: 10 | C115: Fishing
A116: Gold Jelly | B116: 10 | C116: Fishing
A117: Gold Peas | B117: 10 | C117: Farming | D117: Mastery will take a bit, but isn't that bad with and gold seeds from quests. GM will be pretty rough unless you have cookies to boost harvest amount.
A118: Gold Peas | B118: 10 | C118: Farming
A119: Gold Peppers | B119: 10 | C119: Farming | D119: Mastery will take a bit, but isn't that bad with and gold seeds from quests. GM will be pretty rough unless you have cookies to boost harvest amount.
...

Sheet Export 260901
A1: Item | B1: ItemID | C1: Mastered | D1: Grand Mastered | E1: Mega Mastered | F1: Progress | H1: King's Rating April 2023* | I1: Tower Req | K1: Mastered | L1: M Change | M1: % Change | P1: Grand Mastered | Q1: GM Change | R1: % Change | U1: Mega Mastered | V1: MM Change | W1: % Change
A2: Lobster | B2: 1155 | C2: 0 | D2: 0 | E2: 0 | F2: 1 | H2: =VLOOKUP(A2,'Kings Ratings'!$A$2:$B$1000,2,false) -> 11 | K2: 0 | L2: =C2-K2 -> 0 | M2: =L2/K2 -> #DIV/0! | N2: =CONCATENATE(A2, " with +",L2, ", +", 100*round(M2,3), "% (",K2, " to ",C2,")") -> #DIV/0! | P2: 0 | Q2: =D2-P2 -> 0 | R2: =Q2/P2 -> #DIV/0! | S2: =CONCATENATE(A2, " with +",Q2, ", +", 100*round(R2,3), "% (",P2, " to ",D2,")") -> #DIV/0! | U2: 0 | V2: =E2-U2 -> 0 | W2: =V2/U2 -> #DIV/0! | X2: =CONCATENATE(A2, " with +",V2, ", +", 100*round(W2,3), "% (",U2, " to ",E2,")") -> #DIV/0!
A3: Sea Urchin | B3: 1241 | C3: 0 | D3: 0 | E3: 0 | F3: 882 | H3: =VLOOKUP(A3,'Kings Ratings'!$A$2:$B$1000,2,false) -> 10 | K3: 0 | L3: =C3-K3 -> 0 | M3: =L3/K3 -> #DIV/0! | N3: =CONCATENATE(A3, " with +",L3, ", +", 100*round(M3,3), "% (",K3, " to ",C3,")") -> #DIV/0! | P3: 0 | Q3: =D3-P3 -> 0 | R3: =Q3/P3 -> #DIV/0! | S3: =CONCATENATE(A3, " with +",Q3, ", +", 100*round(R3,3), "% (",P3, " to ",D3,")") -> #DIV/0! | U3: 0 | V3: =E3-U3 -> 0 | W3: =V3/U3 -> #DIV/0! | X3: =CONCATENATE(A3, " with +",V3, ", +", 100*round(W3,3), "% (",U3, " to ",E3,")") -> #DIV/0!
A4: Ghost Jelly | B4: 1242 | C4: 0 | D4: 0 | E4: 0 | F4: 927 | H4: =VLOOKUP(A4,'Kings Ratings'!$A$2:$B$1000,2,false) -> 10 | K4: 0 | L4: =C4-K4 -> 0 | M4: =L4/K4 -> #DIV/0! | N4: =CONCATENATE(A4, " with +",L4, ", +", 100*round(M4,3), "% (",K4, " to ",C4,")") -> #DIV/0! | P4: 0 | Q4: =D4-P4 -> 0 | R4: =Q4/P4 -> #DIV/0! | S4: =CONCATENATE(A4, " with +",Q4, ", +", 100*round(R4,3), "% (",P4, " to ",D4,")") -> #DIV/0! | U4: 0 | V4: =E4-U4 -> 0 | W4: =V4/U4 -> #DIV/0! | X4: =CONCATENATE(A4, " with +",V4, ", +", 100*round(W4,3), "% (",U4, " to ",E4,")") -> #DIV/0!
A5: Barnacle Shell | B5: 1243 | C5: 0 | D5: 0 | E5: 0 | F5: 915 | H5: =VLOOKUP(A5,'Kings Ratings'!$A$2:$B$1000,2,false) -> 10 | K5: 0 | L5: =C5-K5 -> 0 | M5: =L5/K5 -> #DIV/0! | N5: =CONCATENATE(A5, " with +",L5, ", +", 100*round(M5,3), "% (",K5, " to ",C5,")") -> #DIV/0! | P5: 0 | Q5: =D5-P5 -> 0 | R5: =Q5/P5 -> #DIV/0! | S5: =CONCATENATE(A5, " with +",Q5, ", +", 100*round(R5,3), "% (",P5, " to ",D5,")") -> #DIV/0! | U5: 0 | V5: =E5-U5 -> 0 | W5: =V5/U5 -> #DIV/0! | X5: =CONCATENATE(A5, " with +",V5, ", +", 100*round(W5,3), "% (",U5, " to ",E5,")") -> #DIV/0!
A6: Ant Apple | B6: 1278 | C6: 0 | D6: 0 | E6: 0 | F6: 581 | H6: =VLOOKUP(A6,'Kings Ratings'!$A$2:$B$1000,2,false) -> 11 | K6: 0 | L6: =C6-K6 -> 0 | M6: =L6/K6 -> #DIV/0! | N6: =CONCATENATE(A6, " with +",L6, ", +", 100*round(M6,3), "% (",K6, " to ",C6,")") -> #DIV/0! | P6: 0 | Q6: =D6-P6 -> 0 | R6: =Q6/P6 -> #DIV/0! | S6: =CONCATENATE(A6, " with +",Q6, ", +", 100*round(R6,3), "% (",P6, " to ",D6,")") -> #DIV/0! | U6: 0 | V6: =E6-U6 -> 0 | W6: =V6/U6 -> #DIV/0! | X6: =CONCATENATE(A6, " with +",V6, ", +", 100*round(W6,3), "% (",U6, " to ",E6,")") -> #DIV/0!
A7: Apple Ant | B7: 1279 | C7: 0 | D7: 0 | E7: 0 | F7: 1163 | H7: =VLOOKUP(A7,'Kings Ratings'!$A$2:$B$1000,2,false) -> 11 | K7: 0 | L7: =C7-K7 -> 0 | M7: =L7/K7 -> #DIV/0! | N7: =CONCATENATE(A7, " with +",L7, ", +", 100*round(M7,3), "% (",K7, " to ",C7,")") -> #DIV/0! | P7: 0 | Q7: =D7-P7 -> 0 | R7: =Q7/P7 -> #DIV/0! | S7: =CONCATENATE(A7, " with +",Q7, ", +", 100*round(R7,3), "% (",P7, " to ",D7,")") -> #DIV/0! | U7: 0 | V7: =E7-U7 -> 0 | W7: =V7/U7 -> #DIV/0! | X7: =CONCATENATE(A7, " with +",V7, ", +", 100*round(W7,3), "% (",U7, " to ",E7,")") -> #DIV/0!
A8: 11th Leaf Centerpiece | B8: 1319 | C8: 0 | D8: 0 | E8: 0 | F8: 40 | H8: =VLOOKUP(A8,'Kings Ratings'!$A$2:$B$1000,2,false) -> 11 | K8: 0 | L8: =C8-K8 -> 0 | M8: =L8/K8 -> #DIV/0! | N8: =CONCATENATE(A8, " with +",L8, ", +", 100*round(M8,3), "% (",K8, " to ",C8,")") -> #DIV/0! | P8: 0 | Q8: =D8-P8 -> 0 | R8: =Q8/P8 -> #DIV/0! | S8: =CONCATENATE(A8, " with +",Q8, ", +", 100*round(R8,3), "% (",P8, " to ",D8,")") -> #DIV/0! | U8: 0 | V8: =E8-U8 -> 0 | W8: =V8/U8 -> #DIV/0! | X8: =CONCATENATE(A8, " with +",V8, ", +", 100*round(W8,3), "% (",U8, " to ",E8,")") -> #DIV/0!
A9: Lucky Corn | B9: 1461 | C9: 1 | D9: 0 | E9: 0 | F9: 0 | H9: =VLOOKUP(A9,'Kings Ratings'!$A$2:$B$1000,2,false) -> 11 | K9: 1 | L9: =C9-K9 -> 0 | M9: =L9/K9 -> 0 | N9: =CONCATENATE(A9, " with +",L9, ", +", 100*round(M9,3), "% (",K9, " to ",C9,")") -> Lucky Corn with +0, +0% (1 to 1) | P9: 0 | Q9: =D9-P9 -> 0 | R9: =Q9/P9 -> #DIV/0! | S9: =CONCATENATE(A9, " with +",Q9, ", +", 100*round(R9,3), "% (",P9, " to ",D9,")") -> #DIV/0! | U9: 0 | V9: =E9-U9 -> 0 | W9: =V9/U9 -> #DIV/0! | X9: =CONCATENATE(A9, " with +",V9, ", +", 100*round(W9,3), "% (",U9, " to ",E9,")") -> #DIV/0!
A10: Lucky Potato | B10: 1462 | C10: 1 | D10: 0 | E10: 0 | F10: 0 | H10: =VLOOKUP(A10,'Kings Ratings'!$A$2:$B$1000,2,false) -> 11 | K10: 1 | L10: =C10-K10 -> 0 | M10: =L10/K10 -> 0 | N10: =CONCATENATE(A10, " with +",L10, ", +", 100*round(M10,3), "% (",K10, " to ",C10,")") -> Lucky Potato with +0, +0% (1 to 1) | P10: 0 | Q10: =D10-P10 -> 0 | R10: =Q10/P10 -> #DIV/0! | S10: =CONCATENATE(A10, " with +",Q10, ", +", 100*round(R10,3), "% (",P10, " to ",D10,")") -> #DIV/0! | U10: 0 | V10: =E10-U10 -> 0 | W10: =V10/U10 -> #DIV/0! | X10: =CONCATENATE(A10, " with +",V10, ", +", 100*round(W10,3), "% (",U10, " to ",E10,")") -> #DIV/0!
A11: Lucky Trout | B11: 1465 | C11: 49 | D11: 0 | E11: 0 | F11: 0 | H11: =VLOOKUP(A11,'Kings Ratings'!$A$2:$B$1000,2,false) -> 11 | K11: 48 | L11: =C11-K11 -> 1 | M11: =L11/K11 -> 0.020833333 | N11: =CONCATENATE(A11, " with +",L11, ", +", 100*round(M11,3), "% (",K11, " to ",C11,")") -> Lucky Trout with +1, +2.1% (48 to 49) | P11: 0 | Q11: =D11-P11 -> 0 | R11: =Q11/P11 -> #DIV/0! | S11: =CONCATENATE(A11, " with +",Q11, ", +", 100*round(R11,3), "% (",P11, " to ",D11,")") -> #DIV/0! | U11: 0 | V11: =E11-U11 -> 0 | W11: =V11/U11 -> #DIV/0! | X11: =CONCATENATE(A11, " with +",V11, ", +", 100*round(W11,3), "% (",U11, " to ",E11,")") -> #DIV/0!
A12: Fuzzy Trout | B12: 1480 | C12: 159 | D12: 0 | E12: 0 | F12: 0 | H12: =VLOOKUP(A12,'Kings Ratings'!$A$2:$B$1000,2,false) -> 11 | K12: 159 | L12: =C12-K12 -> 0 | M12: =L12/K12 -> 0 | N12: =CONCATENATE(A12, " with +",L12, ", +", 100*round(M12,3), "% (",K12, " to ",C12,")") -> Fuzzy Trout with +0, +0% (159 to 159) | P12: 0 | Q12: =D12-P12 -> 0 | R12: =Q12/P12 -> #DIV/0! | S12: =CONCATENATE(A12, " with +",Q12, ", +", 100*round(R12,3), "% (",P12, " to ",D12,")") -> #DIV/0! | U12: 0 | V12: =E12-U12 -> 0 | W12: =V12/U12 -> #DIV/0! | X12: =CONCATENATE(A12, " with +",V12, ", +", 100*round(W12,3), "% (",U12, " to ",E12,")") -> #DIV/0!
A13: Red Velvet Cake | B13: 1496 | C13: 153 | D13: 0 | E13: 0 | F13: 0 | H13: =VLOOKUP(A13,'Kings Ratings'!$A$2:$B$1000,2,false) -> 9 | K13: 98 | L13: =C13-K13 -> 55 | M13: =L13/K13 -> 0.56122449 | N13: =CONCATENATE(A13, " with +",L13, ", +", 100*round(M13,3), "% (",K13, " to ",C13,")") -> Red Velvet Cake with +55, +56.1% (98 to 153) | P13: 0 | Q13: =D13-P13 -> 0 | R13: =Q13/P13 -> #DIV/0! | S13: =CONCATENATE(A13, " with +",Q13, ", +", 100*round(R13,3), "% (",P13, " to ",D13,")") -> #DIV/0! | U13: 0 | V13: =E13-U13 -> 0 | W13: =V13/U13 -> #DIV/0! | X13: =CONCATENATE(A13, " with +",V13, ", +", 100*round(W13,3), "% (",U13, " to ",E13,")") -> #DIV/0!
... A40: Cicada | B40: 1247 | C40: 612 | D40: 0 | E40: 0 | F40: 4456 | H40: =VLOOKUP(A40,'Kings Ratings'!$A$2:$B$1000,2,false) -> 11 | K40: 83 | L40: =C40-K40 -> 529 | M40: =L40/K40 -> 6.373494 | N40: =CONCATENATE(A40, " with +",L40, ", +", 100*round(M40,3), "% (",K40, " to ",C40,")") -> Cicada with +529, +637.3% (83 to 612) | P40: 0 | Q40: =D40-P40 -> 0 | R40: =Q40/P40 -> #DIV/0! | S40: =CONCATENATE(A40, " with +",Q40, ", +", 100*round(R40,3), "% (",P40, " to ",D40,")") -> #DIV/0! | U40: 0 | V40: =E40-U40 -> 0 | W40: =V40/U40 -> #DIV/0! | X40: =CONCATENATE(A40, " with +",V40, ", +", 100*round(W40,3), "% (",U40, " to ",E40,")") -> #DIV/0!
A41: Blue Milk | B41: 546 | C41: 4 | D41: 0 | E41: 0 | F41: 4456 | K41: 3 | L41: =C41-K41 -> 1 | M41: =L41/K41 -> 0.33333333 | N41: =CONCATENATE(A41, " with +",L41, ", +", 100*round(M41,3), "% (",K41, " to ",C41,")") -> Blue Milk with +1, +33.3% (3 to 4) | P41: 0 | Q41: =D41-P41 -> 0 | R41: =Q41/P41 -> #DIV/0! | S41: =CONCATENATE(A41, " with +",Q41, ", +", 100*round(R41,3), "% (",P41, " to ",D41,")") -> #DIV/0! | U41: 0 | V41: =E41-U41 -> 0 | W41: =V41/U41 -> #DIV/0! | X41: =CONCATENATE(A41, " with +",V41, ", +", 100*round(W41,3), "% (",U41, " to ",E41,")") -> #DIV/0!
A42: Aquacite | B42: 901 | C42: 49 | D42: 1 | E42: 0 | F42: 3264 | H42: =VLOOKUP(A42,'Kings Ratings'!$A$2:$B$1000,2,false) -> 10 | K42: 24 | L42: =C42-K42 -> 25 | M42: =L42/K42 -> 1.0416667 | N42: =CONCATENATE(A42, " with +",L42, ", +", 100*round(M42,3), "% (",K42, " to ",C42,")") -> Aquacite with +25, +104.2% (24 to 49) | P42: 1 | Q42: =D42-P42 -> 0 | R42: =Q42/P42 -> 0 | S42: =CONCATENATE(A42, " with +",Q42, ", +", 100*round(R42,3), "% (",P42, " to ",D42,")") -> Aquacite with +0, +0% (1 to 1) | U42: 0 | V42: =E42-U42 -> 0 | W42: =V42/U42 -> #DIV/0! | X42: =CONCATENATE(A42, " with +",V42, ", +", 100*round(W42,3), "% (",U42, " to ",E42,")") -> #DIV/0!
A43: Amber Cane | B43: 800 | C43: 4155 | D43: 1 | E43: 0 | F43: 15770 | H43: =VLOOKUP(A43,'Kings Ratings'!$A$2:$B$1000,2,false) -> 10 | K43: 3710 | L43: =C43-K43 -> 445 | M43: =L43/K43 -> 0.11994609 | N43: =CONCATENATE(A43, " with +",L43, ", +", 100*round(M43,3), "% (",K43, " to ",C43,")") -> Amber Cane with +445, +12% (3710 to 4155) | P43: 1 | Q43: =D43-P43 -> 0 | R43: =Q43/P43 -> 0 | S43: =CONCATENATE(A43, " with +",Q43, ", +", 100*round(R43,3), "% (",P43, " to ",D43,")") -> Amber Cane with +0, +0% (1 to 1) | U43: 0 | V43: =E43-U43 -> 0 | W43: =V43/U43 -> #DIV/0! | X43: =CONCATENATE(A43, " with +",V43, ", +", 100*round(W43,3), "% (",U43, " to ",E43,")") -> #DIV/0!
A44: Festive Eggnog | B44: 1157 | C44: 202 | D44: 1 | E44: 0 | F44: 6594 | H44: =VLOOKUP(A44,'Kings Ratings'!$A$2:$B$1000,2,false) -> 11 | K44: 202 | L44: =C44-K44 -> 0 | M44: =L44/K44 -> 0 | N44: =CONCATENATE(A44, " with +",L44, ", +", 100*round(M44,3), "% (",K44, " to ",C44,")") -> Festive Eggnog with +0, +0% (202 to 202) | P44: 1 | Q44: =D44-P44 -> 0 | R44: =Q44/P44 -> 0 | S44: =CONCATENATE(A44, " with +",Q44, ", +", 100*round(R44,3), "% (",P44, " to ",D44,")") -> Festive Eggnog with +0, +0% (1 to 1) | U44: 0 | V44: =E44-U44 -> 0 | W44: =V44/U44 -> #DIV/0! | X44: =CONCATENATE(A44, " with +",V44, ", +", 100*round(W44,3), "% (",U44, " to ",E44,")") -> #DIV/0!
A45: Fancy Sword | B45: 1328 | C45: 2342 | D45: 8 | E45: 0 | F45: 3050 | H45: =VLOOKUP(A45,'Kings Ratings'!$A$2:$B$1000,2,false) -> 10 | K45: 1639 | L45: =C45-K45 -> 703 | M45: =L45/K45 -> 0.42892007 | N45: =CONCATENATE(A45, " with +",L45, ", +", 100*round(M45,3), "% (",K45, " to ",C45,")") -> Fancy Sword with +703, +42.9% (1639 to 2342) | P45: 2 | Q45: =D45-P45 -> 6 | R45: =Q45/P45 -> 3 | S45: =CONCATENATE(A45, " with +",Q45, ", +", 100*round(R45,3), "% (",P45, " to ",D45,")") -> Fancy Sword with +6, +300% (2 to 8) | U45: 0 | V45: =E45-U45 -> 0 | W45: =V45/U45 -> #DIV/0! | X45: =CONCATENATE(A45, " with +",V45, ", +", 100*round(W45,3), "% (",U45, " to ",E45,")") -> #DIV/0!
A46: Gold Diamond Ring | B46: 1431 | C46: 862 | D46: 5 | E46: 0 | F46: 10101 | H46: =VLOOKUP(A46,'Kings Ratings'!$A$2:$B$1000,2,false) -> 8 | K46: 517 | L46: =C46-K46 -> 345 | M46: =L46/K46 -> 0.66731141 | N46: =CONCATENATE(A46, " with +",L46, ", +", 100*round(M46,3), "% (",K46, " to ",C46,")") -> Gold Diamond Ring with +345, +66.7% (517 to 862) | P46: 3 | Q46: =D46-P46 -> 2 | R46: =Q46/P46 -> 0.66666667 | S46: =CONCATENATE(A46, " with +",Q46, ", +", 100*round(R46,3), "% (",P46, " to ",D46,")") -> Gold Diamond Ring with +2, +66.7% (3 to 5) | U46: 0 | V46: =E46-U46 -> 0 | W46: =V46/U46 -> #DIV/0! | X46: =CONCATENATE(A46, " with +",V46, ", +", 100*round(W46,3), "% (",U46, " to ",E46,")") -> #DIV/0!
A47: Flarite | B47: 927 | C47: 77 | D47: 5 | E47: 0 | F47: 7146 | H47: =VLOOKUP(A47,'Kings Ratings'!$A$2:$B$1000,2,false) -> 10 | K47: 49 | L47: =C47-K47 -> 28 | M47: =L47/K47 -> 0.57142857 | N47: =CONCATENATE(A47, " with +",L47, ", +", 100*round(M47,3), "% (",K47, " to ",C47,")") -> Flarite with +28, +57.1% (49 to 77) | P47: 3 | Q47: =D47-P47 -> 2 | R47: =Q47/P47 -> 0.66666667 | S47: =CONCATENATE(A47, " with +",Q47, ", +", 100*round(R47,3), "% (",P47, " to ",D47,")") -> Flarite with +2, +66.7% (3 to 5) | U47: 0 | V47: =E47-U47 -> 0 | W47: =V47/U47 -> #DIV/0! | X47: =CONCATENATE(A47, " with +",V47, ", +", 100*round(W47,3), "% (",U47, " to ",E47,")") -> #DIV/0!
A48: Orange Butterfly | B48: 1396 | C48: 184 | D48: 9 | E48: 0 | F48: 1246 | H48: =VLOOKUP(A48,'Kings Ratings'!$A$2:$B$1000,2,false) -> 10 | K48: 75 | L48: =C48-K48 -> 109 | M48: =L48/K48 -> 1.4533333 | N48: =CONCATENATE(A48, " with +",L48, ", +", 100*round(M48,3), "% (",K48, " to ",C48,")") -> Orange Butterfly with +109, +145.3% (75 to 184) | P48: 4 | Q48: =D48-P48 -> 5 | R48: =Q48/P48 -> 1.25 | S48: =CONCATENATE(A48, " with +",Q48, ", +", 100*round(R48,3), "% (",P48, " to ",D48,")") -> Orange Butterfly with +5, +125% (4 to 9) | U48: 0 | V48: =E48-U48 -> 0 | W48: =V48/U48 -> #DIV/0! | X48: =CONCATENATE(A48, " with +",V48, ", +", 100*round(W48,3), "% (",U48, " to ",E48,")") -> #DIV/0!
A49: Gold Slimeback | B49: 1383 | C49: 50 | D49: 9 | E49: 1 | F49: 1307 | H49: =VLOOKUP(A49,'Kings Ratings'!$A$2:$B$1000,2,false) -> 9 | K49: 32 | L49: =C49-K49 -> 18 | M49: =L49/K49 -> 0.5625 | N49: =CONCATENATE(A49, " with +",L49, ", +", 100*round(M49,3), "% (",K49, " to ",C49,")") -> Gold Slimeback with +18, +56.3% (32 to 50) | P49: 4 | Q49: =D49-P49 -> 5 | R49: =Q49/P49 -> 1.25 | S49: =CONCATENATE(A49, " with +",Q49, ", +", 100*round(R49,3), "% (",P49, " to ",D49,")") -> Gold Slimeback with +5, +125% (4 to 9) | U49: 0 | V49: =E49-U49 -> 1 | W49: =V49/U49 -> #DIV/0! | X49: =CONCATENATE(A49, " with +",V49, ", +", 100*round(W49,3), "% (",U49, " to ",E49,")") -> #DIV/0!
A50: Runestone 20 | B50: 230 | C50: 11852 | D50: 20 | E50: 0 | F50: 24551 | H50: =VLOOKUP(A50,'Kings Ratings'!$A$2:$B$1000,2,false) -> 10 | K50: 11087 | L50: =C50-K50 -> 765 | M50: =L50/K50 -> 0.068999729 | N50: =CONCATENATE(A50, " with +",L50, ", +", 100*round(M50,3), "% (",K50, " to ",C50,")") -> Runestone 20 with +765, +6.9% (11087 to 11852) | P50: 4 | Q50: =D50-P50 -> 16 | R50: =Q50/P50 -> 4 | S50: =CONCATENATE(A50, " with +",Q50, ", +", 100*round(R50,3), "% (",P50, " to ",D50,")") -> Runestone 20 with +16, +400% (4 to 20) | U50: 0 | V50: =E50-U50 -> 0 | W50: =V50/U50 -> #DIV/0! | X50: =CONCATENATE(A50, " with +",V50, ", +", 100*round(W50,3), "% (",U50, " to ",E50,")") -> #DIV/0!
A51: Runestone 16 | B51: 226 | C51: 11650 | D51: 20 | E51: 0 | F51: 23135 | H51: =VLOOKUP(A51,'Kings Ratings'!$A$2:$B$1000,2,false) -> 10 | K51: 10873 | L51: =C51-K51 -> 777 | M51: =L51/K51 -> 0.071461418 | N51: =CONCATENATE(A51, " with +",L51, ", +", 100*round(M51,3), "% (",K51, " to ",C51,")") -> Runestone 16 with +777, +7.1% (10873 to 11650) | P51: 5 | Q51: =D51-P51 -> 15 | R51: =Q51/P51 -> 3 | S51: =CONCATENATE(A51, " with +",Q51, ", +", 100*round(R51,3), "% (",P51, " to ",D51,")") -> Runestone 16 with +15, +300% (5 to 20) | U51: 0 | V51: =E51-U51 -> 0 | W51: =V51/U51 -> #DIV/0! | X51: =CONCATENATE(A51, " with +",V51, ", +", 100*round(W51,3), "% (",U51, " to ",E51,")") -> #DIV/0!
A52: Black Cloak | B52: 1401 | C52: 250 | D52: 19 | E52: 0 | F52: 812 | H52: =VLOOKUP(A52,'Kings Ratings'!$A$2:$B$1000,2,false) -> 8 | K52: 137 | L52: =C52-K52 -> 113 | M52: =L52/K52 -> 0.82481752 | N52: =CONCATENATE(A52, " with +",L52, ", +", 100*round(M52,3), "% (",K52, " to ",C52,")") -> Black Cloak with +113, +82.5% (137 to 250) | P52: 7 | Q52: =D52-P52 -> 12 | R52: =Q52/P52 -> 1.7142857 | S52: =CONCATENATE(A52, " with +",Q52, ", +", 100*round(R52,3), "% (",P52, " to ",D52,")") -> Black Cloak with +12, +171.4% (7 to 19) | U52: 0 | V52: =E52-U52 -> 0 | W52: =V52/U52 -> #DIV/0! | X52: =CONCATENATE(A52, " with +",V52, ", +", 100*round(W52,3), "% (",U52, " to ",E52,")") -> #DIV/0!
A53: Red Butterfly | B53: 1210 | C53: 272 | D53: 10 | E53: 0 | F53: 2055 | H53: =VLOOKUP(A53,'Kings Ratings'!$A$2:$B$1000,2,false) -> 10 | K53: 198 | L53: =C53-K53 -> 74 | M53: =L53/K53 -> 0.37373737 | N53: =CONCATENATE(A53, " with +",L53, ", +", 100*round(M53,3), "% (",K53, " to ",C53,")") -> Red Butterfly with +74, +37.4% (198 to 272) | P53: 7 | Q53: =D53-P53 -> 3 | R53: =Q53/P53 -> 0.42857143 | S53: =CONCATENATE(A53, " with +",Q53, ", +", 100*round(R53,3), "% (",P53, " to ",D53,")") -> Red Butterfly with +3, +42.9% (7 to 10) | U53: 0 | V53: =E53-U53 -> 0 | W53: =V53/U53 -> #DIV/0! | X53: =CONCATENATE(A53, " with +",V53, ", +", 100*round(W53,3), "% (",U53, " to ",E53,")") -> #DIV/0!
... A296: Blue Diary | B296: 896 | C296: 11559 | D296: 6008 | E296: 668 | F296: 958084 | H296: =VLOOKUP(A296,'Kings Ratings'!$A$2:$B$1000,2,false) -> 2 | K296: 10682 | L296: =C296-K296 -> 877 | M296: =L296/K296 -> 0.08210073 | N296: =CONCATENATE(A296, " with +",L296, ", +", 100*round(M296,3), "% (",K296, " to ",C296,")") -> Blue Diary with +877, +8.2% (10682 to 11559) | P296: 5482 | Q296: =D296-P296 -> 526 | R296: =Q296/P296 -> 0.095950383 | S296: =CONCATENATE(A296, " with +",Q296, ", +", 100*round(R296,3), "% (",P296, " to ",D296,")") -> Blue Diary with +526, +9.6% (5482 to 6008) | U296: 555 | V296: =E296-U296 -> 113 | W296: =V296/U296 -> 0.2036036 | X296: =CONCATENATE(A296, " with +",V296, ", +", 100*round(W296,3), "% (",U296, " to ",E296,")") -> Blue Diary with +113, +20.4% (555 to 668)
A297: Wizard Hat | B297: 240 | C297: 10457 | D297: 1584 | E297: 721 | F297: 639619 | H297: =VLOOKUP(A297,'Kings Ratings'!$A$2:$B$1000,2,false) -> 7 | I297: 300 | K297: 9605 | L297: =C297-K297 -> 852 | M297: =L297/K297 -> 0.0887038 | N297: =CONCATENATE(A297, " with +",L297, ", +", 100*round(M297,3), "% (",K297, " to ",C297,")") -> Wizard Hat with +852, +8.9% (9605 to 10457) | P297: 1374 | Q297: =D297-P297 -> 210 | R297: =Q297/P297 -> 0.15283843 | S297: =CONCATENATE(A297, " with +",Q297, ", +", 100*round(R297,3), "% (",P297, " to ",D297,")") -> Wizard Hat with +210, +15.3% (1374 to 1584) | U297: 560 | V297: =E297-U297 -> 161 | W297: =V297/U297 -> 0.2875 | X297: =CONCATENATE(A297, " with +",V297, ", +", 100*round(W297,3), "% (",U297, " to ",E297,")") -> Wizard Hat with +161, +28.8% (560 to 721)
A298: Mini Slime Squid | B298: 1378 | C298: 2410 | D298: 2182 | E298: 1167 | F298: 185943 | H298: =VLOOKUP(A298,'Kings Ratings'!$A$2:$B$1000,2,false) -> 4 | K298: 1694 | L298: =C298-K298 -> 716 | M298: =L298/K298 -> 0.42266824 | N298: =CONCATENATE(A298, " with +",L298, ", +", 100*round(M298,3), "% (",K298, " to ",C298,")") -> Mini Slime Squid with +716, +42.3% (1694 to 2410) | P298: 1413 | Q298: =D298-P298 -> 769 | R298: =Q298/P298 -> 0.54423213 | S298: =CONCATENATE(A298, " with +",Q298, ", +", 100*round(R298,3), "% (",P298, " to ",D298,")") -> Mini Slime Squid with +769, +54.4% (1413 to 2182) | U298: 560 | V298: =E298-U298 -> 607 | W298: =V298/U298 -> 1.0839286 | X298: =CONCATENATE(A298, " with +",V298, ", +", 100*round(W298,3), "% (",U298, " to ",E298,")") -> Mini Slime Squid with +607, +108.4% (560 to 1167)
A299: Tin Can | B299: 1382 | C299: 2410 | D299: 2184 | E299: 1167 | F299: 186929 | H299: =VLOOKUP(A299,'Kings Ratings'!$A$2:$B$1000,2,false) -> 4 | K299: 1696 | L299: =C299-K299 -> 714 | M299: =L299/K299 -> 0.42099057 | N299: =CONCATENATE(A299, " with +",L299, ", +", 100*round(M299,3), "% (",K299, " to ",C299,")") -> Tin Can with +714, +42.1% (1696 to 2410) | P299: 1417 | Q299: =D299-P299 -> 767 | R299: =Q299/P299 -> 0.5412844 | S299: =CONCATENATE(A299, " with +",Q299, ", +", 100*round(R299,3), "% (",P299, " to ",D299,")") -> Tin Can with +767, +54.1% (1417 to 2184) | U299: 560 | V299: =E299-U299 -> 607 | W299: =V299/U299 -> 1.0839286 | X299: =CONCATENATE(A299, " with +",V299, ", +", 100*round(W299,3), "% (",U299, " to ",E299,")") -> Tin Can with +607, +108.4% (560 to 1167)
A300: Gold Ring | B300: 1380 | C300: 2410 | D300: 2184 | E300: 1168 | F300: 185978 | H300: =VLOOKUP(A300,'Kings Ratings'!$A$2:$B$1000,2,false) -> 7 | K300: 1695 | L300: =C300-K300 -> 715 | M300: =L300/K300 -> 0.42182891 | N300: =CONCATENATE(A300, " with +",L300, ", +", 100*round(M300,3), "% (",K300, " to ",C300,")") -> Gold Ring with +715, +42.2% (1695 to 2410) | P300: 1417 | Q300: =D300-P300 -> 767 | R300: =Q300/P300 -> 0.5412844 | S300: =CONCATENATE(A300, " with +",Q300, ", +", 100*round(R300,3), "% (",P300, " to ",D300,")") -> Gold Ring with +767, +54.1% (1417 to 2184) | U300: 560 | V300: =E300-U300 -> 608 | W300: =V300/U300 -> 1.0857143 | X300: =CONCATENATE(A300, " with +",V300, ", +", 100*round(W300,3), "% (",U300, " to ",E300,")") -> Gold Ring with +608, +108.6% (560 to 1168)
A301: Red Trunk | B301: 760 | C301: 6105 | D301: 1278 | E301: 746 | F301: 78666 | H301: =VLOOKUP(A301,'Kings Ratings'!$A$2:$B$1000,2,false) -> 9 | I301: 299 | K301: 5575 | L301: =C301-K301 -> 530 | M301: =L301/K301 -> 0.095067265 | N301: =CONCATENATE(A301, " with +",L301, ", +", 100*round(M301,3), "% (",K301, " to ",C301,")") -> Red Trunk with +530, +9.5% (5575 to 6105) | P301: 1049 | Q301: =D301-P301 -> 229 | R301: =Q301/P301 -> 0.21830315 | S301: =CONCATENATE(A301, " with +",Q301, ", +", 100*round(R301,3), "% (",P301, " to ",D301,")") -> Red Trunk with +229, +21.8% (1049 to 1278) | U301: 576 | V301: =E301-U301 -> 170 | W301: =V301/U301 -> 0.29513889 | X301: =CONCATENATE(A301, " with +",V301, ", +", 100*round(W301,3), "% (",U301, " to ",E301,")") -> Red Trunk with +170, +29.5% (576 to 746)
A302: Blue Parchment | B302: 895 | C302: 13701 | D302: 7077 | E302: 702 | F302: 887575 | H302: =VLOOKUP(A302,'Kings Ratings'!$A$2:$B$1000,2,false) -> 2 | K302: 12691 | L302: =C302-K302 -> 1010 | M302: =L302/K302 -> 0.079583957 | N302: =CONCATENATE(A302, " with +",L302, ", +", 100*round(M302,3), "% (",K302, " to ",C302,")") -> Blue Parchment with +1010, +8% (12691 to 13701) | P302: 6472 | Q302: =D302-P302 -> 605 | R302: =Q302/P302 -> 0.093479604 | S302: =CONCATENATE(A302, " with +",Q302, ", +", 100*round(R302,3), "% (",P302, " to ",D302,")") -> Blue Parchment with +605, +9.3% (6472 to 7077) | U302: 576 | V302: =E302-U302 -> 126 | W302: =V302/U302 -> 0.21875 | X302: =CONCATENATE(A302, " with +",V302, ", +", 100*round(W302,3), "% (",U302, " to ",E302,")") -> Blue Parchment with +126, +21.9% (576 to 702)
A303: Frozen Sheepshead | B303: 943 | C303: 10667 | D303: 6022 | E303: 581 | F303: 1281246 | H303: =VLOOKUP(A303,'Kings Ratings'!$A$2:$B$1000,2,false) -> 11 | K303: 10666 | L303: =C303-K303 -> 1 | M303: =L303/K303 -> 9.375586e-05 | N303: =CONCATENATE(A303, " with +",L303, ", +", 100*round(M303,3), "% (",K303, " to ",C303,")") -> Frozen Sheepshead with +1, +0% (10666 to 10667) | P303: 6022 | Q303: =D303-P303 -> 0 | R303: =Q303/P303 -> 0 | S303: =CONCATENATE(A303, " with +",Q303, ", +", 100*round(R303,3), "% (",P303, " to ",D303,")") -> Frozen Sheepshead with +0, +0% (6022 to 6022) | U303: 581 | V303: =E303-U303 -> 0 | W303: =V303/U303 -> 0 | X303: =CONCATENATE(A303, " with +",V303, ", +", 100*round(W303,3), "% (",U303, " to ",E303,")") -> Frozen Sheepshead with +0, +0% (581 to 581)
A304: Linked Lantern | B304: 837 | C304: 14130 | D304: 6712 | E304: 791 | F304: 379090 | H304: =VLOOKUP(A304,'Kings Ratings'!$A$2:$B$1000,2,false) -> 5 | K304: 12991 | L304: =C304-K304 -> 1139 | M304: =L304/K304 -> 0.087676083 | N304: =CONCATENATE(A304, " with +",L304, ", +", 100*round(M304,3), "% (",K304, " to ",C304,")") -> Linked Lantern with +1139, +8.8% (12991 to 14130) | P304: 6037 | Q304: =D304-P304 -> 675 | R304: =Q304/P304 -> 0.1118105 | S304: =CONCATENATE(A304, " with +",Q304, ", +", 100*round(R304,3), "% (",P304, " to ",D304,")") -> Linked Lantern with +675, +11.2% (6037 to 6712) | U304: 588 | V304: =E304-U304 -> 203 | W304: =V304/U304 -> 0.3452381 | X304: =CONCATENATE(A304, " with +",V304, ", +", 100*round(W304,3), "% (",U304, " to ",E304,")") -> Linked Lantern with +203, +34.5% (588 to 791)
A305: Bone Pickaxe | B305: 879 | C305: 8576 | D305: 2716 | E305: 701 | F305: 1009996 | H305: =VLOOKUP(A305,'Kings Ratings'!$A$2:$B$1000,2,false) -> 9 | K305: 7704 | L305: =C305-K305 -> 872 | M305: =L305/K305 -> 0.11318795 | N305: =CONCATENATE(A305, " with +",L305, ", +", 100*round(M305,3), "% (",K305, " to ",C305,")") -> Bone Pickaxe with +872, +11.3% (7704 to 8576) | P305: 2361 | Q305: =D305-P305 -> 355 | R305: =Q305/P305 -> 0.15036002 | S305: =CONCATENATE(A305, " with +",Q305, ", +", 100*round(R305,3), "% (",P305, " to ",D305,")") -> Bone Pickaxe with +355, +15% (2361 to 2716) | U305: 631 | V305: =E305-U305 -> 70 | W305: =V305/U305 -> 0.11093502 | X305: =CONCATENATE(A305, " with +",V305, ", +", 100*round(W305,3), "% (",U305, " to ",E305,")") -> Bone Pickaxe with +70, +11.1% (631 to 701)
A306: Cucumber | B306: 29 | C306: 18277 | D306: 6467 | E306: 742 | F306: 1113525 | H306: =VLOOKUP(A306,'Kings Ratings'!$A$2:$B$1000,2,false) -> 2 | K306: 17308 | L306: =C306-K306 -> 969 | M306: =L306/K306 -> 0.055985671 | N306: =CONCATENATE(A306, " with +",L306, ", +", 100*round(M306,3), "% (",K306, " to ",C306,")") -> Cucumber with +969, +5.6% (17308 to 18277) | P306: 5906 | Q306: =D306-P306 -> 561 | R306: =Q306/P306 -> 0.094988148 | S306: =CONCATENATE(A306, " with +",Q306, ", +", 100*round(R306,3), "% (",P306, " to ",D306,")") -> Cucumber with +561, +9.5% (5906 to 6467) | U306: 634 | V306: =E306-U306 -> 108 | W306: =V306/U306 -> 0.170347 | X306: =CONCATENATE(A306, " with +",V306, ", +", 100*round(W306,3), "% (",U306, " to ",E306,")") -> Cucumber with +108, +17% (634 to 742)
A307: Wrench | B307: 594 | C307: 14213 | D307: 3075 | E307: 847 | F307: 563055 | H307: =VLOOKUP(A307,'Kings Ratings'!$A$2:$B$1000,2,false) -> 6 | I307: 298 | K307: 13235 | L307: =C307-K307 -> 978 | M307: =L307/K307 -> 0.073894975 | N307: =CONCATENATE(A307, " with +",L307, ", +", 100*round(M307,3), "% (",K307, " to ",C307,")") -> Wrench with +978, +7.4% (13235 to 14213) | P307: 2804 | Q307: =D307-P307 -> 271 | R307: =Q307/P307 -> 0.096647646 | S307: =CONCATENATE(A307, " with +",Q307, ", +", 100*round(R307,3), "% (",P307, " to ",D307,")") -> Wrench with +271, +9.7% (2804 to 3075) | U307: 662 | V307: =E307-U307 -> 185 | W307: =V307/U307 -> 0.27945619 | X307: =CONCATENATE(A307, " with +",V307, ", +", 100*round(W307,3), "% (",U307, " to ",E307,")") -> Wrench with +185, +27.9% (662 to 847)
A308: Spoon | B308: 675 | C308: 12485 | D308: 5974 | E308: 850 | F308: 1014847 | H308: =VLOOKUP(A308,'Kings Ratings'!$A$2:$B$1000,2,false) -> 5 | K308: 11616 | L308: =C308-K308 -> 869 | M308: =L308/K308 -> 0.074810606 | N308: =CONCATENATE(A308, " with +",L308, ", +", 100*round(M308,3), "% (",K308, " to ",C308,")") -> Spoon with +869, +7.5% (11616 to 12485) | P308: 5450 | Q308: =D308-P308 -> 524 | R308: =Q308/P308 -> 0.096146789 | S308: =CONCATENATE(A308, " with +",Q308, ", +", 100*round(R308,3), "% (",P308, " to ",D308,")") -> Spoon with +524, +9.6% (5450 to 5974) | U308: 692 | V308: =E308-U308 -> 158 | W308: =V308/U308 -> 0.2283237 | X308: =CONCATENATE(A308, " with +",V308, ", +", 100*round(W308,3), "% (",U308, " to ",E308,")") -> Spoon with +158, +22.8% (692 to 850)
A309: Feed | B309: 275 | C309: 36607 | D309: 13136 | E309: 799 | F309: 1102066 | H309: =VLOOKUP(A309,'Kings Ratings'!$A$2:$B$1000,2,false) -> 5 | K309: 34547 | L309: =C309-K309 -> 2060 | M309: =L309/K309 -> 0.059628911 | N309: =CONCATENATE(A309, " with +",L309, ", +", 100*round(M309,3), "% (",K309, " to ",C309,")") -> Feed with +2060, +6% (34547 to 36607) | P309: 12119 | Q309: =D309-P309 -> 1017 | R309: =Q309/P309 -> 0.083917815 | S309: =CONCATENATE(A309, " with +",Q309, ", +", 100*round(R309,3), "% (",P309, " to ",D309,")") -> Feed with +1017, +8.4% (12119 to 13136) | U309: 693 | V309: =E309-U309 -> 106 | W309: =V309/U309 -> 0.15295815 | X309: =CONCATENATE(A309, " with +",V309, ", +", 100*round(W309,3), "% (",U309, " to ",E309,")") -> Feed with +106, +15.3% (693 to 799)
A310: Fancy Drum | B310: 474 | C310: 9840 | D310: 2406 | E310: 918 | F310: 265988 | H310: =VLOOKUP(A310,'Kings Ratings'!$A$2:$B$1000,2,false) -> 6 | I310: 295 | K310: 9204 | L310: =C310-K310 -> 636 | M310: =L310/K310 -> 0.069100391 | N310: =CONCATENATE(A310, " with +",L310, ", +", 100*round(M310,3), "% (",K310, " to ",C310,")") -> Fancy Drum with +636, +6.9% (9204 to 9840) | P310: 2159 | Q310: =D310-P310 -> 247 | R310: =Q310/P310 -> 0.11440482 | S310: =CONCATENATE(A310, " with +",Q310, ", +", 100*round(R310,3), "% (",P310, " to ",D310,")") -> Fancy Drum with +247, +11.4% (2159 to 2406) | U310: 711 | V310: =E310-U310 -> 207 | W310: =V310/U310 -> 0.29113924 | X310: =CONCATENATE(A310, " with +",V310, ", +", 100*round(W310,3), "% (",U310, " to ",E310,")") -> Fancy Drum with +207, +29.1% (711 to 918)
A311: Leather Bag | B311: 166 | C311: 13074 | D311: 5333 | E311: 927 | F311: 1037200 | H311: =VLOOKUP(A311,'Kings Ratings'!$A$2:$B$1000,2,false) -> 2 | I311: 296 | K311: 12085 | L311: =C311-K311 -> 989 | M311: =L311/K311 -> 0.081836988 | N311: =CONCATENATE(A311, " with +",L311, ", +", 100*round(M311,3), "% (",K311, " to ",C311,")") -> Leather Bag with +989, +8.2% (12085 to 13074) | P311: 4875 | Q311: =D311-P311 -> 458 | R311: =Q311/P311 -> 0.093948718 | S311: =CONCATENATE(A311, " with +",Q311, ", +", 100*round(R311,3), "% (",P311, " to ",D311,")") -> Leather Bag with +458, +9.4% (4875 to 5333) | U311: 716 | V311: =E311-U311 -> 211 | W311: =V311/U311 -> 0.29469274 | X311: =CONCATENATE(A311, " with +",V311, ", +", 100*round(W311,3), "% (",U311, " to ",E311,")") -> Leather Bag with +211, +29.5% (716 to 927)
A312: Eggplant | B312: 13 | C312: 22315 | D312: 6890 | E312: 838 | F312: 1169888 | H312: =VLOOKUP(A312,'Kings Ratings'!$A$2:$B$1000,2,false) -> 2 | K312: 22142 | L312: =C312-K312 -> 173 | M312: =L312/K312 -> 0.0078132057 | N312: =CONCATENATE(A312, " with +",L312, ", +", 100*round(M312,3), "% (",K312, " to ",C312,")") -> Eggplant with +173, +0.8% (22142 to 22315) | P312: 6348 | Q312: =D312-P312 -> 542 | R312: =Q312/P312 -> 0.085381222 | S312: =CONCATENATE(A312, " with +",Q312, ", +", 100*round(R312,3), "% (",P312, " to ",D312,")") -> Eggplant with +542, +8.5% (6348 to 6890) | U312: 725 | V312: =E312-U312 -> 113 | W312: =V312/U312 -> 0.15586207 | X312: =CONCATENATE(A312, " with +",V312, ", +", 100*round(W312,3), "% (",U312, " to ",E312,")") -> Eggplant with +113, +15.6% (725 to 838)
A313: Salt | B313: 305 | C313: 20787 | D313: 7074 | E313: 968 | F313: 563503 | H313: =VLOOKUP(A313,'Kings Ratings'!$A$2:$B$1000,2,false) -> 7 | I313: 294 | K313: 19562 | L313: =C313-K313 -> 1225 | M313: =L313/K313 -> 0.062621409 | N313: =CONCATENATE(A313, " with +",L313, ", +", 100*round(M313,3), "% (",K313, " to ",C313,")") -> Salt with +1225, +6.3% (19562 to 20787) | P313: 6480 | Q313: =D313-P313 -> 594 | R313: =Q313/P313 -> 0.091666667 | S313: =CONCATENATE(A313, " with +",Q313, ", +", 100*round(R313,3), "% (",P313, " to ",D313,")") -> Salt with +594, +9.2% (6480 to 7074) | U313: 769 | V313: =E313-U313 -> 199 | W313: =V313/U313 -> 0.25877763 | X313: =CONCATENATE(A313, " with +",V313, ", +", 100*round(W313,3), "% (",U313, " to ",E313,")") -> Salt with +199, +25.9% (769 to 968)
A314: Corn | B314: 65 | C314: 39175 | D314: 11397 | E314: 1015 | F314: 784336 | H314: =VLOOKUP(A314,'Kings Ratings'!$A$2:$B$1000,2,false) -> 7 | K314: 43435 | L314: =C314-K314 -> -4260 | M314: =L314/K314 -> -0.098077587 | N314: =CONCATENATE(A314, " with +",L314, ", +", 100*round(M314,3), "% (",K314, " to ",C314,")") -> Corn with +-4260, +-9.8% (43435 to 39175) | P314: 10526 | Q314: =D314-P314 -> 871 | R314: =Q314/P314 -> 0.082747482 | S314: =CONCATENATE(A314, " with +",Q314, ", +", 100*round(R314,3), "% (",P314, " to ",D314,")") -> Corn with +871, +8.3% (10526 to 11397) | U314: 786 | V314: =E314-U314 -> 229 | W314: =V314/U314 -> 0.2913486 | X314: =CONCATENATE(A314, " with +",V314, ", +", 100*round(W314,3), "% (",U314, " to ",E314,")") -> Corn with +229, +29.1% (786 to 1015)
A315: Frozen Bones | B315: 951 | C315: 15271 | D315: 7198 | E315: 791 | F315: 840024 | H315: =VLOOKUP(A315,'Kings Ratings'!$A$2:$B$1000,2,false) -> 11 | K315: 15264 | L315: =C315-K315 -> 7 | M315: =L315/K315 -> 0.00045859539 | N315: =CONCATENATE(A315, " with +",L315, ", +", 100*round(M315,3), "% (",K315, " to ",C315,")") -> Frozen Bones with +7, +0% (15264 to 15271) | P315: 7194 | Q315: =D315-P315 -> 4 | R315: =Q315/P315 -> 0.0005560189 | S315: =CONCATENATE(A315, " with +",Q315, ", +", 100*round(R315,3), "% (",P315, " to ",D315,")") -> Frozen Bones with +4, +0.1% (7194 to 7198) | U315: 791 | V315: =E315-U315 -> 0 | W315: =V315/U315 -> 0 | X315: =CONCATENATE(A315, " with +",V315, ", +", 100*round(W315,3), "% (",U315, " to ",E315,")") -> Frozen Bones with +0, +0% (791 to 791)
A316: Fancy Pan Flute | B316: 737 | C316: 6362 | D316: 2484 | E316: 1026 | F316: 499636 | H316: =VLOOKUP(A316,'Kings Ratings'!$A$2:$B$1000,2,false) -> 6 | I316: 295 | K316: 5855 | L316: =C316-K316 -> 507 | M316: =L316/K316 -> 0.086592656 | N316: =CONCATENATE(A316, " with +",L316, ", +", 100*round(M316,3), "% (",K316, " to ",C316,")") -> Fancy Pan Flute with +507, +8.7% (5855 to 6362) | P316: 2236 | Q316: =D316-P316 -> 248 | R316: =Q316/P316 -> 0.11091234 | S316: =CONCATENATE(A316, " with +",Q316, ", +", 100*round(R316,3), "% (",P316, " to ",D316,")") -> Fancy Pan Flute with +248, +11.1% (2236 to 2484) | U316: 792 | V316: =E316-U316 -> 234 | W316: =V316/U316 -> 0.29545455 | X316: =CONCATENATE(A316, " with +",V316, ", +", 100*round(W316,3), "% (",U316, " to ",E316,")") -> Fancy Pan Flute with +234, +29.5% (792 to 1026)
A317: Sewing Needle | B317: 1129 | C317: 9018 | D317: 3339 | E317: 1015 | F317: 1124044 | H317: =VLOOKUP(A317,'Kings Ratings'!$A$2:$B$1000,2,false) -> 4 | I317: 300 | K317: 8239 | L317: =C317-K317 -> 779 | M317: =L317/K317 -> 0.094550309 | N317: =CONCATENATE(A317, " with +",L317, ", +", 100*round(M317,3), "% (",K317, " to ",C317,")") -> Sewing Needle with +779, +9.5% (8239 to 9018) | P317: 2938 | Q317: =D317-P317 -> 401 | R317: =Q317/P317 -> 0.13648741 | S317: =CONCATENATE(A317, " with +",Q317, ", +", 100*round(R317,3), "% (",P317, " to ",D317,")") -> Sewing Needle with +401, +13.6% (2938 to 3339) | U317: 845 | V317: =E317-U317 -> 170 | W317: =V317/U317 -> 0.20118343 | X317: =CONCATENATE(A317, " with +",V317, ", +", 100*round(W317,3), "% (",U317, " to ",E317,")") -> Sewing Needle with +170, +20.1% (845 to 1015)
A318: Water Lily | B318: 378 | C318: 12767 | D318: 4327 | E318: 1022 | F318: 1014503 | H318: =VLOOKUP(A318,'Kings Ratings'!$A$2:$B$1000,2,false) -> 10 | I318: 300 | K318: 11912 | L318: =C318-K318 -> 855 | M318: =L318/K318 -> 0.07177636 | N318: =CONCATENATE(A318, " with +",L318, ", +", 100*round(M318,3), "% (",K318, " to ",C318,")") -> Water Lily with +855, +7.2% (11912 to 12767) | P318: 3875 | Q318: =D318-P318 -> 452 | R318: =Q318/P318 -> 0.11664516 | S318: =CONCATENATE(A318, " with +",Q318, ", +", 100*round(R318,3), "% (",P318, " to ",D318,")") -> Water Lily with +452, +11.7% (3875 to 4327) | U318: 858 | V318: =E318-U318 -> 164 | W318: =V318/U318 -> 0.19114219 | X318: =CONCATENATE(A318, " with +",V318, ", +", 100*round(W318,3), "% (",U318, " to ",E318,")") -> Water Lily with +164, +19.1% (858 to 1022)
A319: Sturdy Sword | B319: 300 | C319: 20423 | D319: 8191 | E319: 1083 | F319: 1012632 | H319: =VLOOKUP(A319,'Kings Ratings'!$A$2:$B$1000,2,false) -> 2 | I319: 299 | K319: 19109 | L319: =C319-K319 -> 1314 | M319: =L319/K319 -> 0.06876341 | N319: =CONCATENATE(A319, " with +",L319, ", +", 100*round(M319,3), "% (",K319, " to ",C319,")") -> Sturdy Sword with +1314, +6.9% (19109 to 20423) | P319: 7565 | Q319: =D319-P319 -> 626 | R319: =Q319/P319 -> 0.082749504 | S319: =CONCATENATE(A319, " with +",Q319, ", +", 100*round(R319,3), "% (",P319, " to ",D319,")") -> Sturdy Sword with +626, +8.3% (7565 to 8191) | U319: 862 | V319: =E319-U319 -> 221 | W319: =V319/U319 -> 0.25638051 | X319: =CONCATENATE(A319, " with +",V319, ", +", 100*round(W319,3), "% (",U319, " to ",E319,")") -> Sturdy Sword with +221, +25.6% (862 to 1083)
A320: Fancy Guitar | B320: 393 | C320: 13711 | D320: 3657 | E320: 1092 | F320: 1010438 | H320: =VLOOKUP(A320,'Kings Ratings'!$A$2:$B$1000,2,false) -> 6 | I320: 295 | K320: 12848 | L320: =C320-K320 -> 863 | M320: =L320/K320 -> 0.067169988 | N320: =CONCATENATE(A320, " with +",L320, ", +", 100*round(M320,3), "% (",K320, " to ",C320,")") -> Fancy Guitar with +863, +6.7% (12848 to 13711) | P320: 3374 | Q320: =D320-P320 -> 283 | R320: =Q320/P320 -> 0.083876704 | S320: =CONCATENATE(A320, " with +",Q320, ", +", 100*round(R320,3), "% (",P320, " to ",D320,")") -> Fancy Guitar with +283, +8.4% (3374 to 3657) | U320: 879 | V320: =E320-U320 -> 213 | W320: =V320/U320 -> 0.24232082 | X320: =CONCATENATE(A320, " with +",V320, ", +", 100*round(W320,3), "% (",U320, " to ",E320,")") -> Fancy Guitar with +213, +24.2% (879 to 1092)
A321: Mystic Ring | B321: 195 | C321: 15337 | D321: 6767 | E321: 1090 | F321: 1014713 | H321: =VLOOKUP(A321,'Kings Ratings'!$A$2:$B$1000,2,false) -> 4 | I321: 297 | K321: 14270 | L321: =C321-K321 -> 1067 | M321: =L321/K321 -> 0.074772249 | N321: =CONCATENATE(A321, " with +",L321, ", +", 100*round(M321,3), "% (",K321, " to ",C321,")") -> Mystic Ring with +1067, +7.5% (14270 to 15337) | P321: 6180 | Q321: =D321-P321 -> 587 | R321: =Q321/P321 -> 0.094983819 | S321: =CONCATENATE(A321, " with +",Q321, ", +", 100*round(R321,3), "% (",P321, " to ",D321,")") -> Mystic Ring with +587, +9.5% (6180 to 6767) | U321: 899 | V321: =E321-U321 -> 191 | W321: =V321/U321 -> 0.21245829 | X321: =CONCATENATE(A321, " with +",V321, ", +", 100*round(W321,3), "% (",U321, " to ",E321,")") -> Mystic Ring with +191, +21.2% (899 to 1090)
A322: Green Diary | B322: 82 | C322: 15031 | D322: 8233 | E322: 1118 | F322: 1058174 | H322: =VLOOKUP(A322,'Kings Ratings'!$A$2:$B$1000,2,false) -> 2 | K322: 14119 | L322: =C322-K322 -> 912 | M322: =L322/K322 -> 0.06459381 | N322: =CONCATENATE(A322, " with +",L322, ", +", 100*round(M322,3), "% (",K322, " to ",C322,")") -> Green Diary with +912, +6.5% (14119 to 15031) | P322: 7616 | Q322: =D322-P322 -> 617 | R322: =Q322/P322 -> 0.081013655 | S322: =CONCATENATE(A322, " with +",Q322, ", +", 100*round(R322,3), "% (",P322, " to ",D322,")") -> Green Diary with +617, +8.1% (7616 to 8233) | U322: 906 | V322: =E322-U322 -> 212 | W322: =V322/U322 -> 0.23399559 | X322: =CONCATENATE(A322, " with +",V322, ", +", 100*round(W322,3), "% (",U322, " to ",E322,")") -> Green Diary with +212, +23.4% (906 to 1118)
A323: Toxic Tendrils | B323: 1374 | C323: 2425 | D323: 2284 | E323: 1603 | F323: 361834 | H323: =VLOOKUP(A323,'Kings Ratings'!$A$2:$B$1000,2,false) -> 4 | K323: 1725 | L323: =C323-K323 -> 700 | M323: =L323/K323 -> 0.4057971 | N323: =CONCATENATE(A323, " with +",L323, ", +", 100*round(M323,3), "% (",K323, " to ",C323,")") -> Toxic Tendrils with +700, +40.6% (1725 to 2425) | P323: 1530 | Q323: =D323-P323 -> 754 | R323: =Q323/P323 -> 0.49281046 | S323: =CONCATENATE(A323, " with +",Q323, ", +", 100*round(R323,3), "% (",P323, " to ",D323,")") -> Toxic Tendrils with +754, +49.3% (1530 to 2284) | U323: 925 | V323: =E323-U323 -> 678 | W323: =V323/U323 -> 0.73297297 | X323: =CONCATENATE(A323, " with +",V323, ", +", 100*round(W323,3), "% (",U323, " to ",E323,")") -> Toxic Tendrils with +678, +73.3% (925 to 1603)
A324: Green Twine | B324: 976 | C324: 10765 | D324: 5157 | E324: 1251 | F324: 1063254 | H324: =VLOOKUP(A324,'Kings Ratings'!$A$2:$B$1000,2,false) -> 2 | I324: 292 | K324: 9966 | L324: =C324-K324 -> 799 | M324: =L324/K324 -> 0.080172587 | N324: =CONCATENATE(A324, " with +",L324, ", +", 100*round(M324,3), "% (",K324, " to ",C324,")") -> Green Twine with +799, +8% (9966 to 10765) | P324: 4576 | Q324: =D324-P324 -> 581 | R324: =Q324/P324 -> 0.12696678 | S324: =CONCATENATE(A324, " with +",Q324, ", +", 100*round(R324,3), "% (",P324, " to ",D324,")") -> Green Twine with +581, +12.7% (4576 to 5157) | U324: 967 | V324: =E324-U324 -> 284 | W324: =V324/U324 -> 0.29369183 | X324: =CONCATENATE(A324, " with +",V324, ", +", 100*round(W324,3), "% (",U324, " to ",E324,")") -> Green Twine with +284, +29.4% (967 to 1251)
A325: Hourglass | B325: 388 | C325: 12382 | D325: 4247 | E325: 1204 | F325: 1014474 | H325: =VLOOKUP(A325,'Kings Ratings'!$A$2:$B$1000,2,false) -> 5 | I325: 298 | K325: 11507 | L325: =C325-K325 -> 875 | M325: =L325/K325 -> 0.076040671 | N325: =CONCATENATE(A325, " with +",L325, ", +", 100*round(M325,3), "% (",K325, " to ",C325,")") -> Hourglass with +875, +7.6% (11507 to 12382) | P325: 3911 | Q325: =D325-P325 -> 336 | R325: =Q325/P325 -> 0.085911532 | S325: =CONCATENATE(A325, " with +",Q325, ", +", 100*round(R325,3), "% (",P325, " to ",D325,")") -> Hourglass with +336, +8.6% (3911 to 4247) | U325: 968 | V325: =E325-U325 -> 236 | W325: =V325/U325 -> 0.24380165 | X325: =CONCATENATE(A325, " with +",V325, ", +", 100*round(W325,3), "% (",U325, " to ",E325,")") -> Hourglass with +236, +24.4% (968 to 1204)
A326: Green Scarf | B326: 414 | C326: 14011 | D326: 6176 | E326: 1227 | F326: 1127282 | H326: =VLOOKUP(A326,'Kings Ratings'!$A$2:$B$1000,2,false) -> 2 | I326: 293 | K326: 13150 | L326: =C326-K326 -> 861 | M326: =L326/K326 -> 0.065475285 | N326: =CONCATENATE(A326, " with +",L326, ", +", 100*round(M326,3), "% (",K326, " to ",C326,")") -> Green Scarf with +861, +6.5% (13150 to 14011) | P326: 5712 | Q326: =D326-P326 -> 464 | R326: =Q326/P326 -> 0.081232493 | S326: =CONCATENATE(A326, " with +",Q326, ", +", 100*round(R326,3), "% (",P326, " to ",D326,")") -> Green Scarf with +464, +8.1% (5712 to 6176) | U326: 983 | V326: =E326-U326 -> 244 | W326: =V326/U326 -> 0.24821974 | X326: =CONCATENATE(A326, " with +",V326, ", +", 100*round(W326,3), "% (",U326, " to ",E326,")") -> Green Scarf with +244, +24.8% (983 to 1227)
A327: Beet | B327: 450 | C327: 24028 | D327: 8275 | E327: 1212 | F327: 1003694 | H327: =VLOOKUP(A327,'Kings Ratings'!$A$2:$B$1000,2,false) -> 5 | I327: 296 | K327: 22738 | L327: =C327-K327 -> 1290 | M327: =L327/K327 -> 0.056733222 | N327: =CONCATENATE(A327, " with +",L327, ", +", 100*round(M327,3), "% (",K327, " to ",C327,")") -> Beet with +1290, +5.7% (22738 to 24028) | P327: 7649 | Q327: =D327-P327 -> 626 | R327: =Q327/P327 -> 0.081840763 | S327: =CONCATENATE(A327, " with +",Q327, ", +", 100*round(R327,3), "% (",P327, " to ",D327,")") -> Beet with +626, +8.2% (7649 to 8275) | U327: 1036 | V327: =E327-U327 -> 176 | W327: =V327/U327 -> 0.16988417 | X327: =CONCATENATE(A327, " with +",V327, ", +", 100*round(W327,3), "% (",U327, " to ",E327,")") -> Beet with +176, +17% (1036 to 1212)
A328: Glass Eye Urchin | B328: 1368 | C328: 2430 | D328: 2328 | E328: 1778 | F328: 480662 | H328: =VLOOKUP(A328,'Kings Ratings'!$A$2:$B$1000,2,false) -> 4 | K328: 1740 | L328: =C328-K328 -> 690 | M328: =L328/K328 -> 0.39655172 | N328: =CONCATENATE(A328, " with +",L328, ", +", 100*round(M328,3), "% (",K328, " to ",C328,")") -> Glass Eye Urchin with +690, +39.7% (1740 to 2430) | P328: 1581 | Q328: =D328-P328 -> 747 | R328: =Q328/P328 -> 0.47248577 | S328: =CONCATENATE(A328, " with +",Q328, ", +", 100*round(R328,3), "% (",P328, " to ",D328,")") -> Glass Eye Urchin with +747, +47.2% (1581 to 2328) | U328: 1078 | V328: =E328-U328 -> 700 | W328: =V328/U328 -> 0.64935065 | X328: =CONCATENATE(A328, " with +",V328, ", +", 100*round(W328,3), "% (",U328, " to ",E328,")") -> Glass Eye Urchin with +700, +64.9% (1078 to 1778)
A329: Slobster | B329: 1370 | C329: 2436 | D329: 2344 | E329: 1851 | F329: 552455 | H329: =VLOOKUP(A329,'Kings Ratings'!$A$2:$B$1000,2,false) -> 4 | K329: 1743 | L329: =C329-K329 -> 693 | M329: =L329/K329 -> 0.39759036 | N329: =CONCATENATE(A329, " with +",L329, ", +", 100*round(M329,3), "% (",K329, " to ",C329,")") -> Slobster with +693, +39.8% (1743 to 2436) | P329: 1598 | Q329: =D329-P329 -> 746 | R329: =Q329/P329 -> 0.46683354 | S329: =CONCATENATE(A329, " with +",Q329, ", +", 100*round(R329,3), "% (",P329, " to ",D329,")") -> Slobster with +746, +46.7% (1598 to 2344) | U329: 1128 | V329: =E329-U329 -> 723 | W329: =V329/U329 -> 0.64095745 | X329: =CONCATENATE(A329, " with +",V329, ", +", 100*round(W329,3), "% (",U329, " to ",E329,")") -> Slobster with +723, +64.1% (1128 to 1851)
A330: Slime Egg Shell | B330: 1371 | C330: 2437 | D330: 2348 | E330: 1879 | F330: 597506 | H330: =VLOOKUP(A330,'Kings Ratings'!$A$2:$B$1000,2,false) -> 4 | K330: 1748 | L330: =C330-K330 -> 689 | M330: =L330/K330 -> 0.39416476 | N330: =CONCATENATE(A330, " with +",L330, ", +", 100*round(M330,3), "% (",K330, " to ",C330,")") -> Slime Egg Shell with +689, +39.4% (1748 to 2437) | P330: 1605 | Q330: =D330-P330 -> 743 | R330: =Q330/P330 -> 0.46292835 | S330: =CONCATENATE(A330, " with +",Q330, ", +", 100*round(R330,3), "% (",P330, " to ",D330,")") -> Slime Egg Shell with +743, +46.3% (1605 to 2348) | U330: 1155 | V330: =E330-U330 -> 724 | W330: =V330/U330 -> 0.62683983 | X330: =CONCATENATE(A330, " with +",V330, ", +", 100*round(W330,3), "% (",U330, " to ",E330,")") -> Slime Egg Shell with +724, +62.7% (1155 to 1879)
A331: Pickaxe | B331: 820 | C331: 10435 | D331: 4089 | E331: 1453 | F331: 1606439 | H331: =VLOOKUP(A331,'Kings Ratings'!$A$2:$B$1000,2,false) -> 9 | I331: 294 | K331: 9197 | L331: =C331-K331 -> 1238 | M331: =L331/K331 -> 0.13460911 | N331: =CONCATENATE(A331, " with +",L331, ", +", 100*round(M331,3), "% (",K331, " to ",C331,")") -> Pickaxe with +1238, +13.5% (9197 to 10435) | P331: 3514 | Q331: =D331-P331 -> 575 | R331: =Q331/P331 -> 0.16363119 | S331: =CONCATENATE(A331, " with +",Q331, ", +", 100*round(R331,3), "% (",P331, " to ",D331,")") -> Pickaxe with +575, +16.4% (3514 to 4089) | U331: 1196 | V331: =E331-U331 -> 257 | W331: =V331/U331 -> 0.21488294 | X331: =CONCATENATE(A331, " with +",V331, ", +", 100*round(W331,3), "% (",U331, " to ",E331,")") -> Pickaxe with +257, +21.5% (1196 to 1453)
A332: Boghead Snapper | B332: 1372 | C332: 2444 | D332: 2365 | E332: 1937 | F332: 713536 | H332: =VLOOKUP(A332,'Kings Ratings'!$A$2:$B$1000,2,false) -> 4 | K332: 1755 | L332: =C332-K332 -> 689 | M332: =L332/K332 -> 0.39259259 | N332: =CONCATENATE(A332, " with +",L332, ", +", 100*round(M332,3), "% (",K332, " to ",C332,")") -> Boghead Snapper with +689, +39.3% (1755 to 2444) | P332: 1626 | Q332: =D332-P332 -> 739 | R332: =Q332/P332 -> 0.45448954 | S332: =CONCATENATE(A332, " with +",Q332, ", +", 100*round(R332,3), "% (",P332, " to ",D332,")") -> Boghead Snapper with +739, +45.4% (1626 to 2365) | U332: 1208 | V332: =E332-U332 -> 729 | W332: =V332/U332 -> 0.60347682 | X332: =CONCATENATE(A332, " with +",V332, ", +", 100*round(W332,3), "% (",U332, " to ",E332,")") -> Boghead Snapper with +729, +60.3% (1208 to 1937)
A333: Blubberfish | B333: 1385 | C333: 2444 | D333: 2365 | E333: 1937 | F333: 714758 | H333: =VLOOKUP(A333,'Kings Ratings'!$A$2:$B$1000,2,false) -> 4 | K333: 1754 | L333: =C333-K333 -> 690 | M333: =L333/K333 -> 0.39338654 | N333: =CONCATENATE(A333, " with +",L333, ", +", 100*round(M333,3), "% (",K333, " to ",C333,")") -> Blubberfish with +690, +39.3% (1754 to 2444) | P333: 1626 | Q333: =D333-P333 -> 739 | R333: =Q333/P333 -> 0.45448954 | S333: =CONCATENATE(A333, " with +",Q333, ", +", 100*round(R333,3), "% (",P333, " to ",D333,")") -> Blubberfish with +739, +45.4% (1626 to 2365) | U333: 1208 | V333: =E333-U333 -> 729 | W333: =V333/U333 -> 0.60347682 | X333: =CONCATENATE(A333, " with +",V333, ", +", 100*round(W333,3), "% (",U333, " to ",E333,")") -> Blubberfish with +729, +60.3% (1208 to 1937)
A334: Horn Canteen | B334: 165 | C334: 13865 | D334: 6070 | E334: 1435 | F334: 1136102 | H334: =VLOOKUP(A334,'Kings Ratings'!$A$2:$B$1000,2,false) -> 3 | I334: 297 | K334: 13016 | L334: =C334-K334 -> 849 | M334: =L334/K334 -> 0.065227412 | N334: =CONCATENATE(A334, " with +",L334, ", +", 100*round(M334,3), "% (",K334, " to ",C334,")") -> Horn Canteen with +849, +6.5% (13016 to 13865) | P334: 5657 | Q334: =D334-P334 -> 413 | R334: =Q334/P334 -> 0.073006894 | S334: =CONCATENATE(A334, " with +",Q334, ", +", 100*round(R334,3), "% (",P334, " to ",D334,")") -> Horn Canteen with +413, +7.3% (5657 to 6070) | U334: 1220 | V334: =E334-U334 -> 215 | W334: =V334/U334 -> 0.17622951 | X334: =CONCATENATE(A334, " with +",V334, ", +", 100*round(W334,3), "% (",U334, " to ",E334,")") -> Horn Canteen with +215, +17.6% (1220 to 1435)
A335: Reaver Claw | B335: 1375 | C335: 2445 | D335: 2370 | E335: 1956 | F335: 792176 | H335: =VLOOKUP(A335,'Kings Ratings'!$A$2:$B$1000,2,false) -> 4 | K335: 1760 | L335: =C335-K335 -> 685 | M335: =L335/K335 -> 0.38920455 | N335: =CONCATENATE(A335, " with +",L335, ", +", 100*round(M335,3), "% (",K335, " to ",C335,")") -> Reaver Claw with +685, +38.9% (1760 to 2445) | P335: 1635 | Q335: =D335-P335 -> 735 | R335: =Q335/P335 -> 0.44954128 | S335: =CONCATENATE(A335, " with +",Q335, ", +", 100*round(R335,3), "% (",P335, " to ",D335,")") -> Reaver Claw with +735, +45% (1635 to 2370) | U335: 1224 | V335: =E335-U335 -> 732 | W335: =V335/U335 -> 0.59803922 | X335: =CONCATENATE(A335, " with +",V335, ", +", 100*round(W335,3), "% (",U335, " to ",E335,")") -> Reaver Claw with +732, +59.8% (1224 to 1956)
A336: Glass Jar | B336: 1094 | C336: 8944 | D336: 2914 | E336: 1491 | F336: 1057009 | H336: =VLOOKUP(A336,'Kings Ratings'!$A$2:$B$1000,2,false) -> 10 | I336: 287 | K336: 8167 | L336: =C336-K336 -> 777 | M336: =L336/K336 -> 0.095138974 | N336: =CONCATENATE(A336, " with +",L336, ", +", 100*round(M336,3), "% (",K336, " to ",C336,")") -> Glass Jar with +777, +9.5% (8167 to 8944) | P336: 2534 | Q336: =D336-P336 -> 380 | R336: =Q336/P336 -> 0.14996054 | S336: =CONCATENATE(A336, " with +",Q336, ", +", 100*round(R336,3), "% (",P336, " to ",D336,")") -> Glass Jar with +380, +15% (2534 to 2914) | U336: 1225 | V336: =E336-U336 -> 266 | W336: =V336/U336 -> 0.21714286 | X336: =CONCATENATE(A336, " with +",V336, ", +", 100*round(W336,3), "% (",U336, " to ",E336,")") -> Glass Jar with +266, +21.7% (1225 to 1491)
A337: Wooden Bow | B337: 455 | C337: 11860 | D337: 5779 | E337: 1539 | F337: 1037303 | H337: =VLOOKUP(A337,'Kings Ratings'!$A$2:$B$1000,2,false) -> 2 | I337: 291 | K337: 10928 | L337: =C337-K337 -> 932 | M337: =L337/K337 -> 0.085285505 | N337: =CONCATENATE(A337, " with +",L337, ", +", 100*round(M337,3), "% (",K337, " to ",C337,")") -> Wooden Bow with +932, +8.5% (10928 to 11860) | P337: 5349 | Q337: =D337-P337 -> 430 | R337: =Q337/P337 -> 0.080388858 | S337: =CONCATENATE(A337, " with +",Q337, ", +", 100*round(R337,3), "% (",P337, " to ",D337,")") -> Wooden Bow with +430, +8% (5349 to 5779) | U337: 1239 | V337: =E337-U337 -> 300 | W337: =V337/U337 -> 0.24213075 | X337: =CONCATENATE(A337, " with +",V337, ", +", 100*round(W337,3), "% (",U337, " to ",E337,")") -> Wooden Bow with +300, +24.2% (1239 to 1539)
A338: Pitchfork | B338: 900 | C338: 9072 | D338: 2809 | E338: 1517 | F338: 1043666 | H338: =VLOOKUP(A338,'Kings Ratings'!$A$2:$B$1000,2,false) -> 2 | I338: 290 | K338: 8171 | L338: =C338-K338 -> 901 | M338: =L338/K338 -> 0.11026802 | N338: =CONCATENATE(A338, " with +",L338, ", +", 100*round(M338,3), "% (",K338, " to ",C338,")") -> Pitchfork with +901, +11% (8171 to 9072) | P338: 2437 | Q338: =D338-P338 -> 372 | R338: =Q338/P338 -> 0.1526467 | S338: =CONCATENATE(A338, " with +",Q338, ", +", 100*round(R338,3), "% (",P338, " to ",D338,")") -> Pitchfork with +372, +15.3% (2437 to 2809) | U338: 1252 | V338: =E338-U338 -> 265 | W338: =V338/U338 -> 0.21166134 | X338: =CONCATENATE(A338, " with +",V338, ", +", 100*round(W338,3), "% (",U338, " to ",E338,")") -> Pitchfork with +265, +21.2% (1252 to 1517)
A339: Magenta Growth | B339: 1373 | C339: 2450 | D339: 2384 | E339: 2035 | F339: 1009984 | H339: =VLOOKUP(A339,'Kings Ratings'!$A$2:$B$1000,2,false) -> 4 | K339: 1766 | L339: =C339-K339 -> 684 | M339: =L339/K339 -> 0.38731597 | N339: =CONCATENATE(A339, " with +",L339, ", +", 100*round(M339,3), "% (",K339, " to ",C339,")") -> Magenta Growth with +684, +38.7% (1766 to 2450) | P339: 1654 | Q339: =D339-P339 -> 730 | R339: =Q339/P339 -> 0.44135429 | S339: =CONCATENATE(A339, " with +",Q339, ", +", 100*round(R339,3), "% (",P339, " to ",D339,")") -> Magenta Growth with +730, +44.1% (1654 to 2384) | U339: 1284 | V339: =E339-U339 -> 751 | W339: =V339/U339 -> 0.58489097 | X339: =CONCATENATE(A339, " with +",V339, ", +", 100*round(W339,3), "% (",U339, " to ",E339,")") -> Magenta Growth with +751, +58.5% (1284 to 2035)
A340: Frozen Spyfish | B340: 944 | C340: 16594 | D340: 8256 | E340: 1291 | F340: 2195884 | H340: =VLOOKUP(A340,'Kings Ratings'!$A$2:$B$1000,2,false) -> 11 | K340: 16593 | L340: =C340-K340 -> 1 | M340: =L340/K340 -> 6.0266377e-05 | N340: =CONCATENATE(A340, " with +",L340, ", +", 100*round(M340,3), "% (",K340, " to ",C340,")") -> Frozen Spyfish with +1, +0% (16593 to 16594) | P340: 8250 | Q340: =D340-P340 -> 6 | R340: =Q340/P340 -> 0.00072727273 | S340: =CONCATENATE(A340, " with +",Q340, ", +", 100*round(R340,3), "% (",P340, " to ",D340,")") -> Frozen Spyfish with +6, +0.1% (8250 to 8256) | U340: 1290 | V340: =E340-U340 -> 1 | W340: =V340/U340 -> 0.0007751938 | X340: =CONCATENATE(A340, " with +",V340, ", +", 100*round(W340,3), "% (",U340, " to ",E340,")") -> Frozen Spyfish with +1, +0.1% (1290 to 1291)
A341: Bog Barnacle | B341: 1376 | C341: 2451 | D341: 2391 | E341: 2081 | F341: 1176285 | H341: =VLOOKUP(A341,'Kings Ratings'!$A$2:$B$1000,2,false) -> 4 | K341: 1767 | L341: =C341-K341 -> 684 | M341: =L341/K341 -> 0.38709677 | N341: =CONCATENATE(A341, " with +",L341, ", +", 100*round(M341,3), "% (",K341, " to ",C341,")") -> Bog Barnacle with +684, +38.7% (1767 to 2451) | P341: 1667 | Q341: =D341-P341 -> 724 | R341: =Q341/P341 -> 0.43431314 | S341: =CONCATENATE(A341, " with +",Q341, ", +", 100*round(R341,3), "% (",P341, " to ",D341,")") -> Bog Barnacle with +724, +43.4% (1667 to 2391) | U341: 1311 | V341: =E341-U341 -> 770 | W341: =V341/U341 -> 0.58733791 | X341: =CONCATENATE(A341, " with +",V341, ", +", 100*round(W341,3), "% (",U341, " to ",E341,")") -> Bog Barnacle with +770, +58.7% (1311 to 2081)
A342: Splatfish | B342: 1369 | C342: 2450 | D342: 2391 | E342: 2081 | F342: 1175479 | H342: =VLOOKUP(A342,'Kings Ratings'!$A$2:$B$1000,2,false) -> 4 | K342: 1767 | L342: =C342-K342 -> 683 | M342: =L342/K342 -> 0.38653084 | N342: =CONCATENATE(A342, " with +",L342, ", +", 100*round(M342,3), "% (",K342, " to ",C342,")") -> Splatfish with +683, +38.7% (1767 to 2450) | P342: 1667 | Q342: =D342-P342 -> 724 | R342: =Q342/P342 -> 0.43431314 | S342: =CONCATENATE(A342, " with +",Q342, ", +", 100*round(R342,3), "% (",P342, " to ",D342,")") -> Splatfish with +724, +43.4% (1667 to 2391) | U342: 1311 | V342: =E342-U342 -> 770 | W342: =V342/U342 -> 0.58733791 | X342: =CONCATENATE(A342, " with +",V342, ", +", 100*round(W342,3), "% (",U342, " to ",E342,")") -> Splatfish with +770, +58.7% (1311 to 2081)
A343: Red Dye | B343: 536 | C343: 24416 | D343: 11464 | E343: 1609 | F343: 1372250 | H343: =VLOOKUP(A343,'Kings Ratings'!$A$2:$B$1000,2,false) -> 3 | I343: 296 | K343: 22727 | L343: =C343-K343 -> 1689 | M343: =L343/K343 -> 0.074316892 | N343: =CONCATENATE(A343, " with +",L343, ", +", 100*round(M343,3), "% (",K343, " to ",C343,")") -> Red Dye with +1689, +7.4% (22727 to 24416) | P343: 10614 | Q343: =D343-P343 -> 850 | R343: =Q343/P343 -> 0.080082909 | S343: =CONCATENATE(A343, " with +",Q343, ", +", 100*round(R343,3), "% (",P343, " to ",D343,")") -> Red Dye with +850, +8% (10614 to 11464) | U343: 1333 | V343: =E343-U343 -> 276 | W343: =V343/U343 -> 0.20705176 | X343: =CONCATENATE(A343, " with +",V343, ", +", 100*round(W343,3), "% (",U343, " to ",E343,")") -> Red Dye with +276, +20.7% (1333 to 1609)
A344: Leather Diary | B344: 118 | C344: 18508 | D344: 9657 | E344: 1656 | F344: 1495569 | H344: =VLOOKUP(A344,'Kings Ratings'!$A$2:$B$1000,2,false) -> 2 | I344: 292 | K344: 17514 | L344: =C344-K344 -> 994 | M344: =L344/K344 -> 0.056754596 | N344: =CONCATENATE(A344, " with +",L344, ", +", 100*round(M344,3), "% (",K344, " to ",C344,")") -> Leather Diary with +994, +5.7% (17514 to 18508) | P344: 8912 | Q344: =D344-P344 -> 745 | R344: =Q344/P344 -> 0.083595153 | S344: =CONCATENATE(A344, " with +",Q344, ", +", 100*round(R344,3), "% (",P344, " to ",D344,")") -> Leather Diary with +745, +8.4% (8912 to 9657) | U344: 1352 | V344: =E344-U344 -> 304 | W344: =V344/U344 -> 0.22485207 | X344: =CONCATENATE(A344, " with +",V344, ", +", 100*round(W344,3), "% (",U344, " to ",E344,")") -> Leather Diary with +304, +22.5% (1352 to 1656)
A345: Green Shield | B345: 204 | C345: 16739 | D345: 8342 | E345: 1689 | F345: 1047558 | H345: =VLOOKUP(A345,'Kings Ratings'!$A$2:$B$1000,2,false) -> 2 | I345: 291 | K345: 15669 | L345: =C345-K345 -> 1070 | M345: =L345/K345 -> 0.068287702 | N345: =CONCATENATE(A345, " with +",L345, ", +", 100*round(M345,3), "% (",K345, " to ",C345,")") -> Green Shield with +1070, +6.8% (15669 to 16739) | P345: 7745 | Q345: =D345-P345 -> 597 | R345: =Q345/P345 -> 0.077081988 | S345: =CONCATENATE(A345, " with +",Q345, ", +", 100*round(R345,3), "% (",P345, " to ",D345,")") -> Green Shield with +597, +7.7% (7745 to 8342) | U345: 1396 | V345: =E345-U345 -> 293 | W345: =V345/U345 -> 0.20988539 | X345: =CONCATENATE(A345, " with +",V345, ", +", 100*round(W345,3), "% (",U345, " to ",E345,")") -> Green Shield with +293, +21% (1396 to 1689)
A346: Slimeback | B346: 1367 | C346: 2454 | D346: 2408 | E346: 2177 | F346: 1749329 | H346: =VLOOKUP(A346,'Kings Ratings'!$A$2:$B$1000,2,false) -> 4 | K346: 1775 | L346: =C346-K346 -> 679 | M346: =L346/K346 -> 0.38253521 | N346: =CONCATENATE(A346, " with +",L346, ", +", 100*round(M346,3), "% (",K346, " to ",C346,")") -> Slimeback with +679, +38.3% (1775 to 2454) | P346: 1690 | Q346: =D346-P346 -> 718 | R346: =Q346/P346 -> 0.42485207 | S346: =CONCATENATE(A346, " with +",Q346, ", +", 100*round(R346,3), "% (",P346, " to ",D346,")") -> Slimeback with +718, +42.5% (1690 to 2408) | U346: 1403 | V346: =E346-U346 -> 774 | W346: =V346/U346 -> 0.55167498 | X346: =CONCATENATE(A346, " with +",V346, ", +", 100*round(W346,3), "% (",U346, " to ",E346,")") -> Slimeback with +774, +55.2% (1403 to 2177)
A347: Gold Cucumber | B347: 189 | C347: 19493 | D347: 8001 | E347: 1579 | F347: 4087249 | H347: =VLOOKUP(A347,'Kings Ratings'!$A$2:$B$1000,2,false) -> 8 | K347: 18378 | L347: =C347-K347 -> 1115 | M347: =L347/K347 -> 0.060670367 | N347: =CONCATENATE(A347, " with +",L347, ", +", 100*round(M347,3), "% (",K347, " to ",C347,")") -> Gold Cucumber with +1115, +6.1% (18378 to 19493) | P347: 7372 | Q347: =D347-P347 -> 629 | R347: =Q347/P347 -> 0.085322843 | S347: =CONCATENATE(A347, " with +",Q347, ", +", 100*round(R347,3), "% (",P347, " to ",D347,")") -> Gold Cucumber with +629, +8.5% (7372 to 8001) | U347: 1426 | V347: =E347-U347 -> 153 | W347: =V347/U347 -> 0.10729313 | X347: =CONCATENATE(A347, " with +",V347, ", +", 100*round(W347,3), "% (",U347, " to ",E347,")") -> Gold Cucumber with +153, +10.7% (1426 to 1579)
A348: Essence of Slime | B348: 492 | C348: 20414 | D348: 9516 | E348: 1792 | F348: 1048906 | H348: =VLOOKUP(A348,'Kings Ratings'!$A$2:$B$1000,2,false) -> 3 | I348: 298 | K348: 19098 | L348: =C348-K348 -> 1316 | M348: =L348/K348 -> 0.068907739 | N348: =CONCATENATE(A348, " with +",L348, ", +", 100*round(M348,3), "% (",K348, " to ",C348,")") -> Essence of Slime with +1316, +6.9% (19098 to 20414) | P348: 8753 | Q348: =D348-P348 -> 763 | R348: =Q348/P348 -> 0.087170113 | S348: =CONCATENATE(A348, " with +",Q348, ", +", 100*round(R348,3), "% (",P348, " to ",D348,")") -> Essence of Slime with +763, +8.7% (8753 to 9516) | U348: 1498 | V348: =E348-U348 -> 294 | W348: =V348/U348 -> 0.19626168 | X348: =CONCATENATE(A348, " with +",V348, ", +", 100*round(W348,3), "% (",U348, " to ",E348,")") -> Essence of Slime with +294, +19.6% (1498 to 1792)
A349: Coin Purse | B349: 122 | C349: 23007 | D349: 11659 | E349: 1799 | F349: 1425230 | H349: =VLOOKUP(A349,'Kings Ratings'!$A$2:$B$1000,2,false) -> 5 | I349: 293 | K349: 22147 | L349: =C349-K349 -> 860 | M349: =L349/K349 -> 0.038831444 | N349: =CONCATENATE(A349, " with +",L349, ", +", 100*round(M349,3), "% (",K349, " to ",C349,")") -> Coin Purse with +860, +3.9% (22147 to 23007) | P349: 10882 | Q349: =D349-P349 -> 777 | R349: =Q349/P349 -> 0.071402316 | S349: =CONCATENATE(A349, " with +",Q349, ", +", 100*round(R349,3), "% (",P349, " to ",D349,")") -> Coin Purse with +777, +7.1% (10882 to 11659) | U349: 1510 | V349: =E349-U349 -> 289 | W349: =V349/U349 -> 0.19139073 | X349: =CONCATENATE(A349, " with +",V349, ", +", 100*round(W349,3), "% (",U349, " to ",E349,")") -> Coin Purse with +289, +19.1% (1510 to 1799)
A350: Jade Charm | B350: 265 | C350: 15294 | D350: 6959 | E350: 1799 | F350: 1033439 | H350: =VLOOKUP(A350,'Kings Ratings'!$A$2:$B$1000,2,false) -> 5 | I350: 299 | K350: 14285 | L350: =C350-K350 -> 1009 | M350: =L350/K350 -> 0.070633532 | N350: =CONCATENATE(A350, " with +",L350, ", +", 100*round(M350,3), "% (",K350, " to ",C350,")") -> Jade Charm with +1009, +7.1% (14285 to 15294) | P350: 6421 | Q350: =D350-P350 -> 538 | R350: =Q350/P350 -> 0.083787572 | S350: =CONCATENATE(A350, " with +",Q350, ", +", 100*round(R350,3), "% (",P350, " to ",D350,")") -> Jade Charm with +538, +8.4% (6421 to 6959) | U350: 1534 | V350: =E350-U350 -> 265 | W350: =V350/U350 -> 0.17275098 | X350: =CONCATENATE(A350, " with +",V350, ", +", 100*round(W350,3), "% (",U350, " to ",E350,")") -> Jade Charm with +265, +17.3% (1534 to 1799)
A351: Green Parchment | B351: 74 | C351: 19204 | D351: 10567 | E351: 1851 | F351: 1273344 | H351: =VLOOKUP(A351,'Kings Ratings'!$A$2:$B$1000,2,false) -> 1 | I351: 297 | K351: 17996 | L351: =C351-K351 -> 1208 | M351: =L351/K351 -> 0.067126028 | N351: =CONCATENATE(A351, " with +",L351, ", +", 100*round(M351,3), "% (",K351, " to ",C351,")") -> Green Parchment with +1208, +6.7% (17996 to 19204) | P351: 9709 | Q351: =D351-P351 -> 858 | R351: =Q351/P351 -> 0.088371614 | S351: =CONCATENATE(A351, " with +",Q351, ", +", 100*round(R351,3), "% (",P351, " to ",D351,")") -> Green Parchment with +858, +8.8% (9709 to 10567) | U351: 1561 | V351: =E351-U351 -> 290 | W351: =V351/U351 -> 0.18577835 | X351: =CONCATENATE(A351, " with +",V351, ", +", 100*round(W351,3), "% (",U351, " to ",E351,")") -> Green Parchment with +290, +18.6% (1561 to 1851)
